Workbook

Sheet LIST HPP
A1: LIST HARGA POKOK PENJUALAN
A4: No. | B4: Nama Produk | C4: HPP
A5: 1 | B5: Matcha Latte | C5: 8805.63
A6: 2 | B6: Hojicha Latte | C6: 8150.63
A7: 3 | B7: Choco Latte | C7: 6013.63
A8: 4 | B8: Matcha Tea | C8: 3748.21
A9: 5 | B9: Ice Tea | C9: 1448.63
A10: 6 | B10: Gyumeshi | C10: 11670
A11: 7 | B11: Karage Don | C11: 9350.16
A12: 8 | B12: Hot Honey Karage Don | C12: 9990.16
A13: 9 | B13: Chicken Katsu Don | C13: 7445.2
A14: 10 | B14: Gyuniku Ala Carte | C14: 17260
A15: 11 | B15: Karage Ala Carte | C15: 14155
A16: 12 | B16: Hot Honey Karage Ala Carte | C16: 15435
... A35: 31 | B35: Gyuniku Bento | C35: 14616.31

Sheet MASTERFILE
A1: PLATFORM | B1: Tanggal | C1: Nama Item | D1: HPP | E1: Jumlah | F1: Jumlah QR | G1: Total Jumlah | H1: Total | I1: Total HPP | J1: Uang Masuk | K1: Margin | L1: Gross Profit
A2: SHOPEE | C2: Matcha Latte | D2: =VLOOKUP(C2, 'LIST HPP'!$B$4:$C$39, 2, ) -> 8805.63 | G2: =sum(E2:F2) -> 0 | H2: =D2*G2 -> 0 | I2: =sum(H2:H32) -> 0 | K2: =(J2-I2)/J2 -> #DIV/0! | L2: =J2-I2 -> 0
C3: Hojicha Latte | D3: =VLOOKUP(C3, 'LIST HPP'!$B$4:$C$39, 2, ) -> 8150.63 | G3: =sum(E3:F3) -> 0 | H3: =D3*G3 -> 0
C4: Choco Latte | D4: =VLOOKUP(C4, 'LIST HPP'!$B$4:$C$39, 2, ) -> 6013.63 | G4: =sum(E4:F4) -> 0 | H4: =D4*G4 -> 0
C5: Choco Ichigo Latte | D5: =VLOOKUP(C5, 'LIST HPP'!$B$4:$C$39, 2, ) -> 7131.43 | G5: =sum(E5:F5) -> 0 | H5: =D5*G5 -> 0
C6: Matcha Tea | D6: =VLOOKUP(C6, 'LIST HPP'!$B$4:$C$39, 2, ) -> 3748.21 | G6: =sum(E6:F6) -> 0 | H6: =D6*G6 -> 0
C7: Ice Tea | D7: =VLOOKUP(C7, 'LIST HPP'!$B$4:$C$39, 2, ) -> 1448.63 | G7: =sum(E7:F7) -> 0 | H7: =D7*G7 -> 0
C8: Gyumeshi | D8: =VLOOKUP(C8, 'LIST HPP'!$B$4:$C$39, 2, ) -> 11670 | G8: =sum(E8:F8) -> 0 | H8: =D8*G8 -> 0
C9: Karage Don | D9: =VLOOKUP(C9, 'LIST HPP'!$B$4:$C$39, 2, ) -> 9350.16 | G9: =sum(E9:F9) -> 0 | H9: =D9*G9 -> 0
C10: Hot Honey Karage Don | D10: =VLOOKUP(C10, 'LIST HPP'!$B$4:$C$39, 2, ) -> 9990.16 | G10: =sum(E10:F10) -> 0 | H10: =D10*G10 -> 0
C11: Chicken Katsu Don | D11: =VLOOKUP(C11, 'LIST HPP'!$B$4:$C$39, 2, ) -> 7445.2 | G11: =sum(E11:F11) -> 0 | H11: =D11*G11 -> 0
C12: Gyuniku Ala Carte | D12: =VLOOKUP(C12, 'LIST HPP'!$B$4:$C$39, 2, ) -> 17260 | G12: =sum(E12:F12) -> 0 | H12: =D12*G12 -> 0
C13: Karage Ala Carte | D13: =VLOOKUP(C13, 'LIST HPP'!$B$4:$C$39, 2, ) -> 14155 | G13: =sum(E13:F13) -> 0 | H13: =D13*G13 -> 0
C14: Hot Honey Karage Ala Carte | D14: =VLOOKUP(C14, 'LIST HPP'!$B$4:$C$39, 2, ) -> 15435 | G14: =sum(E14:F14) -> 0 | H14: =D14*G14 -> 0
... C32: Gyuniku Bento | D32: =VLOOKUP(C32, 'LIST HPP'!$B$4:$C$39, 2, ) -> 14616.31 | G32: =sum(E32:F32) -> 0 | H32: =D32*G32 -> 0
A33: GRAB/ OFFLINE Q | C33: Matcha Latte | D33: =VLOOKUP(C33, 'LIST HPP'!$B$4:$C$39, 2, ) -> 8805.63 | G33: =SUM(E33:F33) -> 0 | H33: =D33*G33 -> 0 | I33: =sum(H33:H63) -> 0 | K33: =(J33-I33)/J33 -> #DIV/0! | L33: =J33-I33 -> 0
C34: Hojicha Latte | D34: =VLOOKUP(C34, 'LIST HPP'!$B$4:$C$39, 2, ) -> 8150.63 | G34: =SUM(E34:F34) -> 0 | H34: =D34*G34 -> 0
C35: Choco Latte | D35: =VLOOKUP(C35, 'LIST HPP'!$B$4:$C$39, 2, ) -> 6013.63 | G35: =SUM(E35:F35) -> 0 | H35: =D35*G35 -> 0
C36: Choco Ichigo Latte | D36: =VLOOKUP(C36, 'LIST HPP'!$B$4:$C$39, 2, ) -> 7131.43 | G36: =SUM(E36:F36) -> 0 | H36: =D36*G36 -> 0
C37: Matcha Tea | D37: =VLOOKUP(C37, 'LIST HPP'!$B$4:$C$39, 2, ) -> 3748.21 | G37: =SUM(E37:F37) -> 0 | H37: =D37*G37 -> 0
C38: Ice Tea | D38: =VLOOKUP(C38, 'LIST HPP'!$B$4:$C$39, 2, ) -> 1448.63 | G38: =SUM(E38:F38) -> 0 | H38: =D38*G38 -> 0
C39: Gyumeshi | D39: =VLOOKUP(C39, 'LIST HPP'!$B$4:$C$39, 2, ) -> 11670 | G39: =SUM(E39:F39) -> 0 | H39: =D39*G39 -> 0
C40: Karage Don | D40: =VLOOKUP(C40, 'LIST HPP'!$B$4:$C$39, 2, ) -> 9350.16 | G40: =SUM(E40:F40) -> 0 | H40: =D40*G40 -> 0
C41: Hot Honey Karage Don | D41: =VLOOKUP(C41, 'LIST HPP'!$B$4:$C$39, 2, ) -> 9990.16 | G41: =SUM(E41:F41) -> 0 | H41: =D41*G41 -> 0
C42: Chicken Katsu Don | D42: =VLOOKUP(C42, 'LIST HPP'!$B$4:$C$39, 2, ) -> 7445.2 | G42: =SUM(E42:F42) -> 0 | H42: =D42*G42 -> 0
C43: Gyuniku Ala Carte | D43: =VLOOKUP(C43, 'LIST HPP'!$B$4:$C$39, 2, ) -> 17260 | G43: =SUM(E43:F43) -> 0 | H43: =D43*G43 -> 0
C44: Karage Ala Carte | D44: =VLOOKUP(C44, 'LIST HPP'!$B$4:$C$39, 2, ) -> 14155 | G44: =SUM(E44:F44) -> 0 | H44: =D44*G44 -> 0
C45: Hot Honey Karage Ala Carte | D45: =VLOOKUP(C45, 'LIST HPP'!$B$4:$C$39, 2, ) -> 15435 | G45: =SUM(E45:F45) -> 0 | H45: =D45*G45 -> 0
... C63: Gyuniku Bento | D63: =VLOOKUP(C63, 'LIST HPP'!$B$4:$C$39, 2, ) -> 14616.31 | G63: =SUM(E63:F63) -> 0 | H63: =D63*G63 -> 0
A64: GOJEK | C64: Matcha Latte | D64: =VLOOKUP(C64, 'LIST HPP'!$B$4:$C$39, 2, ) -> 8805.63 | G64: =Sum(E64:F64) -> 0 | H64: =D64*G64 -> 0 | I64: =sum(H64:H94) -> 0 | K64: =(J64-I64)/J64 -> #DIV/0! | L64: =J64-I64 -> 0
C65: Hojicha Latte | D65: =VLOOKUP(C65, 'LIST HPP'!$B$4:$C$39, 2, ) -> 8150.63 | G65: =Sum(E65:F65) -> 0 | H65: =D65*G65 -> 0
C66: Choco Latte | D66: =VLOOKUP(C66, 'LIST HPP'!$B$4:$C$39, 2, ) -> 6013.63 | G66: =Sum(E66:F66) -> 0 | H66: =D66*G66 -> 0
C67: Choco Ichigo Latte | D67: =VLOOKUP(C67, 'LIST HPP'!$B$4:$C$39, 2, ) -> 7131.43 | G67: =Sum(E67:F67) -> 0 | H67: =D67*G67 -> 0
C68: Matcha Tea | D68: =VLOOKUP(C68, 'LIST HPP'!$B$4:$C$39, 2, ) -> 3748.21 | G68: =Sum(E68:F68) -> 0 | H68: =D68*G68 -> 0
C69: Ice Tea | D69: =VLOOKUP(C69, 'LIST HPP'!$B$4:$C$39, 2, ) -> 1448.63 | G69: =Sum(E69:F69) -> 0 | H69: =D69*G69 -> 0
C70: Gyumeshi | D70: =VLOOKUP(C70, 'LIST HPP'!$B$4:$C$39, 2, ) -> 11670 | G70: =Sum(E70:F70) -> 0 | H70: =D70*G70 -> 0
C71: Karage Don | D71: =VLOOKUP(C71, 'LIST HPP'!$B$4:$C$39, 2, ) -> 9350.16 | G71: =Sum(E71:F71) -> 0 | H71: =D71*G71 -> 0
C72: Hot Honey Karage Don | D72: =VLOOKUP(C72, 'LIST HPP'!$B$4:$C$39, 2, ) -> 9990.16 | G72: =Sum(E72:F72) -> 0 | H72: =D72*G72 -> 0
C73: Chicken Katsu Don | D73: =VLOOKUP(C73, 'LIST HPP'!$B$4:$C$39, 2, ) -> 7445.2 | G73: =Sum(E73:F73) -> 0 | H73: =D73*G73 -> 0
C74: Gyuniku Ala Carte | D74: =VLOOKUP(C74, 'LIST HPP'!$B$4:$C$39, 2, ) -> 17260 | G74: =Sum(E74:F74) -> 0 | H74: =D74*G74 -> 0
C75: Karage Ala Carte | D75: =VLOOKUP(C75, 'LIST HPP'!$B$4:$C$39, 2, ) -> 14155 | G75: =Sum(E75:F75) -> 0 | H75: =D75*G75 -> 0
C76: Hot Honey Karage Ala Carte | D76: =VLOOKUP(C76, 'LIST HPP'!$B$4:$C$39, 2, ) -> 15435 | G76: =Sum(E76:F76) -> 0 | H76: =D76*G76 -> 0
... C93: Kaarage Bento | D93: =VLOOKUP(C93, 'LIST HPP'!$B$4:$C$39, 2, ) -> 12796.31 | G93: =Sum(E93:F93) -> 0 | H93: =D93*G93 -> 0
C94: Gyuniku Bento | D94: =VLOOKUP(C94, 'LIST HPP'!$B$4:$C$39, 2, FALSE) -> 14616.31 | G94: =Sum(E94:F94) -> 0 | H94: =D94*G94 -> 0
C95: Matcha Latte | D95: =VLOOKUP(C95, 'LIST HPP'!$B$4:$C$39, 2, FALSE) -> 8805.63 | G95: =sum(E95:F95) -> 0 | H95: =D95*G95 -> 0 | I95: =sum(H95:H125) -> 0 | K95: =(J95-I95)/J95 -> #DIV/0! | L95: =J95-I95 -> 0
C96: Hojicha Latte | D96: =VLOOKUP(C96, 'LIST HPP'!$B$4:$C$39, 2, FALSE) -> 8150.63 | G96: =sum(E96:F96) -> 0 | H96: =D96*G96 -> 0
C97: Choco Latte | D97: =VLOOKUP(C97, 'LIST HPP'!$B$4:$C$39, 2, FALSE) -> 6013.63 | G97: =sum(E97:F97) -> 0 | H97: =D97*G97 -> 0
C98: Choco Ichigo Latte | D98: =VLOOKUP(C98, 'LIST HPP'!$B$4:$C$39, 2, FALSE) -> 7131.43 | G98: =sum(E98:F98) -> 0 | H98: =D98*G98 -> 0
C99: Matcha Tea | D99: =VLOOKUP(C99, 'LIST HPP'!$B$4:$C$39, 2, FALSE) -> 3748.21 | G99: =sum(E99:F99) -> 0 | H99: =D99*G99 -> 0
C100: Ice Tea | D100: =VLOOKUP(C100, 'LIST HPP'!$B$4:$C$39, 2, FALSE) -> 1448.63 | G100: =sum(E100:F100) -> 0 | H100: =D100*G100 -> 0
C101: Gyumeshi | D101: =VLOOKUP(C101, 'LIST HPP'!$B$4:$C$39, 2, FALSE) -> 11670 | G101: =sum(E101:F101) -> 0 | H101: =D101*G101 -> 0
C102: Karage Don | D102: =VLOOKUP(C102, 'LIST HPP'!$B$4:$C$39, 2, FALSE) -> 9350.16 | G102: =sum(E102:F102) -> 0 | H102: =D102*G102 -> 0
C103: Hot Honey Karage Don | D103: =VLOOKUP(C103, 'LIST HPP'!$B$4:$C$39, 2, FALSE) -> 9990.16 | G103: =sum(E103:F103) -> 0 | H103: =D103*G103 -> 0
C104: Chicken Katsu Don | D104: =VLOOKUP(C104, 'LIST HPP'!$B$4:$C$39, 2, FALSE) -> 7445.2 | G104: =sum(E104:F104) -> 0 | H104: =D104*G104 -> 0
C105: Gyuniku Ala Carte | D105: =VLOOKUP(C105, 'LIST HPP'!$B$4:$C$39, 2, FALSE) -> 17260 | G105: =sum(E105:F105) -> 0 | H105: =D105*G105 -> 0
C106: Karage Ala Carte | D106: =VLOOKUP(C106, 'LIST HPP'!$B$4:$C$39, 2, FALSE) -> 14155 | G106: =sum(E106:F106) -> 0 | H106: =D106*G106 -> 0
C107: Hot Honey Karage Ala Carte | D107: =VLOOKUP(C107, 'LIST HPP'!$B$4:$C$39, 2, FALSE) -> 15435 | G107: =sum(E107:F107) -> 0 | H107: =D107*G107 -> 0
... C125: Gyuniku Bento | D125: =VLOOKUP(C125, 'LIST HPP'!$B$4:$C$39, 2, FALSE) -> 14616.31 | G125: =sum(E125:F125) -> 0 | H125: =D125*G125 -> 0
B126: =#REF! -> #REF! | I126: =SUM(I2:I125) -> 0 | J126: =SUM(J2:J125) -> 0 | L126: =SUM(L2:L125) -> 0
A128: Stock Opname Inventory | I128: TOTAL JUMLAH ITEM TERJUAL
A129: Menu | B129: No | F129: Data Penjualan
C130: Bahan | D130: Berat | E130: Satuan | F130: Porsi | G130: Total Bahan Terpakai
A131: Gyumeshi | B131: 1 | C131: Daging Blackpepper | D131: 70 | E131: gr | F131: =VLOOKUP(A131, MASTERFILE!$I$130:$J$158, 2, ) -> 0 | G131: =D131*F131 -> 0
B132: 2 | C132: Bowl Mangkok | D132: 1 | E132: pcs | G132: =D132*F131 -> 0
B133: 3 | C133: Tutup Mangkok | D133: 1 | E133: pcs | G133: =D133*F131 -> 0
B134: 4 | C134: inner tray bowl | D134: 1 | E134: pcs | G134: =D134*F131 -> 0
B135: 5 | C135: Nasi Putih | D135: 180 | E135: gr | G135: =D135*F131 -> 0
A136: Karage Don | B136: 1 | C136: Ayam Karage | D136: 130 | E136: gr | F136: =VLOOKUP(A136, MASTERFILE!$I$130:$J$158, 2, ) -> 0 | G136: =D136*F136 -> 0
B137: 2 | C137: Bowl Mangkok | D137: 1 | E137: pcs | G137: =D137*F136 -> 0
B138: 3 | C138: Tutup Mangkok | D138: 1 | E138: pcs | G138: =D138*F136 -> 0
B139: 4 | C139: Nasi Putih | D139: 180 | E139: gr | G139: =D139*F136 -> 0
A140: Hot Honey Karage Don | B140: 1 | C140: Ayam Karage | D140: 130 | E140: gr | F140: =VLOOKUP(A140, MASTERFILE!$I$130:$J$158, 2, ) -> 0 | G140: =D140*F140 -> 0
B141: 2 | C141: Bowl Mangkok | D141: 1 | E141: pcs | G141: =D141*F140 -> 0
B142: 3 | C142: Tutup Mangkok | D142: 1 | E142: pcs | G142: =D142*F140 -> 0
B143: 4 | C143: Nasi Putih | D143: 180 | E143: gr | G143: =D143*F140 -> 0
B144: 5 | C144: Hot Honey Sauce | D144: 20 | E144: gr | G144: =D144*F140 -> 0
A145: Gyuniku Ala Carte | B145: 1 | C145: Daging Blackpepper | D145: 140 | E145: gr | F145: =VLOOKUP(A145, MASTERFILE!$I$130:$J$158, 2, ) -> 0 | G145: =D145*F145 -> 0
B146: 2 | C146: thinwall 500ml | D146: 1 | E146: pcs | G146: =D146*F145 -> 0
A147: Karage Ala Carte | B147: 1 | C147: Ayam Karage | D147: 260 | E147: gr | F147: =VLOOKUP(A147, MASTERFILE!$I$130:$J$158, 2, ) -> 0 | G147: =D147*F147 -> 0
B148: 2 | C148: Bowl Mangkok | D148: 1 | E148: pcs | G148: =D148*F147 -> 0
B149: 3 | C149: Tutup Mangkok | D149: 1 | E149: pcs | G149: =D149*F147 -> 0
A150: Hot Honey Karage Ala Carte | B150: 1 | C150: Ayam Karage | D150: 260 | E150: gr | F150: =VLOOKUP(A150, MASTERFILE!$I$130:$J$158, 2, ) -> 0 | G150: =D150*F150 -> 0
B151: 2 | C151: Bowl Mangkok | D151: 1 | E151: pcs | G151: =D151*F150 -> 0
B152: 3 | C152: Tutup Mangkok | D152: 1 | E152: pcs | G152: =D152*F150 -> 0
B153: 4 | C153: Hot Honey Sauce | D153: 40 | E153: gr | G153: =D153*F150 -> 0
A154: Curry Karage Don | B154: 1 | C154: Ayam Karage | D154: 130 | E154: porsi | F154: =VLOOKUP(A154, MASTERFILE!$I$130:$J$158, 2, ) -> 0 | G154: =D154*F154 -> 0
B155: 2 | C155: Bowl Mangkok | D155: 1 | E155: pcs | G155: =D155*F154 -> 0
B156: 3 | C156: Tutup Mangkok | D156: 1 | E156: pcs | G156: =D156*F154 -> 0
B157: 4 | C157: Nasi Putih | D157: 180 | E157: gr | G157: =D157*F154 -> 0
B158: 5 | C158: Curry Sauce | D158: 1 | E158: pcs | G158: =D158*F154 -> 0
A159: Curry Omurice | B159: 1 | C159: Telor Ayam | D159: 2 | E159: pcs | F159: =VLOOKUP(A159, MASTERFILE!$I$130:$J$158, 2, ) -> 0 | G159: =D159*F159 -> 0
B160: 2 | C160: Bowl Mangkok | D160: 1 | E160: pcs | G160: =D160*F159 -> 0
B161: 3 | C161: Tutup Mangkok | D161: 1 | E161: pcs | G161: =D161*F159 -> 0
B162: 4 | C162: Nasi Putih | D162: 180 | E162: gr | G162: =D162*F159 -> 0
B163: 5 | C163: Curry Sauce | D163: 1 | E163: pcs | G163: =D163*F159 -> 0
B164: 6 | C164: Gula Pasir | D164: 3 | E164: gr | G164: =D164*F159 -> 0
B165: 7 | C165: Dashi Halal | D165: 3 | E165: gr | G165: =D165*F159 -> 0
B166: 8 | C166: Mirin Halal | D166: 5 | E166: gr | G166: =D166*F159 -> 0
A167: Miso Sup | B167: 1 | C167: miso soup | D167: 1 | E167: porsi | F167: =VLOOKUP(A167, MASTERFILE!$I$130:$J$158, 2, ) -> 0 | G167: =D167*F167 -> 0
B168: 2 | C168: daun bawang | D168: 1 | E168: Pcs | G168: =D168*F167 -> 0
...

Sheet 25062026
B1: Tanggal | C1: Nama Item | D1: HPP | E1: Jumlah | F1: Jumlah QR | G1: Total Jumlah | H1: Total | I1: Total HPP | J1: Uang Masuk | K1: Margin | L1: Gross Profit
A2: SHOPEE | C2: Matcha Latte | D2: =VLOOKUP(C2, 'LIST HPP'!$B$4:$C$39, 2, ) -> 8805.63 | E2: 1 | G2: =sum(E2:F2) -> 1 | H2: =D2*G2 -> 8805.63 | I2: =sum(H2:H32) -> 625968.41 | J2: 1014574 | K2: =(J2-I2)/J2 -> 0.38302341 | L2: =J2-I2 -> 388605.59
C3: Hojicha Latte | D3: =VLOOKUP(C3, 'LIST HPP'!$B$4:$C$39, 2, ) -> 8150.63 | E3: 0 | G3: =sum(E3:F3) -> 0 | H3: =D3*G3 -> 0
C4: Choco Latte | D4: =VLOOKUP(C4, 'LIST HPP'!$B$4:$C$39, 2, ) -> 6013.63 | E4: 0 | G4: =sum(E4:F4) -> 0 | H4: =D4*G4 -> 0
C5: Choco Ichigo Latte | D5: =VLOOKUP(C5, 'LIST HPP'!$B$4:$C$39, 2, ) -> 7131.43 | E5: 0 | G5: =sum(E5:F5) -> 0 | H5: =D5*G5 -> 0
C6: Matcha Tea | D6: =VLOOKUP(C6, 'LIST HPP'!$B$4:$C$39, 2, ) -> 3748.21 | E6: 3 | G6: =sum(E6:F6) -> 3 | H6: =D6*G6 -> 11244.63
C7: Ice Tea | D7: =VLOOKUP(C7, 'LIST HPP'!$B$4:$C$39, 2, ) -> 1448.63 | E7: 7 | G7: =sum(E7:F7) -> 7 | H7: =D7*G7 -> 10140.41
C8: Gyumeshi | D8: =VLOOKUP(C8, 'LIST HPP'!$B$4:$C$39, 2, ) -> 11670 | E8: 5 | G8: =sum(E8:F8) -> 5 | H8: =D8*G8 -> 58350
C9: Karage Don | D9: =VLOOKUP(C9, 'LIST HPP'!$B$4:$C$39, 2, ) -> 9350.16 | E9: 19 | G9: =sum(E9:F9) -> 19 | H9: =D9*G9 -> 177653.04
C10: Hot Honey Karage Don | D10: =VLOOKUP(C10, 'LIST HPP'!$B$4:$C$39, 2, ) -> 9990.16 | E10: 2 | G10: =sum(E10:F10) -> 2 | H10: =D10*G10 -> 19980.32
C11: Chicken Katsu Don | D11: =VLOOKUP(C11, 'LIST HPP'!$B$4:$C$39, 2, ) -> 7445.2 | E11: 28 | G11: =sum(E11:F11) -> 28 | H11: =D11*G11 -> 208465.6
C12: Gyuniku Ala Carte | D12: =VLOOKUP(C12, 'LIST HPP'!$B$4:$C$39, 2, ) -> 17260 | E12: 0 | G12: =sum(E12:F12) -> 0 | H12: =D12*G12 -> 0
C13: Karage Ala Carte | D13: =VLOOKUP(C13, 'LIST HPP'!$B$4:$C$39, 2, ) -> 14155 | E13: 0 | G13: =sum(E13:F13) -> 0 | H13: =D13*G13 -> 0
C14: Hot Honey Karage Ala Carte | D14: =VLOOKUP(C14, 'LIST HPP'!$B$4:$C$39, 2, ) -> 15435 | E14: 0 | G14: =sum(E14:F14) -> 0 | H14: =D14*G14 -> 0
... C32: Gyuniku Bento | D32: =VLOOKUP(C32, 'LIST HPP'!$B$4:$C$39, 2, ) -> 14616.31 | E32: 0 | G32: =sum(E32:F32) -> 0 | H32: =D32*G32 -> 0
A33: GRAB/ OFFLINE Q | C33: Matcha Latte | D33: =VLOOKUP(C33, 'LIST HPP'!$B$4:$C$39, 2, ) -> 8805.63 | E33: 0 | G33: =SUM(E33:F33) -> 0 | H33: =D33*G33 -> 0 | I33: =sum(H33:H63) -> 153667 | J33: 323442 | K33: =(J33-I33)/J33 -> 0.52490091 | L33: =J33-I33 -> 169775
C34: Hojicha Latte | D34: =VLOOKUP(C34, 'LIST HPP'!$B$4:$C$39, 2, ) -> 8150.63 | E34: 0 | G34: =SUM(E34:F34) -> 0 | H34: =D34*G34 -> 0
C35: Choco Latte | D35: =VLOOKUP(C35, 'LIST HPP'!$B$4:$C$39, 2, ) -> 6013.63 | E35: 0 | G35: =SUM(E35:F35) -> 0 | H35: =D35*G35 -> 0
C36: Choco Ichigo Latte | D36: =VLOOKUP(C36, 'LIST HPP'!$B$4:$C$39, 2, ) -> 7131.43 | E36: 0 | G36: =SUM(E36:F36) -> 0 | H36: =D36*G36 -> 0
C37: Matcha Tea | D37: =VLOOKUP(C37, 'LIST HPP'!$B$4:$C$39, 2, ) -> 3748.21 | E37: 0 | G37: =SUM(E37:F37) -> 0 | H37: =D37*G37 -> 0
C38: Ice Tea | D38: =VLOOKUP(C38, 'LIST HPP'!$B$4:$C$39, 2, ) -> 1448.63 | E38: 0 | G38: =SUM(E38:F38) -> 0 | H38: =D38*G38 -> 0
C39: Gyumeshi | D39: =VLOOKUP(C39, 'LIST HPP'!$B$4:$C$39, 2, ) -> 11670 | E39: 2 | G39: =SUM(E39:F39) -> 2 | H39: =D39*G39 -> 23340
C40: Karage Don | D40: =VLOOKUP(C40, 'LIST HPP'!$B$4:$C$39, 2, ) -> 9350.16 | E40: 8 | G40: =SUM(E40:F40) -> 8 | H40: =D40*G40 -> 74801.28
C41: Hot Honey Karage Don | D41: =VLOOKUP(C41, 'LIST HPP'!$B$4:$C$39, 2, ) -> 9990.16 | E41: 2 | G41: =SUM(E41:F41) -> 2 | H41: =D41*G41 -> 19980.32
C42: Chicken Katsu Don | D42: =VLOOKUP(C42, 'LIST HPP'!$B$4:$C$39, 2, ) -> 7445.2 | E42: 2 | G42: =SUM(E42:F42) -> 2 | H42: =D42*G42 -> 14890.4
C43: Gyuniku Ala Carte | D43: =VLOOKUP(C43, 'LIST HPP'!$B$4:$C$39, 2, ) -> 17260 | E43: 0 | G43: =SUM(E43:F43) -> 0 | H43: =D43*G43 -> 0
C44: Karage Ala Carte | D44: =VLOOKUP(C44, 'LIST HPP'!$B$4:$C$39, 2, ) -> 14155 | E44: 1 | G44: =SUM(E44:F44) -> 1 | H44: =D44*G44 -> 14155
C45: Hot Honey Karage Ala Carte | D45: =VLOOKUP(C45, 'LIST HPP'!$B$4:$C$39, 2, ) -> 15435 | E45: 0 | G45: =SUM(E45:F45) -> 0 | H45: =D45*G45 -> 0
... C63: Gyuniku Bento | D63: =VLOOKUP(C63, 'LIST HPP'!$B$4:$C$39, 2, ) -> 14616.31 | E63: 0 | G63: =SUM(E63:F63) -> 0 | H63: =D63*G63 -> 0
A64: GOJEK | C64: Matcha Latte | D64: =VLOOKUP(C64, 'LIST HPP'!$B$4:$C$39, 2, ) -> 8805.63 | E64: 0 | G64: =Sum(E64:F64) -> 0 | H64: =D64*G64 -> 0 | I64: =sum(H64:H94) -> 19764.66 | J64: 19439 | K64: =(J64-I64)/J64 -> -0.016752919 | L64: =J64-I64 -> -325.66
C65: Hojicha Latte | D65: =VLOOKUP(C65, 'LIST HPP'!$B$4:$C$39, 2, ) -> 8150.63 | E65: 0 | G65: =Sum(E65:F65) -> 0 | H65: =D65*G65 -> 0
C66: Choco Latte | D66: =VLOOKUP(C66, 'LIST HPP'!$B$4:$C$39, 2, ) -> 6013.63 | E66: 0 | G66: =Sum(E66:F66) -> 0 | H66: =D66*G66 -> 0
C67: Choco Ichigo Latte | D67: =VLOOKUP(C67, 'LIST HPP'!$B$4:$C$39, 2, ) -> 7131.43 | E67: 0 | G67: =Sum(E67:F67) -> 0 | H67: =D67*G67 -> 0
C68: Matcha Tea | D68: =VLOOKUP(C68, 'LIST HPP'!$B$4:$C$39, 2, ) -> 3748.21 | E68: 0 | G68: =Sum(E68:F68) -> 0 | H68: =D68*G68 -> 0
C69: Ice Tea | D69: =VLOOKUP(C69, 'LIST HPP'!$B$4:$C$39, 2, ) -> 1448.63 | E69: 2 | G69: =Sum(E69:F69) -> 2 | H69: =D69*G69 -> 2897.26
C70: Gyumeshi | D70: =VLOOKUP(C70, 'LIST HPP'!$B$4:$C$39, 2, ) -> 11670 | E70: 0 | G70: =Sum(E70:F70) -> 0 | H70: =D70*G70 -> 0
C71: Karage Don | D71: =VLOOKUP(C71, 'LIST HPP'!$B$4:$C$39, 2, ) -> 9350.16 | E71: 0 | G71: =Sum(E71:F71) -> 0 | H71: =D71*G71 -> 0
C72: Hot Honey Karage Don | D72: =VLOOKUP(C72, 'LIST HPP'!$B$4:$C$39, 2, ) -> 9990.16 | E72: 0 | G72: =Sum(E72:F72) -> 0 | H72: =D72*G72 -> 0
C73: Chicken Katsu Don | D73: =VLOOKUP(C73, 'LIST HPP'!$B$4:$C$39, 2, ) -> 7445.2 | E73: 2 | G73: =Sum(E73:F73) -> 2 | H73: =D73*G73 -> 14890.4
C74: Gyuniku Ala Carte | D74: =VLOOKUP(C74, 'LIST HPP'!$B$4:$C$39, 2, ) -> 17260 | E74: 0 | G74: =Sum(E74:F74) -> 0 | H74: =D74*G74 -> 0
C75: Karage Ala Carte | D75: =VLOOKUP(C75, 'LIST HPP'!$B$4:$C$39, 2, ) -> 14155 | E75: 0 | G75: =Sum(E75:F75) -> 0 | H75: =D75*G75 -> 0
C76: Hot Honey Karage Ala Carte | D76: =VLOOKUP(C76, 'LIST HPP'!$B$4:$C$39, 2, ) -> 15435 | E76: 0 | G76: =Sum(E76:F76) -> 0 | H76: =D76*G76 -> 0
... C93: Kaarage Bento | D93: =VLOOKUP(C93, 'LIST HPP'!$B$4:$C$39, 2, ) -> 12796.31 | E93: 0 | G93: =Sum(E93:F93) -> 0 | H93: =D93*G93 -> 0
C94: Gyuniku Bento | D94: =VLOOKUP(C94, 'LIST HPP'!$B$4:$C$39, 2, FALSE) -> 14616.31 | E94: 0 | G94: =Sum(E94:F94) -> 0 | H94: =D94*G94 -> 0
C95: Matcha Latte | D95: =VLOOKUP(C95, 'LIST HPP'!$B$4:$C$39, 2, FALSE) -> 8805.63 | G95: =sum(E95:F95) -> 0 | H95: =D95*G95 -> 0 | I95: =sum(H95:H125) -> 0 | K95: =(J95-I95)/J95 -> #DIV/0! | L95: =J95-I95 -> 0
C96: Hojicha Latte | D96: =VLOOKUP(C96, 'LIST HPP'!$B$4:$C$39, 2, FALSE) -> 8150.63 | G96: =sum(E96:F96) -> 0 | H96: =D96*G96 -> 0
C97: Choco Latte | D97: =VLOOKUP(C97, 'LIST HPP'!$B$4:$C$39, 2, FALSE) -> 6013.63 | G97: =sum(E97:F97) -> 0 | H97: =D97*G97 -> 0
C98: Choco Ichigo Latte | D98: =VLOOKUP(C98, 'LIST HPP'!$B$4:$C$39, 2, FALSE) -> 7131.43 | G98: =sum(E98:F98) -> 0 | H98: =D98*G98 -> 0
C99: Matcha Tea | D99: =VLOOKUP(C99, 'LIST HPP'!$B$4:$C$39, 2, FALSE) -> 3748.21 | G99: =sum(E99:F99) -> 0 | H99: =D99*G99 -> 0
C100: Ice Tea | D100: =VLOOKUP(C100, 'LIST HPP'!$B$4:$C$39, 2, FALSE) -> 1448.63 | G100: =sum(E100:F100) -> 0 | H100: =D100*G100 -> 0
C101: Gyumeshi | D101: =VLOOKUP(C101, 'LIST HPP'!$B$4:$C$39, 2, FALSE) -> 11670 | G101: =sum(E101:F101) -> 0 | H101: =D101*G101 -> 0
C102: Karage Don | D102: =VLOOKUP(C102, 'LIST HPP'!$B$4:$C$39, 2, FALSE) -> 9350.16 | G102: =sum(E102:F102) -> 0 | H102: =D102*G102 -> 0
C103: Hot Honey Karage Don | D103: =VLOOKUP(C103, 'LIST HPP'!$B$4:$C$39, 2, FALSE) -> 9990.16 | G103: =sum(E103:F103) -> 0 | H103: =D103*G103 -> 0
C104: Chicken Katsu Don | D104: =VLOOKUP(C104, 'LIST HPP'!$B$4:$C$39, 2, FALSE) -> 7445.2 | G104: =sum(E104:F104) -> 0 | H104: =D104*G104 -> 0
C105: Gyuniku Ala Carte | D105: =VLOOKUP(C105, 'LIST HPP'!$B$4:$C$39, 2, FALSE) -> 17260 | G105: =sum(E105:F105) -> 0 | H105: =D105*G105 -> 0
C106: Karage Ala Carte | D106: =VLOOKUP(C106, 'LIST HPP'!$B$4:$C$39, 2, FALSE) -> 14155 | G106: =sum(E106:F106) -> 0 | H106: =D106*G106 -> 0
C107: Hot Honey Karage Ala Carte | D107: =VLOOKUP(C107, 'LIST HPP'!$B$4:$C$39, 2, FALSE) -> 15435 | G107: =sum(E107:F107) -> 0 | H107: =D107*G107 -> 0
... C125: Gyuniku Bento | D125: =VLOOKUP(C125, 'LIST HPP'!$B$4:$C$39, 2, FALSE) -> 14616.31 | G125: =sum(E125:F125) -> 0 | H125: =D125*G125 -> 0
B126: =#REF! -> #REF! | I126: =SUM(I2:I125) -> 799400.07 | J126: =SUM(J2:J125) -> 1357455 | L126: =SUM(L2:L125) -> 558054.93
A128: Stock Opname Inventory | I128: TOTAL JUMLAH ITEM TERJUAL
A129: Menu | B129: No | F129: Data Penjualan
C130: Bahan | D130: Berat | E130: Satuan | F130: Porsi | G130: Total Bahan Terpakai
A131: Gyumeshi | B131: 1 | C131: Daging Blackpepper | D131: 70 | E131: gr | F131: =VLOOKUP(A131, '25062026'!$I$130:$J$158, 2, ) -> 7 | G131: =D131*F131 -> 490
B132: 2 | C132: Bowl Mangkok | D132: 1 | E132: pcs | G132: =D132*F131 -> 7
B133: 3 | C133: Tutup Mangkok | D133: 1 | E133: pcs | G133: =D133*F131 -> 7
B134: 4 | C134: inner tray bowl | D134: 1 | E134: pcs | G134: =D134*F131 -> 7
B135: 5 | C135: Nasi Putih | D135: 180 | E135: gr | G135: =D135*F131 -> 1260
A136: Karage Don | B136: 1 | C136: Ayam Karage | D136: 130 | E136: gr | F136: =VLOOKUP(A136, '25062026'!$I$130:$J$158, 2, ) -> 27 | G136: =D136*F136 -> 3510
B137: 2 | C137: Bowl Mangkok | D137: 1 | E137: pcs | G137: =D137*F136 -> 27
B138: 3 | C138: Tutup Mangkok | D138: 1 | E138: pcs | G138: =D138*F136 -> 27
B139: 4 | C139: Nasi Putih | D139: 180 | E139: gr | G139: =D139*F136 -> 4860
A140: Hot Honey Karage Don | B140: 1 | C140: Ayam Karage | D140: 130 | E140: gr | F140: =VLOOKUP(A140, '25062026'!$I$130:$J$158, 2, ) -> 4 | G140: =D140*F140 -> 520
B141: 2 | C141: Bowl Mangkok | D141: 1 | E141: pcs | G141: =D141*F140 -> 4
B142: 3 | C142: Tutup Mangkok | D142: 1 | E142: pcs | G142: =D142*F140 -> 4
B143: 4 | C143: Nasi Putih | D143: 180 | E143: gr | G143: =D143*F140 -> 720
B144: 5 | C144: Hot Honey Sauce | D144: 20 | E144: gr | G144: =D144*F140 -> 80
A145: Gyuniku Ala Carte | B145: 1 | C145: Daging Blackpepper | D145: 140 | E145: gr | F145: =VLOOKUP(A145, '25062026'!$I$130:$J$158, 2, ) -> 0 | G145: =D145*F145 -> 0
B146: 2 | C146: thinwall 500ml | D146: 1 | E146: pcs | G146: =D146*F145 -> 0
A147: Karage Ala Carte | B147: 1 | C147: Ayam Karage | D147: 260 | E147: gr | F147: =VLOOKUP(A147, '25062026'!$I$130:$J$158, 2, ) -> 1 | G147: =D147*F147 -> 260
B148: 2 | C148: Bowl Mangkok | D148: 1 | E148: pcs | G148: =D148*F147 -> 1
B149: 3 | C149: Tutup Mangkok | D149: 1 | E149: pcs | G149: =D149*F147 -> 1
A150: Hot Honey Karage Ala Carte | B150: 1 | C150: Ayam Karage | D150: 260 | E150: gr | F150: =VLOOKUP(A150, '25062026'!$I$130:$J$158, 2, ) -> 0 | G150: =D150*F150 -> 0
B151: 2 | C151: Bowl Mangkok | D151: 1 | E151: pcs | G151: =D151*F150 -> 0
B152: 3 | C152: Tutup Mangkok | D152: 1 | E152: pcs | G152: =D152*F150 -> 0
B153: 4 | C153: Hot Honey Sauce | D153: 40 | E153: gr | G153: =D153*F150 -> 0
A154: Curry Karage Don | B154: 1 | C154: Ayam Karage | D154: 130 | E154: porsi | F154: =VLOOKUP(A154, '25062026'!$I$130:$J$158, 2, ) -> 0 | G154: =D154*F154 -> 0
B155: 2 | C155: Bowl Mangkok | D155: 1 | E155: pcs | G155: =D155*F154 -> 0
B156: 3 | C156: Tutup Mangkok | D156: 1 | E156: pcs | G156: =D156*F154 -> 0
B157: 4 | C157: Nasi Putih | D157: 180 | E157: gr | G157: =D157*F154 -> 0
B158: 5 | C158: Curry Sauce | D158: 1 | E158: pcs | G158: =D158*F154 -> 0
A159: Curry Omurice | B159: 1 | C159: Telor Ayam | D159: 2 | E159: pcs | F159: =VLOOKUP(A159, '25062026'!$I$130:$J$158, 2, ) -> 0 | G159: =D159*F159 -> 0
B160: 2 | C160: Bowl Mangkok | D160: 1 | E160: pcs | G160: =D160*F159 -> 0
B161: 3 | C161: Tutup Mangkok | D161: 1 | E161: pcs | G161: =D161*F159 -> 0
B162: 4 | C162: Nasi Putih | D162: 180 | E162: gr | G162: =D162*F159 -> 0
B163: 5 | C163: Curry Sauce | D163: 1 | E163: pcs | G163: =D163*F159 -> 0
B164: 6 | C164: Gula Pasir | D164: 3 | E164: gr | G164: =D164*F159 -> 0
B165: 7 | C165: Dashi Halal | D165: 3 | E165: gr | G165: =D165*F159 -> 0
B166: 8 | C166: Mirin Halal | D166: 5 | E166: gr | G166: =D166*F159 -> 0
A167: Miso Sup | B167: 1 | C167: miso soup | D167: 1 | E167: porsi | F167: =VLOOKUP(A167, '25062026'!$I$130:$J$158, 2, ) -> 8 | G167: =D167*F167 -> 8
B168: 2 | C168: daun bawang | D168: 1 | E168: Pcs | G168: =D168*F167 -> 8
...

Sheet 24062026
B1: Tanggal | C1: Nama Item | D1: HPP | E1: Jumlah | F1: Jumlah QR | G1: Total Jumlah | H1: Total | I1: Total HPP | J1: Uang Masuk | K1: Margin | L1: Gross Profit
A2: SHOPEE | C2: Matcha Latte | D2: =VLOOKUP(C2, 'LIST HPP'!$B$4:$C$39, 2, ) -> 8805.63 | E2: 2 | G2: =sum(E2:F2) -> 2 | H2: =D2*G2 -> 17611.26 | I2: =sum(H2:H32) -> 360944.36 | J2: 561388 | K2: =(J2-I2)/J2 -> 0.3570501 | L2: =J2-I2 -> 200443.64
C3: Hojicha Latte | D3: =VLOOKUP(C3, 'LIST HPP'!$B$4:$C$39, 2, ) -> 8150.63 | E3: 0 | G3: =sum(E3:F3) -> 0 | H3: =D3*G3 -> 0
C4: Choco Latte | D4: =VLOOKUP(C4, 'LIST HPP'!$B$4:$C$39, 2, ) -> 6013.63 | E4: 0 | G4: =sum(E4:F4) -> 0 | H4: =D4*G4 -> 0
C5: Choco Ichigo Latte | D5: =VLOOKUP(C5, 'LIST HPP'!$B$4:$C$39, 2, ) -> 7131.43 | E5: 0 | G5: =sum(E5:F5) -> 0 | H5: =D5*G5 -> 0
C6: Matcha Tea | D6: =VLOOKUP(C6, 'LIST HPP'!$B$4:$C$39, 2, ) -> 3748.21 | E6: 2 | G6: =sum(E6:F6) -> 2 | H6: =D6*G6 -> 7496.42
C7: Ice Tea | D7: =VLOOKUP(C7, 'LIST HPP'!$B$4:$C$39, 2, ) -> 1448.63 | E7: 2 | G7: =sum(E7:F7) -> 2 | H7: =D7*G7 -> 2897.26
C8: Gyumeshi | D8: =VLOOKUP(C8, 'LIST HPP'!$B$4:$C$39, 2, ) -> 11670 | E8: 2 | G8: =sum(E8:F8) -> 2 | H8: =D8*G8 -> 23340
C9: Karage Don | D9: =VLOOKUP(C9, 'LIST HPP'!$B$4:$C$39, 2, ) -> 9350.16 | E9: 6 | G9: =sum(E9:F9) -> 6 | H9: =D9*G9 -> 56100.96
C10: Hot Honey Karage Don | D10: =VLOOKUP(C10, 'LIST HPP'!$B$4:$C$39, 2, ) -> 9990.16 | E10: 4 | G10: =sum(E10:F10) -> 4 | H10: =D10*G10 -> 39960.64
C11: Chicken Katsu Don | D11: =VLOOKUP(C11, 'LIST HPP'!$B$4:$C$39, 2, ) -> 7445.2 | E11: 20 | G11: =sum(E11:F11) -> 20 | H11: =D11*G11 -> 148904
C12: Gyuniku Ala Carte | D12: =VLOOKUP(C12, 'LIST HPP'!$B$4:$C$39, 2, ) -> 17260 | E12: 0 | G12: =sum(E12:F12) -> 0 | H12: =D12*G12 -> 0
C13: Karage Ala Carte | D13: =VLOOKUP(C13, 'LIST HPP'!$B$4:$C$39, 2, ) -> 14155 | E13: 1 | G13: =sum(E13:F13) -> 1 | H13: =D13*G13 -> 14155
C14: Hot Honey Karage Ala Carte | D14: =VLOOKUP(C14, 'LIST HPP'!$B$4:$C$39, 2, ) -> 15435 | E14: 0 | G14: =sum(E14:F14) -> 0 | H14: =D14*G14 -> 0
... C32: Gyuniku Bento | D32: =VLOOKUP(C32, 'LIST HPP'!$B$4:$C$39, 2, ) -> 14616.31 | E32: 0 | G32: =sum(E32:F32) -> 0 | H32: =D32*G32 -> 0
A33: GRAB/ OFFLINE Q | C33: Matcha Latte | D33: =VLOOKUP(C33, 'LIST HPP'!$B$4:$C$39, 2, ) -> 8805.63 | E33: 0 | G33: =SUM(E33:F33) -> 0 | H33: =D33*G33 -> 0 | I33: =sum(H33:H63) -> 87737.28 | J33: 169646 | K33: =(J33-I33)/J33 -> 0.4828214 | L33: =J33-I33 -> 81908.72
C34: Hojicha Latte | D34: =VLOOKUP(C34, 'LIST HPP'!$B$4:$C$39, 2, ) -> 8150.63 | E34: 0 | G34: =SUM(E34:F34) -> 0 | H34: =D34*G34 -> 0
C35: Choco Latte | D35: =VLOOKUP(C35, 'LIST HPP'!$B$4:$C$39, 2, ) -> 6013.63 | E35: 0 | G35: =SUM(E35:F35) -> 0 | H35: =D35*G35 -> 0
C36: Choco Ichigo Latte | D36: =VLOOKUP(C36, 'LIST HPP'!$B$4:$C$39, 2, ) -> 7131.43 | E36: 0 | G36: =SUM(E36:F36) -> 0 | H36: =D36*G36 -> 0
C37: Matcha Tea | D37: =VLOOKUP(C37, 'LIST HPP'!$B$4:$C$39, 2, ) -> 3748.21 | E37: 1 | G37: =SUM(E37:F37) -> 1 | H37: =D37*G37 -> 3748.21
C38: Ice Tea | D38: =VLOOKUP(C38, 'LIST HPP'!$B$4:$C$39, 2, ) -> 1448.63 | E38: 1 | G38: =SUM(E38:F38) -> 1 | H38: =D38*G38 -> 1448.63
C39: Gyumeshi | D39: =VLOOKUP(C39, 'LIST HPP'!$B$4:$C$39, 2, ) -> 11670 | E39: 0 | G39: =SUM(E39:F39) -> 0 | H39: =D39*G39 -> 0
C40: Karage Don | D40: =VLOOKUP(C40, 'LIST HPP'!$B$4:$C$39, 2, ) -> 9350.16 | E40: 0 | G40: =SUM(E40:F40) -> 0 | H40: =D40*G40 -> 0
C41: Hot Honey Karage Don | D41: =VLOOKUP(C41, 'LIST HPP'!$B$4:$C$39, 2, ) -> 9990.16 | E41: 2 | G41: =SUM(E41:F41) -> 2 | H41: =D41*G41 -> 19980.32
C42: Chicken Katsu Don | D42: =VLOOKUP(C42, 'LIST HPP'!$B$4:$C$39, 2, ) -> 7445.2 | E42: 4 | G42: =SUM(E42:F42) -> 4 | H42: =D42*G42 -> 29780.8
C43: Gyuniku Ala Carte | D43: =VLOOKUP(C43, 'LIST HPP'!$B$4:$C$39, 2, ) -> 17260 | E43: 0 | G43: =SUM(E43:F43) -> 0 | H43: =D43*G43 -> 0
C44: Karage Ala Carte | D44: =VLOOKUP(C44, 'LIST HPP'!$B$4:$C$39, 2, ) -> 14155 | E44: 0 | G44: =SUM(E44:F44) -> 0 | H44: =D44*G44 -> 0
C45: Hot Honey Karage Ala Carte | D45: =VLOOKUP(C45, 'LIST HPP'!$B$4:$C$39, 2, ) -> 15435 | E45: 0 | G45: =SUM(E45:F45) -> 0 | H45: =D45*G45 -> 0
... C63: Gyuniku Bento | D63: =VLOOKUP(C63, 'LIST HPP'!$B$4:$C$39, 2, ) -> 14616.31 | E63: 0 | G63: =SUM(E63:F63) -> 0 | H63: =D63*G63 -> 0
A64: GOJEK | C64: Matcha Latte | D64: =VLOOKUP(C64, 'LIST HPP'!$B$4:$C$39, 2, ) -> 8805.63 | E64: 2 | G64: =Sum(E64:F64) -> 2 | H64: =D64*G64 -> 17611.26 | I64: =sum(H64:H94) -> 68089.19 | J64: 114232 | K64: =(J64-I64)/J64 -> 0.40393944 | L64: =J64-I64 -> 46142.81
C65: Hojicha Latte | D65: =VLOOKUP(C65, 'LIST HPP'!$B$4:$C$39, 2, ) -> 8150.63 | E65: 0 | G65: =Sum(E65:F65) -> 0 | H65: =D65*G65 -> 0
C66: Choco Latte | D66: =VLOOKUP(C66, 'LIST HPP'!$B$4:$C$39, 2, ) -> 6013.63 | E66: 0 | G66: =Sum(E66:F66) -> 0 | H66: =D66*G66 -> 0
C67: Choco Ichigo Latte | D67: =VLOOKUP(C67, 'LIST HPP'!$B$4:$C$39, 2, ) -> 7131.43 | E67: 0 | G67: =Sum(E67:F67) -> 0 | H67: =D67*G67 -> 0
C68: Matcha Tea | D68: =VLOOKUP(C68, 'LIST HPP'!$B$4:$C$39, 2, ) -> 3748.21 | E68: 0 | G68: =Sum(E68:F68) -> 0 | H68: =D68*G68 -> 0
C69: Ice Tea | D69: =VLOOKUP(C69, 'LIST HPP'!$B$4:$C$39, 2, ) -> 1448.63 | E69: 1 | G69: =Sum(E69:F69) -> 1 | H69: =D69*G69 -> 1448.63
C70: Gyumeshi | D70: =VLOOKUP(C70, 'LIST HPP'!$B$4:$C$39, 2, ) -> 11670 | E70: 0 | G70: =Sum(E70:F70) -> 0 | H70: =D70*G70 -> 0
C71: Karage Don | D71: =VLOOKUP(C71, 'LIST HPP'!$B$4:$C$39, 2, ) -> 9350.16 | E71: 1 | G71: =Sum(E71:F71) -> 1 | H71: =D71*G71 -> 9350.16
C72: Hot Honey Karage Don | D72: =VLOOKUP(C72, 'LIST HPP'!$B$4:$C$39, 2, ) -> 9990.16 | E72: 1 | G72: =Sum(E72:F72) -> 1 | H72: =D72*G72 -> 9990.16
C73: Chicken Katsu Don | D73: =VLOOKUP(C73, 'LIST HPP'!$B$4:$C$39, 2, ) -> 7445.2 | E73: 0 | G73: =Sum(E73:F73) -> 0 | H73: =D73*G73 -> 0
C74: Gyuniku Ala Carte | D74: =VLOOKUP(C74, 'LIST HPP'!$B$4:$C$39, 2, ) -> 17260 | E74: 0 | G74: =Sum(E74:F74) -> 0 | H74: =D74*G74 -> 0
C75: Karage Ala Carte | D75: =VLOOKUP(C75, 'LIST HPP'!$B$4:$C$39, 2, ) -> 14155 | E75: 0 | G75: =Sum(E75:F75) -> 0 | H75: =D75*G75 -> 0
C76: Hot Honey Karage Ala Carte | D76: =VLOOKUP(C76, 'LIST HPP'!$B$4:$C$39, 2, ) -> 15435 | E76: 0 | G76: =Sum(E76:F76) -> 0 | H76: =D76*G76 -> 0
... C93: Kaarage Bento | D93: =VLOOKUP(C93, 'LIST HPP'!$B$4:$C$39, 2, ) -> 12796.31 | E93: 0 | G93: =Sum(E93:F93) -> 0 | H93: =D93*G93 -> 0
C94: Gyuniku Bento | D94: =VLOOKUP(C94, 'LIST HPP'!$B$4:$C$39, 2, FALSE) -> 14616.31 | E94: 0 | G94: =Sum(E94:F94) -> 0 | H94: =D94*G94 -> 0
C95: Matcha Latte | D95: =VLOOKUP(C95, 'LIST HPP'!$B$4:$C$39, 2, FALSE) -> 8805.63 | G95: =sum(E95:F95) -> 0 | H95: =D95*G95 -> 0 | I95: =sum(H95:H125) -> 0 | K95: =(J95-I95)/J95 -> #DIV/0! | L95: =J95-I95 -> 0
C96: Hojicha Latte | D96: =VLOOKUP(C96, 'LIST HPP'!$B$4:$C$39, 2, FALSE) -> 8150.63 | G96: =sum(E96:F96) -> 0 | H96: =D96*G96 -> 0
C97: Choco Latte | D97: =VLOOKUP(C97, 'LIST HPP'!$B$4:$C$39, 2, FALSE) -> 6013.63 | G97: =sum(E97:F97) -> 0 | H97: =D97*G97 -> 0
C98: Choco Ichigo Latte | D98: =VLOOKUP(C98, 'LIST HPP'!$B$4:$C$39, 2, FALSE) -> 7131.43 | G98: =sum(E98:F98) -> 0 | H98: =D98*G98 -> 0
C99: Matcha Tea | D99: =VLOOKUP(C99, 'LIST HPP'!$B$4:$C$39, 2, FALSE) -> 3748.21 | G99: =sum(E99:F99) -> 0 | H99: =D99*G99 -> 0
C100: Ice Tea | D100: =VLOOKUP(C100, 'LIST HPP'!$B$4:$C$39, 2, FALSE) -> 1448.63 | G100: =sum(E100:F100) -> 0 | H100: =D100*G100 -> 0
C101: Gyumeshi | D101: =VLOOKUP(C101, 'LIST HPP'!$B$4:$C$39, 2, FALSE) -> 11670 | G101: =sum(E101:F101) -> 0 | H101: =D101*G101 -> 0
C102: Karage Don | D102: =VLOOKUP(C102, 'LIST HPP'!$B$4:$C$39, 2, FALSE) -> 9350.16 | G102: =sum(E102:F102) -> 0 | H102: =D102*G102 -> 0
C103: Hot Honey Karage Don | D103: =VLOOKUP(C103, 'LIST HPP'!$B$4:$C$39, 2, FALSE) -> 9990.16 | G103: =sum(E103:F103) -> 0 | H103: =D103*G103 -> 0
C104: Chicken Katsu Don | D104: =VLOOKUP(C104, 'LIST HPP'!$B$4:$C$39, 2, FALSE) -> 7445.2 | G104: =sum(E104:F104) -> 0 | H104: =D104*G104 -> 0
C105: Gyuniku Ala Carte | D105: =VLOOKUP(C105, 'LIST HPP'!$B$4:$C$39, 2, FALSE) -> 17260 | G105: =sum(E105:F105) -> 0 | H105: =D105*G105 -> 0
C106: Karage Ala Carte | D106: =VLOOKUP(C106, 'LIST HPP'!$B$4:$C$39, 2, FALSE) -> 14155 | G106: =sum(E106:F106) -> 0 | H106: =D106*G106 -> 0
C107: Hot Honey Karage Ala Carte | D107: =VLOOKUP(C107, 'LIST HPP'!$B$4:$C$39, 2, FALSE) -> 15435 | G107: =sum(E107:F107) -> 0 | H107: =D107*G107 -> 0
... C125: Gyuniku Bento | D125: =VLOOKUP(C125, 'LIST HPP'!$B$4:$C$39, 2, FALSE) -> 14616.31 | G125: =sum(E125:F125) -> 0 | H125: =D125*G125 -> 0
B126: =#REF! -> #REF! | I126: =SUM(I2:I125) -> 516770.83 | J126: =SUM(J2:J125) -> 845266 | L126: =SUM(L2:L125) -> 328495.17
A128: Stock Opname Inventory | I128: TOTAL JUMLAH ITEM TERJUAL
A129: Menu | B129: No | F129: Data Penjualan
C130: Bahan | D130: Berat | E130: Satuan | F130: Porsi | G130: Total Bahan Terpakai
A131: Gyumeshi | B131: 1 | C131: Daging Blackpepper | D131: 70 | E131: gr | F131: =VLOOKUP(A131, '24062026'!$I$130:$J$158, 2, ) -> 2 | G131: =D131*F131 -> 140
B132: 2 | C132: Bowl Mangkok | D132: 1 | E132: pcs | G132: =D132*F131 -> 2
B133: 3 | C133: Tutup Mangkok | D133: 1 | E133: pcs | G133: =D133*F131 -> 2
B134: 4 | C134: inner tray bowl | D134: 1 | E134: pcs | G134: =D134*F131 -> 2
B135: 5 | C135: Nasi Putih | D135: 180 | E135: gr | G135: =D135*F131 -> 360
A136: Karage Don | B136: 1 | C136: Ayam Karage | D136: 130 | E136: gr | F136: =VLOOKUP(A136, '24062026'!$I$130:$J$158, 2, ) -> 7 | G136: =D136*F136 -> 910
B137: 2 | C137: Bowl Mangkok | D137: 1 | E137: pcs | G137: =D137*F136 -> 7
B138: 3 | C138: Tutup Mangkok | D138: 1 | E138: pcs | G138: =D138*F136 -> 7
B139: 4 | C139: Nasi Putih | D139: 180 | E139: gr | G139: =D139*F136 -> 1260
A140: Hot Honey Karage Don | B140: 1 | C140: Ayam Karage | D140: 130 | E140: gr | F140: =VLOOKUP(A140, '24062026'!$I$130:$J$158, 2, ) -> 7 | G140: =D140*F140 -> 910
B141: 2 | C141: Bowl Mangkok | D141: 1 | E141: pcs | G141: =D141*F140 -> 7
B142: 3 | C142: Tutup Mangkok | D142: 1 | E142: pcs | G142: =D142*F140 -> 7
B143: 4 | C143: Nasi Putih | D143: 180 | E143: gr | G143: =D143*F140 -> 1260
B144: 5 | C144: Hot Honey Sauce | D144: 20 | E144: gr | G144: =D144*F140 -> 140
A145: Gyuniku Ala Carte | B145: 1 | C145: Daging Blackpepper | D145: 140 | E145: gr | F145: =VLOOKUP(A145, '24062026'!$I$130:$J$158, 2, ) -> 0 | G145: =D145*F145 -> 0
B146: 2 | C146: thinwall 500ml | D146: 1 | E146: pcs | G146: =D146*F145 -> 0
A147: Karage Ala Carte | B147: 1 | C147: Ayam Karage | D147: 260 | E147: gr | F147: =VLOOKUP(A147, '24062026'!$I$130:$J$158, 2, ) -> 1 | G147: =D147*F147 -> 260
B148: 2 | C148: Bowl Mangkok | D148: 1 | E148: pcs | G148: =D148*F147 -> 1
B149: 3 | C149: Tutup Mangkok | D149: 1 | E149: pcs | G149: =D149*F147 -> 1
A150: Hot Honey Karage Ala Carte | B150: 1 | C150: Ayam Karage | D150: 260 | E150: gr | F150: =VLOOKUP(A150, '24062026'!$I$130:$J$158, 2, ) -> 0 | G150: =D150*F150 -> 0
B151: 2 | C151: Bowl Mangkok | D151: 1 | E151: pcs | G151: =D151*F150 -> 0
B152: 3 | C152: Tutup Mangkok | D152: 1 | E152: pcs | G152: =D152*F150 -> 0
B153: 4 | C153: Hot Honey Sauce | D153: 40 | E153: gr | G153: =D153*F150 -> 0
A154: Curry Karage Don | B154: 1 | C154: Ayam Karage | D154: 130 | E154: porsi | F154: =VLOOKUP(A154, '24062026'!$I$130:$J$158, 2, ) -> 0 | G154: =D154*F154 -> 0
B155: 2 | C155: Bowl Mangkok | D155: 1 | E155: pcs | G155: =D155*F154 -> 0
B156: 3 | C156: Tutup Mangkok | D156: 1 | E156: pcs | G156: =D156*F154 -> 0
B157: 4 | C157: Nasi Putih | D157: 180 | E157: gr | G157: =D157*F154 -> 0
B158: 5 | C158: Curry Sauce | D158: 1 | E158: pcs | G158: =D158*F154 -> 0
A159: Curry Omurice | B159: 1 | C159: Telor Ayam | D159: 2 | E159: pcs | F159: =VLOOKUP(A159, '24062026'!$I$130:$J$158, 2, ) -> 0 | G159: =D159*F159 -> 0
B160: 2 | C160: Bowl Mangkok | D160: 1 | E160: pcs | G160: =D160*F159 -> 0
B161: 3 | C161: Tutup Mangkok | D161: 1 | E161: pcs | G161: =D161*F159 -> 0
B162: 4 | C162: Nasi Putih | D162: 180 | E162: gr | G162: =D162*F159 -> 0
B163: 5 | C163: Curry Sauce | D163: 1 | E163: pcs | G163: =D163*F159 -> 0
B164: 6 | C164: Gula Pasir | D164: 3 | E164: gr | G164: =D164*F159 -> 0
B165: 7 | C165: Dashi Halal | D165: 3 | E165: gr | G165: =D165*F159 -> 0
B166: 8 | C166: Mirin Halal | D166: 5 | E166: gr | G166: =D166*F159 -> 0
A167: Miso Sup | B167: 1 | C167: miso soup | D167: 1 | E167: porsi | F167: =VLOOKUP(A167, '24062026'!$I$130:$J$158, 2, ) -> 0 | G167: =D167*F167 -> 0
B168: 2 | C168: daun bawang | D168: 1 | E168: Pcs | G168: =D168*F167 -> 0
...

Sheet 23062026
A1: PLATFORM | B1: Tanggal | C1: Nama Item | D1: HPP | E1: Jumlah | F1: Jumlah QR | G1: Total Jumlah | H1: Total | I1: Total HPP | J1: Uang Masuk | K1: Margin | L1: Gross Profit
A2: SHOPEE | C2: Matcha Latte | D2: =VLOOKUP(C2, 'LIST HPP'!$B$4:$C$39, 2, ) -> 8805.63 | E2: 1 | G2: =sum(E2:F2) -> 1 | H2: =D2*G2 -> 8805.63 | I2: =sum(H2:H32) -> 608382.22 | J2: 977502 | K2: =(J2-I2)/J2 -> 0.37761537 | L2: =J2-I2 -> 369119.78
C3: Hojicha Latte | D3: =VLOOKUP(C3, 'LIST HPP'!$B$4:$C$39, 2, ) -> 8150.63 | E3: 0 | G3: =sum(E3:F3) -> 0 | H3: =D3*G3 -> 0
C4: Choco Latte | D4: =VLOOKUP(C4, 'LIST HPP'!$B$4:$C$39, 2, ) -> 6013.63 | E4: 0 | G4: =sum(E4:F4) -> 0 | H4: =D4*G4 -> 0
C5: Choco Ichigo Latte | D5: =VLOOKUP(C5, 'LIST HPP'!$B$4:$C$39, 2, ) -> 7131.43 | E5: 0 | G5: =sum(E5:F5) -> 0 | H5: =D5*G5 -> 0
C6: Matcha Tea | D6: =VLOOKUP(C6, 'LIST HPP'!$B$4:$C$39, 2, ) -> 3748.21 | E6: 1 | G6: =sum(E6:F6) -> 1 | H6: =D6*G6 -> 3748.21
C7: Ice Tea | D7: =VLOOKUP(C7, 'LIST HPP'!$B$4:$C$39, 2, ) -> 1448.63 | E7: 4 | G7: =sum(E7:F7) -> 4 | H7: =D7*G7 -> 5794.52
C8: Gyumeshi | D8: =VLOOKUP(C8, 'LIST HPP'!$B$4:$C$39, 2, ) -> 11670 | E8: 10 | G8: =sum(E8:F8) -> 10 | H8: =D8*G8 -> 116700
C9: Karage Don | D9: =VLOOKUP(C9, 'LIST HPP'!$B$4:$C$39, 2, ) -> 9350.16 | E9: 4 | G9: =sum(E9:F9) -> 4 | H9: =D9*G9 -> 37400.64
C10: Hot Honey Karage Don | D10: =VLOOKUP(C10, 'LIST HPP'!$B$4:$C$39, 2, ) -> 9990.16 | E10: 4 | G10: =sum(E10:F10) -> 4 | H10: =D10*G10 -> 39960.64
C11: Chicken Katsu Don | D11: =VLOOKUP(C11, 'LIST HPP'!$B$4:$C$39, 2, ) -> 7445.2 | E11: 37 | G11: =sum(E11:F11) -> 37 | H11: =D11*G11 -> 275472.4
C12: Gyuniku Ala Carte | D12: =VLOOKUP(C12, 'LIST HPP'!$B$4:$C$39, 2, ) -> 17260 | E12: 1 | G12: =sum(E12:F12) -> 1 | H12: =D12*G12 -> 17260
C13: Karage Ala Carte | D13: =VLOOKUP(C13, 'LIST HPP'!$B$4:$C$39, 2, ) -> 14155 | E13: 2 | G13: =sum(E13:F13) -> 2 | H13: =D13*G13 -> 28310
C14: Hot Honey Karage Ala Carte | D14: =VLOOKUP(C14, 'LIST HPP'!$B$4:$C$39, 2, ) -> 15435 | E14: 0 | G14: =sum(E14:F14) -> 0 | H14: =D14*G14 -> 0
... C32: Gyuniku Bento | D32: =VLOOKUP(C32, 'LIST HPP'!$B$4:$C$39, 2, ) -> 14616.31 | E32: 0 | G32: =sum(E32:F32) -> 0 | H32: =D32*G32 -> 0
A33: GRAB/ OFFLINE Q | C33: Matcha Latte | D33: =VLOOKUP(C33, 'LIST HPP'!$B$4:$C$39, 2, ) -> 8805.63 | E33: 0 | F33: 0 | G33: =SUM(E33:F33) -> 0 | H33: =D33*G33 -> 0 | I33: =sum(H33:H63) -> 164609.05 | J33: 236017 | K33: =(J33-I33)/J33 -> 0.30255427 | L33: =J33-I33 -> 71407.95
C34: Hojicha Latte | D34: =VLOOKUP(C34, 'LIST HPP'!$B$4:$C$39, 2, ) -> 8150.63 | E34: 0 | F34: 0 | G34: =SUM(E34:F34) -> 0 | H34: =D34*G34 -> 0
C35: Choco Latte | D35: =VLOOKUP(C35, 'LIST HPP'!$B$4:$C$39, 2, ) -> 6013.63 | E35: 0 | F35: 0 | G35: =SUM(E35:F35) -> 0 | H35: =D35*G35 -> 0
C36: Choco Ichigo Latte | D36: =VLOOKUP(C36, 'LIST HPP'!$B$4:$C$39, 2, ) -> 7131.43 | E36: 0 | F36: 0 | G36: =SUM(E36:F36) -> 0 | H36: =D36*G36 -> 0
C37: Matcha Tea | D37: =VLOOKUP(C37, 'LIST HPP'!$B$4:$C$39, 2, ) -> 3748.21 | E37: 0 | F37: 0 | G37: =SUM(E37:F37) -> 0 | H37: =D37*G37 -> 0
C38: Ice Tea | D38: =VLOOKUP(C38, 'LIST HPP'!$B$4:$C$39, 2, ) -> 1448.63 | E38: 1 | F38: 0 | G38: =SUM(E38:F38) -> 1 | H38: =D38*G38 -> 1448.63
C39: Gyumeshi | D39: =VLOOKUP(C39, 'LIST HPP'!$B$4:$C$39, 2, ) -> 11670 | E39: 0 | F39: 0 | G39: =SUM(E39:F39) -> 0 | H39: =D39*G39 -> 0
C40: Karage Don | D40: =VLOOKUP(C40, 'LIST HPP'!$B$4:$C$39, 2, ) -> 9350.16 | E40: 2 | F40: 0 | G40: =SUM(E40:F40) -> 2 | H40: =D40*G40 -> 18700.32
C41: Hot Honey Karage Don | D41: =VLOOKUP(C41, 'LIST HPP'!$B$4:$C$39, 2, ) -> 9990.16 | E41: 3 | F41: 0 | G41: =SUM(E41:F41) -> 3 | H41: =D41*G41 -> 29970.48
C42: Chicken Katsu Don | D42: =VLOOKUP(C42, 'LIST HPP'!$B$4:$C$39, 2, ) -> 7445.2 | E42: 9 | F42: 0 | G42: =SUM(E42:F42) -> 9 | H42: =D42*G42 -> 67006.8
C43: Gyuniku Ala Carte | D43: =VLOOKUP(C43, 'LIST HPP'!$B$4:$C$39, 2, ) -> 17260 | E43: 0 | F43: 0 | G43: =SUM(E43:F43) -> 0 | H43: =D43*G43 -> 0
C44: Karage Ala Carte | D44: =VLOOKUP(C44, 'LIST HPP'!$B$4:$C$39, 2, ) -> 14155 | E44: 0 | F44: 0 | G44: =SUM(E44:F44) -> 0 | H44: =D44*G44 -> 0
C45: Hot Honey Karage Ala Carte | D45: =VLOOKUP(C45, 'LIST HPP'!$B$4:$C$39, 2, ) -> 15435 | E45: 0 | F45: 0 | G45: =SUM(E45:F45) -> 0 | H45: =D45*G45 -> 0
... C63: Gyuniku Bento | D63: =VLOOKUP(C63, 'LIST HPP'!$B$4:$C$39, 2, ) -> 14616.31 | E63: 0 | F63: 0 | G63: =SUM(E63:F63) -> 0 | H63: =D63*G63 -> 0
A64: GOJEK | C64: Matcha Latte | D64: =VLOOKUP(C64, 'LIST HPP'!$B$4:$C$39, 2, ) -> 8805.63 | E64: 0 | G64: =Sum(E64:F64) -> 0 | H64: =D64*G64 -> 0 | I64: =sum(H64:H94) -> 77609.48 | J64: 162602 | K64: =(J64-I64)/J64 -> 0.5227028 | L64: =J64-I64 -> 84992.52
C65: Hojicha Latte | D65: =VLOOKUP(C65, 'LIST HPP'!$B$4:$C$39, 2, ) -> 8150.63 | E65: 0 | G65: =Sum(E65:F65) -> 0 | H65: =D65*G65 -> 0
C66: Choco Latte | D66: =VLOOKUP(C66, 'LIST HPP'!$B$4:$C$39, 2, ) -> 6013.63 | E66: 0 | G66: =Sum(E66:F66) -> 0 | H66: =D66*G66 -> 0
C67: Choco Ichigo Latte | D67: =VLOOKUP(C67, 'LIST HPP'!$B$4:$C$39, 2, ) -> 7131.43 | E67: 0 | G67: =Sum(E67:F67) -> 0 | H67: =D67*G67 -> 0
C68: Matcha Tea | D68: =VLOOKUP(C68, 'LIST HPP'!$B$4:$C$39, 2, ) -> 3748.21 | E68: 0 | G68: =Sum(E68:F68) -> 0 | H68: =D68*G68 -> 0
C69: Ice Tea | D69: =VLOOKUP(C69, 'LIST HPP'!$B$4:$C$39, 2, ) -> 1448.63 | E69: 2 | G69: =Sum(E69:F69) -> 2 | H69: =D69*G69 -> 2897.26
C70: Gyumeshi | D70: =VLOOKUP(C70, 'LIST HPP'!$B$4:$C$39, 2, ) -> 11670 | E70: 1 | G70: =Sum(E70:F70) -> 1 | H70: =D70*G70 -> 11670
C71: Karage Don | D71: =VLOOKUP(C71, 'LIST HPP'!$B$4:$C$39, 2, ) -> 9350.16 | E71: 2 | G71: =Sum(E71:F71) -> 2 | H71: =D71*G71 -> 18700.32
C72: Hot Honey Karage Don | D72: =VLOOKUP(C72, 'LIST HPP'!$B$4:$C$39, 2, ) -> 9990.16 | E72: 2 | G72: =Sum(E72:F72) -> 2 | H72: =D72*G72 -> 19980.32
C73: Chicken Katsu Don | D73: =VLOOKUP(C73, 'LIST HPP'!$B$4:$C$39, 2, ) -> 7445.2 | E73: 2 | G73: =Sum(E73:F73) -> 2 | H73: =D73*G73 -> 14890.4
C74: Gyuniku Ala Carte | D74: =VLOOKUP(C74, 'LIST HPP'!$B$4:$C$39, 2, ) -> 17260 | E74: 0 | G74: =Sum(E74:F74) -> 0 | H74: =D74*G74 -> 0
C75: Karage Ala Carte | D75: =VLOOKUP(C75, 'LIST HPP'!$B$4:$C$39, 2, ) -> 14155 | E75: 0 | G75: =Sum(E75:F75) -> 0 | H75: =D75*G75 -> 0
C76: Hot Honey Karage Ala Carte | D76: =VLOOKUP(C76, 'LIST HPP'!$B$4:$C$39, 2, ) -> 15435 | E76: 0 | G76: =Sum(E76:F76) -> 0 | H76: =D76*G76 -> 0
... C93: Kaarage Bento | D93: =VLOOKUP(C93, 'LIST HPP'!$B$4:$C$39, 2, ) -> 12796.31 | E93: 0 | G93: =Sum(E93:F93) -> 0 | H93: =D93*G93 -> 0
C94: Gyuniku Bento | D94: =VLOOKUP(C94, 'LIST HPP'!$B$4:$C$39, 2, FALSE) -> 14616.31 | E94: 0 | G94: =Sum(E94:F94) -> 0 | H94: =D94*G94 -> 0
C95: Matcha Latte | D95: =VLOOKUP(C95, 'LIST HPP'!$B$4:$C$39, 2, FALSE) -> 8805.63 | G95: =sum(E95:F95) -> 0 | H95: =D95*G95 -> 0 | I95: =sum(H95:H125) -> 0 | K95: =(J95-I95)/J95 -> #DIV/0! | L95: =J95-I95 -> 0
C96: Hojicha Latte | D96: =VLOOKUP(C96, 'LIST HPP'!$B$4:$C$39, 2, FALSE) -> 8150.63 | G96: =sum(E96:F96) -> 0 | H96: =D96*G96 -> 0
C97: Choco Latte | D97: =VLOOKUP(C97, 'LIST HPP'!$B$4:$C$39, 2, FALSE) -> 6013.63 | G97: =sum(E97:F97) -> 0 | H97: =D97*G97 -> 0
C98: Choco Ichigo Latte | D98: =VLOOKUP(C98, 'LIST HPP'!$B$4:$C$39, 2, FALSE) -> 7131.43 | G98: =sum(E98:F98) -> 0 | H98: =D98*G98 -> 0
C99: Matcha Tea | D99: =VLOOKUP(C99, 'LIST HPP'!$B$4:$C$39, 2, FALSE) -> 3748.21 | G99: =sum(E99:F99) -> 0 | H99: =D99*G99 -> 0
C100: Ice Tea | D100: =VLOOKUP(C100, 'LIST HPP'!$B$4:$C$39, 2, FALSE) -> 1448.63 | G100: =sum(E100:F100) -> 0 | H100: =D100*G100 -> 0
C101: Gyumeshi | D101: =VLOOKUP(C101, 'LIST HPP'!$B$4:$C$39, 2, FALSE) -> 11670 | G101: =sum(E101:F101) -> 0 | H101: =D101*G101 -> 0
C102: Karage Don | D102: =VLOOKUP(C102, 'LIST HPP'!$B$4:$C$39, 2, FALSE) -> 9350.16 | G102: =sum(E102:F102) -> 0 | H102: =D102*G102 -> 0
C103: Hot Honey Karage Don | D103: =VLOOKUP(C103, 'LIST HPP'!$B$4:$C$39, 2, FALSE) -> 9990.16 | G103: =sum(E103:F103) -> 0 | H103: =D103*G103 -> 0
C104: Chicken Katsu Don | D104: =VLOOKUP(C104, 'LIST HPP'!$B$4:$C$39, 2, FALSE) -> 7445.2 | G104: =sum(E104:F104) -> 0 | H104: =D104*G104 -> 0
C105: Gyuniku Ala Carte | D105: =VLOOKUP(C105, 'LIST HPP'!$B$4:$C$39, 2, FALSE) -> 17260 | G105: =sum(E105:F105) -> 0 | H105: =D105*G105 -> 0
C106: Karage Ala Carte | D106: =VLOOKUP(C106, 'LIST HPP'!$B$4:$C$39, 2, FALSE) -> 14155 | G106: =sum(E106:F106) -> 0 | H106: =D106*G106 -> 0
C107: Hot Honey Karage Ala Carte | D107: =VLOOKUP(C107, 'LIST HPP'!$B$4:$C$39, 2, FALSE) -> 15435 | G107: =sum(E107:F107) -> 0 | H107: =D107*G107 -> 0
... C125: Gyuniku Bento | D125: =VLOOKUP(C125, 'LIST HPP'!$B$4:$C$39, 2, FALSE) -> 14616.31 | G125: =sum(E125:F125) -> 0 | H125: =D125*G125 -> 0
B126: =#REF! -> #REF! | I126: =SUM(I2:I125) -> 850600.75 | J126: =SUM(J2:J125) -> 1376121 | L126: =SUM(L2:L125) -> 525520.25
A128: Stock Opname Inventory | I128: TOTAL JUMLAH ITEM TERJUAL
A129: Menu | B129: No | F129: Data Penjualan
C130: Bahan | D130: Berat | E130: Satuan | F130: Porsi | G130: Total Bahan Terpakai
A131: Gyumeshi | B131: 1 | C131: Daging Blackpepper | D131: 70 | E131: gr | F131: =VLOOKUP(A131, '23062026'!$I$130:$J$158, 2, ) -> 11 | G131: =D131*F131 -> 770
B132: 2 | C132: Bowl Mangkok | D132: 1 | E132: pcs | G132: =D132*F131 -> 11
B133: 3 | C133: Tutup Mangkok | D133: 1 | E133: pcs | G133: =D133*F131 -> 11
B134: 4 | C134: inner tray bowl | D134: 1 | E134: pcs | G134: =D134*F131 -> 11
B135: 5 | C135: Nasi Putih | D135: 180 | E135: gr | G135: =D135*F131 -> 1980
A136: Karage Don | B136: 1 | C136: Ayam Karage | D136: 130 | E136: gr | F136: =VLOOKUP(A136, '23062026'!$I$130:$J$158, 2, ) -> 8 | G136: =D136*F136 -> 1040
B137: 2 | C137: Bowl Mangkok | D137: 1 | E137: pcs | G137: =D137*F136 -> 8
B138: 3 | C138: Tutup Mangkok | D138: 1 | E138: pcs | G138: =D138*F136 -> 8
B139: 4 | C139: Nasi Putih | D139: 180 | E139: gr | G139: =D139*F136 -> 1440
A140: Hot Honey Karage Don | B140: 1 | C140: Ayam Karage | D140: 130 | E140: gr | F140: =VLOOKUP(A140, '23062026'!$I$130:$J$158, 2, ) -> 9 | G140: =D140*F140 -> 1170
B141: 2 | C141: Bowl Mangkok | D141: 1 | E141: pcs | G141: =D141*F140 -> 9
B142: 3 | C142: Tutup Mangkok | D142: 1 | E142: pcs | G142: =D142*F140 -> 9
B143: 4 | C143: Nasi Putih | D143: 180 | E143: gr | G143: =D143*F140 -> 1620
B144: 5 | C144: Hot Honey Sauce | D144: 20 | E144: gr | G144: =D144*F140 -> 180
A145: Gyuniku Ala Carte | B145: 1 | C145: Daging Blackpepper | D145: 140 | E145: gr | F145: =VLOOKUP(A145, '23062026'!$I$130:$J$158, 2, ) -> 1 | G145: =D145*F145 -> 140
B146: 2 | C146: thinwall 500ml | D146: 1 | E146: pcs | G146: =D146*F145 -> 1
A147: Karage Ala Carte | B147: 1 | C147: Ayam Karage | D147: 260 | E147: gr | F147: =VLOOKUP(A147, '23062026'!$I$130:$J$158, 2, ) -> 2 | G147: =D147*F147 -> 520
B148: 2 | C148: Bowl Mangkok | D148: 1 | E148: pcs | G148: =D148*F147 -> 2
B149: 3 | C149: Tutup Mangkok | D149: 1 | E149: pcs | G149: =D149*F147 -> 2
A150: Hot Honey Karage Ala Carte | B150: 1 | C150: Ayam Karage | D150: 260 | E150: gr | F150: =VLOOKUP(A150, '23062026'!$I$130:$J$158, 2, ) -> 0 | G150: =D150*F150 -> 0
B151: 2 | C151: Bowl Mangkok | D151: 1 | E151: pcs | G151: =D151*F150 -> 0
B152: 3 | C152: Tutup Mangkok | D152: 1 | E152: pcs | G152: =D152*F150 -> 0
B153: 4 | C153: Hot Honey Sauce | D153: 40 | E153: gr | G153: =D153*F150 -> 0
A154: Curry Karage Don | B154: 1 | C154: Ayam Karage | D154: 130 | E154: porsi | F154: =VLOOKUP(A154, '23062026'!$I$130:$J$158, 2, ) -> 1 | G154: =D154*F154 -> 130
B155: 2 | C155: Bowl Mangkok | D155: 1 | E155: pcs | G155: =D155*F154 -> 1
B156: 3 | C156: Tutup Mangkok | D156: 1 | E156: pcs | G156: =D156*F154 -> 1
B157: 4 | C157: Nasi Putih | D157: 180 | E157: gr | G157: =D157*F154 -> 180
B158: 5 | C158: Curry Sauce | D158: 1 | E158: pcs | G158: =D158*F154 -> 1
A159: Curry Omurice | B159: 1 | C159: Telor Ayam | D159: 2 | E159: pcs | F159: =VLOOKUP(A159, '23062026'!$I$130:$J$158, 2, ) -> 0 | G159: =D159*F159 -> 0
B160: 2 | C160: Bowl Mangkok | D160: 1 | E160: pcs | G160: =D160*F159 -> 0
B161: 3 | C161: Tutup Mangkok | D161: 1 | E161: pcs | G161: =D161*F159 -> 0
B162: 4 | C162: Nasi Putih | D162: 180 | E162: gr | G162: =D162*F159 -> 0
B163: 5 | C163: Curry Sauce | D163: 1 | E163: pcs | G163: =D163*F159 -> 0
B164: 6 | C164: Gula Pasir | D164: 3 | E164: gr | G164: =D164*F159 -> 0
B165: 7 | C165: Dashi Halal | D165: 3 | E165: gr | G165: =D165*F159 -> 0
B166: 8 | C166: Mirin Halal | D166: 5 | E166: gr | G166: =D166*F159 -> 0
A167: Miso Sup | B167: 1 | C167: miso soup | D167: 1 | E167: porsi | F167: =VLOOKUP(A167, '23062026'!$I$130:$J$158, 2, ) -> 7 | G167: =D167*F167 -> 7
B168: 2 | C168: daun bawang | D168: 1 | E168: Pcs | G168: =D168*F167 -> 7
...

Sheet 22062026
A1: PLATFORM | B1: Tanggal | C1: Nama Item | D1: HPP | E1: Jumlah | F1: Jumlah QR | G1: Total Jumlah | H1: Total | I1: Total HPP | J1: Uang Masuk | K1: Margin | L1: Gross Profit
A2: SHOPEE | C2: Matcha Latte | D2: =VLOOKUP(C2, 'LIST HPP'!$B$4:$C$39, 2, ) -> 8805.63 | E2: 1 | G2: =sum(E2:F2) -> 1 | H2: =D2*G2 -> 8805.63 | I2: =sum(H2:H32) -> 610271.36 | J2: 971818 | K2: =(J2-I2)/J2 -> 0.37203122 | L2: =J2-I2 -> 361546.64
C3: Hojicha Latte | D3: =VLOOKUP(C3, 'LIST HPP'!$B$4:$C$39, 2, ) -> 8150.63 | E3: 0 | G3: =sum(E3:F3) -> 0 | H3: =D3*G3 -> 0
C4: Choco Latte | D4: =VLOOKUP(C4, 'LIST HPP'!$B$4:$C$39, 2, ) -> 6013.63 | E4: 0 | G4: =sum(E4:F4) -> 0 | H4: =D4*G4 -> 0
C5: Choco Ichigo Latte | D5: =VLOOKUP(C5, 'LIST HPP'!$B$4:$C$39, 2, ) -> 7131.43 | E5: 0 | G5: =sum(E5:F5) -> 0 | H5: =D5*G5 -> 0
C6: Matcha Tea | D6: =VLOOKUP(C6, 'LIST HPP'!$B$4:$C$39, 2, ) -> 3748.21 | E6: 5 | G6: =sum(E6:F6) -> 5 | H6: =D6*G6 -> 18741.05
C7: Ice Tea | D7: =VLOOKUP(C7, 'LIST HPP'!$B$4:$C$39, 2, ) -> 1448.63 | E7: 6 | G7: =sum(E7:F7) -> 6 | H7: =D7*G7 -> 8691.78
C8: Gyumeshi | D8: =VLOOKUP(C8, 'LIST HPP'!$B$4:$C$39, 2, ) -> 11670 | E8: 9 | G8: =sum(E8:F8) -> 9 | H8: =D8*G8 -> 105030
C9: Karage Don | D9: =VLOOKUP(C9, 'LIST HPP'!$B$4:$C$39, 2, ) -> 9350.16 | E9: 17 | G9: =sum(E9:F9) -> 17 | H9: =D9*G9 -> 158952.72
C10: Hot Honey Karage Don | D10: =VLOOKUP(C10, 'LIST HPP'!$B$4:$C$39, 2, ) -> 9990.16 | E10: 3 | G10: =sum(E10:F10) -> 3 | H10: =D10*G10 -> 29970.48
C11: Chicken Katsu Don | D11: =VLOOKUP(C11, 'LIST HPP'!$B$4:$C$39, 2, ) -> 7445.2 | E11: 22 | G11: =sum(E11:F11) -> 22 | H11: =D11*G11 -> 163794.4
C12: Gyuniku Ala Carte | D12: =VLOOKUP(C12, 'LIST HPP'!$B$4:$C$39, 2, ) -> 17260 | E12: 0 | G12: =sum(E12:F12) -> 0 | H12: =D12*G12 -> 0
C13: Karage Ala Carte | D13: =VLOOKUP(C13, 'LIST HPP'!$B$4:$C$39, 2, ) -> 14155 | E13: 0 | G13: =sum(E13:F13) -> 0 | H13: =D13*G13 -> 0
C14: Hot Honey Karage Ala Carte | D14: =VLOOKUP(C14, 'LIST HPP'!$B$4:$C$39, 2, ) -> 15435 | E14: 1 | G14: =sum(E14:F14) -> 1 | H14: =D14*G14 -> 15435
... C32: Gyuniku Bento | D32: =VLOOKUP(C32, 'LIST HPP'!$B$4:$C$39, 2, ) -> 14616.31 | E32: 0 | G32: =sum(E32:F32) -> 0 | H32: =D32*G32 -> 0
A33: GRAB/ OFFLINE Q | C33: Matcha Latte | D33: =VLOOKUP(C33, 'LIST HPP'!$B$4:$C$39, 2, ) -> 8805.63 | E33: 0 | G33: =SUM(E33:F33) -> 0 | H33: =D33*G33 -> 0 | I33: =sum(H33:H63) -> 557174.26 | J33: 1012498 | K33: =(J33-I33)/J33 -> 0.44970335 | L33: =J33-I33 -> 455323.74
C34: Hojicha Latte | D34: =VLOOKUP(C34, 'LIST HPP'!$B$4:$C$39, 2, ) -> 8150.63 | E34: 0 | G34: =SUM(E34:F34) -> 0 | H34: =D34*G34 -> 0
C35: Choco Latte | D35: =VLOOKUP(C35, 'LIST HPP'!$B$4:$C$39, 2, ) -> 6013.63 | E35: 0 | G35: =SUM(E35:F35) -> 0 | H35: =D35*G35 -> 0
C36: Choco Ichigo Latte | D36: =VLOOKUP(C36, 'LIST HPP'!$B$4:$C$39, 2, ) -> 7131.43 | E36: 0 | G36: =SUM(E36:F36) -> 0 | H36: =D36*G36 -> 0
C37: Matcha Tea | D37: =VLOOKUP(C37, 'LIST HPP'!$B$4:$C$39, 2, ) -> 3748.21 | E37: 0 | G37: =SUM(E37:F37) -> 0 | H37: =D37*G37 -> 0
C38: Ice Tea | D38: =VLOOKUP(C38, 'LIST HPP'!$B$4:$C$39, 2, ) -> 1448.63 | E38: 2 | G38: =SUM(E38:F38) -> 2 | H38: =D38*G38 -> 2897.26
C39: Gyumeshi | D39: =VLOOKUP(C39, 'LIST HPP'!$B$4:$C$39, 2, ) -> 11670 | E39: 7 | G39: =SUM(E39:F39) -> 7 | H39: =D39*G39 -> 81690
C40: Karage Don | D40: =VLOOKUP(C40, 'LIST HPP'!$B$4:$C$39, 2, ) -> 9350.16 | E40: 1 | G40: =SUM(E40:F40) -> 1 | H40: =D40*G40 -> 9350.16
C41: Hot Honey Karage Don | D41: =VLOOKUP(C41, 'LIST HPP'!$B$4:$C$39, 2, ) -> 9990.16 | E41: 6 | G41: =SUM(E41:F41) -> 6 | H41: =D41*G41 -> 59940.96
C42: Chicken Katsu Don | D42: =VLOOKUP(C42, 'LIST HPP'!$B$4:$C$39, 2, ) -> 7445.2 | E42: 18 | G42: =SUM(E42:F42) -> 18 | H42: =D42*G42 -> 134013.6
C43: Gyuniku Ala Carte | D43: =VLOOKUP(C43, 'LIST HPP'!$B$4:$C$39, 2, ) -> 17260 | E43: 1 | G43: =SUM(E43:F43) -> 1 | H43: =D43*G43 -> 17260
C44: Karage Ala Carte | D44: =VLOOKUP(C44, 'LIST HPP'!$B$4:$C$39, 2, ) -> 14155 | E44: 3 | G44: =SUM(E44:F44) -> 3 | H44: =D44*G44 -> 42465
C45: Hot Honey Karage Ala Carte | D45: =VLOOKUP(C45, 'LIST HPP'!$B$4:$C$39, 2, ) -> 15435 | E45: 3 | G45: =SUM(E45:F45) -> 3 | H45: =D45*G45 -> 46305
... C63: Gyuniku Bento | D63: =VLOOKUP(C63, 'LIST HPP'!$B$4:$C$39, 2, ) -> 14616.31 | E63: 0 | G63: =SUM(E63:F63) -> 0 | H63: =D63*G63 -> 0
A64: GOJEK | C64: Matcha Latte | D64: =VLOOKUP(C64, 'LIST HPP'!$B$4:$C$39, 2, ) -> 8805.63 | E64: 0 | G64: =Sum(E64:F64) -> 0 | H64: =D64*G64 -> 0 | I64: =sum(H64:H94) -> 37817.76 | J64: 61912 | K64: =(J64-I64)/J64 -> 0.38916914 | L64: =J64-I64 -> 24094.24
C65: Hojicha Latte | D65: =VLOOKUP(C65, 'LIST HPP'!$B$4:$C$39, 2, ) -> 8150.63 | E65: 0 | G65: =Sum(E65:F65) -> 0 | H65: =D65*G65 -> 0
C66: Choco Latte | D66: =VLOOKUP(C66, 'LIST HPP'!$B$4:$C$39, 2, ) -> 6013.63 | E66: 0 | G66: =Sum(E66:F66) -> 0 | H66: =D66*G66 -> 0
C67: Choco Ichigo Latte | D67: =VLOOKUP(C67, 'LIST HPP'!$B$4:$C$39, 2, ) -> 7131.43 | E67: 0 | G67: =Sum(E67:F67) -> 0 | H67: =D67*G67 -> 0
C68: Matcha Tea | D68: =VLOOKUP(C68, 'LIST HPP'!$B$4:$C$39, 2, ) -> 3748.21 | E68: 0 | G68: =Sum(E68:F68) -> 0 | H68: =D68*G68 -> 0
C69: Ice Tea | D69: =VLOOKUP(C69, 'LIST HPP'!$B$4:$C$39, 2, ) -> 1448.63 | E69: 0 | G69: =Sum(E69:F69) -> 0 | H69: =D69*G69 -> 0
C70: Gyumeshi | D70: =VLOOKUP(C70, 'LIST HPP'!$B$4:$C$39, 2, ) -> 11670 | E70: 0 | G70: =Sum(E70:F70) -> 0 | H70: =D70*G70 -> 0
C71: Karage Don | D71: =VLOOKUP(C71, 'LIST HPP'!$B$4:$C$39, 2, ) -> 9350.16 | E71: 0 | G71: =Sum(E71:F71) -> 0 | H71: =D71*G71 -> 0
C72: Hot Honey Karage Don | D72: =VLOOKUP(C72, 'LIST HPP'!$B$4:$C$39, 2, ) -> 9990.16 | E72: 0 | G72: =Sum(E72:F72) -> 0 | H72: =D72*G72 -> 0
C73: Chicken Katsu Don | D73: =VLOOKUP(C73, 'LIST HPP'!$B$4:$C$39, 2, ) -> 7445.2 | E73: 3 | G73: =Sum(E73:F73) -> 3 | H73: =D73*G73 -> 22335.6
C74: Gyuniku Ala Carte | D74: =VLOOKUP(C74, 'LIST HPP'!$B$4:$C$39, 2, ) -> 17260 | E74: 0 | G74: =Sum(E74:F74) -> 0 | H74: =D74*G74 -> 0
C75: Karage Ala Carte | D75: =VLOOKUP(C75, 'LIST HPP'!$B$4:$C$39, 2, ) -> 14155 | E75: 0 | G75: =Sum(E75:F75) -> 0 | H75: =D75*G75 -> 0
C76: Hot Honey Karage Ala Carte | D76: =VLOOKUP(C76, 'LIST HPP'!$B$4:$C$39, 2, ) -> 15435 | E76: 0 | G76: =Sum(E76:F76) -> 0 | H76: =D76*G76 -> 0
... C93: Kaarage Bento | D93: =VLOOKUP(C93, 'LIST HPP'!$B$4:$C$39, 2, ) -> 12796.31 | E93: 0 | G93: =Sum(E93:F93) -> 0 | H93: =D93*G93 -> 0
C94: Gyuniku Bento | D94: =VLOOKUP(C94, 'LIST HPP'!$B$4:$C$39, 2, FALSE) -> 14616.31 | E94: 0 | G94: =Sum(E94:F94) -> 0 | H94: =D94*G94 -> 0
C95: Matcha Latte | D95: =VLOOKUP(C95, 'LIST HPP'!$B$4:$C$39, 2, FALSE) -> 8805.63 | G95: =sum(E95:F95) -> 0 | H95: =D95*G95 -> 0 | I95: =sum(H95:H125) -> 0 | K95: =(J95-I95)/J95 -> #DIV/0! | L95: =J95-I95 -> 0
C96: Hojicha Latte | D96: =VLOOKUP(C96, 'LIST HPP'!$B$4:$C$39, 2, FALSE) -> 8150.63 | G96: =sum(E96:F96) -> 0 | H96: =D96*G96 -> 0
C97: Choco Latte | D97: =VLOOKUP(C97, 'LIST HPP'!$B$4:$C$39, 2, FALSE) -> 6013.63 | G97: =sum(E97:F97) -> 0 | H97: =D97*G97 -> 0
C98: Choco Ichigo Latte | D98: =VLOOKUP(C98, 'LIST HPP'!$B$4:$C$39, 2, FALSE) -> 7131.43 | G98: =sum(E98:F98) -> 0 | H98: =D98*G98 -> 0
C99: Matcha Tea | D99: =VLOOKUP(C99, 'LIST HPP'!$B$4:$C$39, 2, FALSE) -> 3748.21 | G99: =sum(E99:F99) -> 0 | H99: =D99*G99 -> 0
C100: Ice Tea | D100: =VLOOKUP(C100, 'LIST HPP'!$B$4:$C$39, 2, FALSE) -> 1448.63 | G100: =sum(E100:F100) -> 0 | H100: =D100*G100 -> 0
C101: Gyumeshi | D101: =VLOOKUP(C101, 'LIST HPP'!$B$4:$C$39, 2, FALSE) -> 11670 | G101: =sum(E101:F101) -> 0 | H101: =D101*G101 -> 0
C102: Karage Don | D102: =VLOOKUP(C102, 'LIST HPP'!$B$4:$C$39, 2, FALSE) -> 9350.16 | G102: =sum(E102:F102) -> 0 | H102: =D102*G102 -> 0
C103: Hot Honey Karage Don | D103: =VLOOKUP(C103, 'LIST HPP'!$B$4:$C$39, 2, FALSE) -> 9990.16 | G103: =sum(E103:F103) -> 0 | H103: =D103*G103 -> 0
C104: Chicken Katsu Don | D104: =VLOOKUP(C104, 'LIST HPP'!$B$4:$C$39, 2, FALSE) -> 7445.2 | G104: =sum(E104:F104) -> 0 | H104: =D104*G104 -> 0
C105: Gyuniku Ala Carte | D105: =VLOOKUP(C105, 'LIST HPP'!$B$4:$C$39, 2, FALSE) -> 17260 | G105: =sum(E105:F105) -> 0 | H105: =D105*G105 -> 0
C106: Karage Ala Carte | D106: =VLOOKUP(C106, 'LIST HPP'!$B$4:$C$39, 2, FALSE) -> 14155 | G106: =sum(E106:F106) -> 0 | H106: =D106*G106 -> 0
C107: Hot Honey Karage Ala Carte | D107: =VLOOKUP(C107, 'LIST HPP'!$B$4:$C$39, 2, FALSE) -> 15435 | G107: =sum(E107:F107) -> 0 | H107: =D107*G107 -> 0
... C125: Gyuniku Bento | D125: =VLOOKUP(C125, 'LIST HPP'!$B$4:$C$39, 2, FALSE) -> 14616.31 | G125: =sum(E125:F125) -> 0 | H125: =D125*G125 -> 0
B126: =#REF! -> #REF! | I126: =SUM(I2:I125) -> 1205263.4 | J126: =SUM(J2:J125) -> 2046228 | L126: =SUM(L2:L125) -> 840964.62
A128: Stock Opname Inventory | I128: TOTAL JUMLAH ITEM TERJUAL
A129: Menu | B129: No | F129: Data Penjualan
C130: Bahan | D130: Berat | E130: Satuan | F130: Porsi | G130: Total Bahan Terpakai
A131: Gyumeshi | B131: 1 | C131: Daging Blackpepper | D131: 70 | E131: gr | F131: =VLOOKUP(A131, '22062026'!$I$130:$J$158, 2, ) -> 16 | G131: =D131*F131 -> 1120
B132: 2 | C132: Bowl Mangkok | D132: 1 | E132: pcs | G132: =D132*F131 -> 16
B133: 3 | C133: Tutup Mangkok | D133: 1 | E133: pcs | G133: =D133*F131 -> 16
B134: 4 | C134: inner tray bowl | D134: 1 | E134: pcs | G134: =D134*F131 -> 16
B135: 5 | C135: Nasi Putih | D135: 180 | E135: gr | G135: =D135*F131 -> 2880
A136: Karage Don | B136: 1 | C136: Ayam Karage | D136: 130 | E136: gr | F136: =VLOOKUP(A136, '22062026'!$I$130:$J$158, 2, ) -> 18 | G136: =D136*F136 -> 2340
B137: 2 | C137: Bowl Mangkok | D137: 1 | E137: pcs | G137: =D137*F136 -> 18
B138: 3 | C138: Tutup Mangkok | D138: 1 | E138: pcs | G138: =D138*F136 -> 18
B139: 4 | C139: Nasi Putih | D139: 180 | E139: gr | G139: =D139*F136 -> 3240
A140: Hot Honey Karage Don | B140: 1 | C140: Ayam Karage | D140: 130 | E140: gr | F140: =VLOOKUP(A140, '22062026'!$I$130:$J$158, 2, ) -> 9 | G140: =D140*F140 -> 1170
B141: 2 | C141: Bowl Mangkok | D141: 1 | E141: pcs | G141: =D141*F140 -> 9
B142: 3 | C142: Tutup Mangkok | D142: 1 | E142: pcs | G142: =D142*F140 -> 9
B143: 4 | C143: Nasi Putih | D143: 180 | E143: gr | G143: =D143*F140 -> 1620
B144: 5 | C144: Hot Honey Sauce | D144: 20 | E144: gr | G144: =D144*F140 -> 180
A145: Gyuniku Ala Carte | B145: 1 | C145: Daging Blackpepper | D145: 140 | E145: gr | F145: =VLOOKUP(A145, '22062026'!$I$130:$J$158, 2, ) -> 1 | G145: =D145*F145 -> 140
B146: 2 | C146: thinwall 500ml | D146: 1 | E146: pcs | G146: =D146*F145 -> 1
A147: Karage Ala Carte | B147: 1 | C147: Ayam Karage | D147: 260 | E147: gr | F147: =VLOOKUP(A147, '22062026'!$I$130:$J$158, 2, ) -> 3 | G147: =D147*F147 -> 780
B148: 2 | C148: Bowl Mangkok | D148: 1 | E148: pcs | G148: =D148*F147 -> 3
B149: 3 | C149: Tutup Mangkok | D149: 1 | E149: pcs | G149: =D149*F147 -> 3
A150: Hot Honey Karage Ala Carte | B150: 1 | C150: Ayam Karage | D150: 260 | E150: gr | F150: =VLOOKUP(A150, '22062026'!$I$130:$J$158, 2, ) -> 4 | G150: =D150*F150 -> 1040
B151: 2 | C151: Bowl Mangkok | D151: 1 | E151: pcs | G151: =D151*F150 -> 4
B152: 3 | C152: Tutup Mangkok | D152: 1 | E152: pcs | G152: =D152*F150 -> 4
B153: 4 | C153: Hot Honey Sauce | D153: 40 | E153: gr | G153: =D153*F150 -> 160
A154: Curry Karage Don | B154: 1 | C154: Ayam Karage | D154: 130 | E154: porsi | F154: =VLOOKUP(A154, '22062026'!$I$130:$J$158, 2, ) -> 1 | G154: =D154*F154 -> 130
B155: 2 | C155: Bowl Mangkok | D155: 1 | E155: pcs | G155: =D155*F154 -> 1
B156: 3 | C156: Tutup Mangkok | D156: 1 | E156: pcs | G156: =D156*F154 -> 1
B157: 4 | C157: Nasi Putih | D157: 180 | E157: gr | G157: =D157*F154 -> 180
B158: 5 | C158: Curry Sauce | D158: 1 | E158: pcs | G158: =D158*F154 -> 1
A159: Curry Omurice | B159: 1 | C159: Telor Ayam | D159: 2 | E159: pcs | F159: =VLOOKUP(A159, '22062026'!$I$130:$J$158, 2, ) -> 0 | G159: =D159*F159 -> 0
B160: 2 | C160: Bowl Mangkok | D160: 1 | E160: pcs | G160: =D160*F159 -> 0
B161: 3 | C161: Tutup Mangkok | D161: 1 | E161: pcs | G161: =D161*F159 -> 0
B162: 4 | C162: Nasi Putih | D162: 180 | E162: gr | G162: =D162*F159 -> 0
B163: 5 | C163: Curry Sauce | D163: 1 | E163: pcs | G163: =D163*F159 -> 0
B164: 6 | C164: Gula Pasir | D164: 3 | E164: gr | G164: =D164*F159 -> 0
B165: 7 | C165: Dashi Halal | D165: 3 | E165: gr | G165: =D165*F159 -> 0
B166: 8 | C166: Mirin Halal | D166: 5 | E166: gr | G166: =D166*F159 -> 0
A167: Miso Sup | B167: 1 | C167: miso soup | D167: 1 | E167: porsi | F167: =VLOOKUP(A167, '22062026'!$I$130:$J$158, 2, ) -> 13 | G167: =D167*F167 -> 13
B168: 2 | C168: daun bawang | D168: 1 | E168: Pcs | G168: =D168*F167 -> 13
...

Sheet 21062026
A1: PLATFORM | B1: Tanggal | C1: Nama Item | D1: HPP | E1: Jumlah | F1: Jumlah QR | G1: Total Jumlah | H1: Total | I1: Total HPP | J1: Uang Masuk | K1: Margin | L1: Gross Profit
A2: SHOPEE | C2: Matcha Latte | D2: =VLOOKUP(C2, 'LIST HPP'!$B$4:$C$39, 2, ) -> 8805.63 | E2: 2 | G2: =sum(E2:F2) -> 2 | H2: =D2*G2 -> 17611.26 | I2: =sum(H2:H32) -> 708574.15 | J2: 1103513 | K2: =(J2-I2)/J2 -> 0.35789234 | L2: =J2-I2 -> 394938.85
C3: Hojicha Latte | D3: =VLOOKUP(C3, 'LIST HPP'!$B$4:$C$39, 2, ) -> 8150.63 | E3: 0 | G3: =sum(E3:F3) -> 0 | H3: =D3*G3 -> 0
C4: Choco Latte | D4: =VLOOKUP(C4, 'LIST HPP'!$B$4:$C$39, 2, ) -> 6013.63 | E4: 0 | G4: =sum(E4:F4) -> 0 | H4: =D4*G4 -> 0
C5: Choco Ichigo Latte | D5: =VLOOKUP(C5, 'LIST HPP'!$B$4:$C$39, 2, ) -> 7131.43 | E5: 0 | G5: =sum(E5:F5) -> 0 | H5: =D5*G5 -> 0
C6: Matcha Tea | D6: =VLOOKUP(C6, 'LIST HPP'!$B$4:$C$39, 2, ) -> 3748.21 | E6: 3 | G6: =sum(E6:F6) -> 3 | H6: =D6*G6 -> 11244.63
C7: Ice Tea | D7: =VLOOKUP(C7, 'LIST HPP'!$B$4:$C$39, 2, ) -> 1448.63 | E7: 2 | G7: =sum(E7:F7) -> 2 | H7: =D7*G7 -> 2897.26
C8: Gyumeshi | D8: =VLOOKUP(C8, 'LIST HPP'!$B$4:$C$39, 2, ) -> 11670 | E8: 5 | G8: =sum(E8:F8) -> 5 | H8: =D8*G8 -> 58350
C9: Karage Don | D9: =VLOOKUP(C9, 'LIST HPP'!$B$4:$C$39, 2, ) -> 9350.16 | E9: 14 | G9: =sum(E9:F9) -> 14 | H9: =D9*G9 -> 130902.24
C10: Hot Honey Karage Don | D10: =VLOOKUP(C10, 'LIST HPP'!$B$4:$C$39, 2, ) -> 9990.16 | E10: 2 | G10: =sum(E10:F10) -> 2 | H10: =D10*G10 -> 19980.32
C11: Chicken Katsu Don | D11: =VLOOKUP(C11, 'LIST HPP'!$B$4:$C$39, 2, ) -> 7445.2 | E11: 39 | G11: =sum(E11:F11) -> 39 | H11: =D11*G11 -> 290362.8
C12: Gyuniku Ala Carte | D12: =VLOOKUP(C12, 'LIST HPP'!$B$4:$C$39, 2, ) -> 17260 | E12: 0 | G12: =sum(E12:F12) -> 0 | H12: =D12*G12 -> 0
C13: Karage Ala Carte | D13: =VLOOKUP(C13, 'LIST HPP'!$B$4:$C$39, 2, ) -> 14155 | E13: 2 | G13: =sum(E13:F13) -> 2 | H13: =D13*G13 -> 28310
C14: Hot Honey Karage Ala Carte | D14: =VLOOKUP(C14, 'LIST HPP'!$B$4:$C$39, 2, ) -> 15435 | E14: 2 | G14: =sum(E14:F14) -> 2 | H14: =D14*G14 -> 30870
... C32: Gyuniku Bento | D32: =VLOOKUP(C32, 'LIST HPP'!$B$4:$C$39, 2, ) -> 14616.31 | E32: 0 | G32: =sum(E32:F32) -> 0 | H32: =D32*G32 -> 0
A33: GRAB/ OFFLINE Q | C33: Matcha Latte | D33: =VLOOKUP(C33, 'LIST HPP'!$B$4:$C$39, 2, ) -> 8805.63 | E33: 0 | F33: 1 | G33: =SUM(E33:F33) -> 1 | H33: =D33*G33 -> 8805.63 | I33: =sum(H33:H63) -> 593267.74 | J33: 1052812 | K33: =(J33-I33)/J33 -> 0.43649223 | L33: =J33-I33 -> 459544.26
C34: Hojicha Latte | D34: =VLOOKUP(C34, 'LIST HPP'!$B$4:$C$39, 2, ) -> 8150.63 | E34: 0 | F34: 0 | G34: =SUM(E34:F34) -> 0 | H34: =D34*G34 -> 0
C35: Choco Latte | D35: =VLOOKUP(C35, 'LIST HPP'!$B$4:$C$39, 2, ) -> 6013.63 | E35: 0 | F35: 0 | G35: =SUM(E35:F35) -> 0 | H35: =D35*G35 -> 0
C36: Choco Ichigo Latte | D36: =VLOOKUP(C36, 'LIST HPP'!$B$4:$C$39, 2, ) -> 7131.43 | E36: 0 | F36: 0 | G36: =SUM(E36:F36) -> 0 | H36: =D36*G36 -> 0
C37: Matcha Tea | D37: =VLOOKUP(C37, 'LIST HPP'!$B$4:$C$39, 2, ) -> 3748.21 | E37: 0 | F37: 0 | G37: =SUM(E37:F37) -> 0 | H37: =D37*G37 -> 0
C38: Ice Tea | D38: =VLOOKUP(C38, 'LIST HPP'!$B$4:$C$39, 2, ) -> 1448.63 | E38: 1 | F38: 0 | G38: =SUM(E38:F38) -> 1 | H38: =D38*G38 -> 1448.63
C39: Gyumeshi | D39: =VLOOKUP(C39, 'LIST HPP'!$B$4:$C$39, 2, ) -> 11670 | E39: 5 | F39: 0 | G39: =SUM(E39:F39) -> 5 | H39: =D39*G39 -> 58350
C40: Karage Don | D40: =VLOOKUP(C40, 'LIST HPP'!$B$4:$C$39, 2, ) -> 9350.16 | E40: 0 | F40: 0 | G40: =SUM(E40:F40) -> 0 | H40: =D40*G40 -> 0
C41: Hot Honey Karage Don | D41: =VLOOKUP(C41, 'LIST HPP'!$B$4:$C$39, 2, ) -> 9990.16 | E41: 1 | F41: 0 | G41: =SUM(E41:F41) -> 1 | H41: =D41*G41 -> 9990.16
C42: Chicken Katsu Don | D42: =VLOOKUP(C42, 'LIST HPP'!$B$4:$C$39, 2, ) -> 7445.2 | E42: 46 | F42: 0 | G42: =SUM(E42:F42) -> 46 | H42: =D42*G42 -> 342479.2
C43: Gyuniku Ala Carte | D43: =VLOOKUP(C43, 'LIST HPP'!$B$4:$C$39, 2, ) -> 17260 | E43: 0 | F43: 0 | G43: =SUM(E43:F43) -> 0 | H43: =D43*G43 -> 0
C44: Karage Ala Carte | D44: =VLOOKUP(C44, 'LIST HPP'!$B$4:$C$39, 2, ) -> 14155 | E44: 1 | F44: 0 | G44: =SUM(E44:F44) -> 1 | H44: =D44*G44 -> 14155
C45: Hot Honey Karage Ala Carte | D45: =VLOOKUP(C45, 'LIST HPP'!$B$4:$C$39, 2, ) -> 15435 | E45: 2 | F45: 0 | G45: =SUM(E45:F45) -> 2 | H45: =D45*G45 -> 30870
... C63: Gyuniku Bento | D63: =VLOOKUP(C63, 'LIST HPP'!$B$4:$C$39, 2, ) -> 14616.31 | E63: 0 | F63: 0 | G63: =SUM(E63:F63) -> 0 | H63: =D63*G63 -> 0
A64: GOJEK | C64: Matcha Latte | D64: =VLOOKUP(C64, 'LIST HPP'!$B$4:$C$39, 2, ) -> 8805.63 | E64: 1 | G64: =Sum(E64:F64) -> 1 | H64: =D64*G64 -> 8805.63 | I64: =sum(H64:H94) -> 32249.73 | J64: 62872 | K64: =(J64-I64)/J64 -> 0.48705735 | L64: =J64-I64 -> 30622.27
C65: Hojicha Latte | D65: =VLOOKUP(C65, 'LIST HPP'!$B$4:$C$39, 2, ) -> 8150.63 | E65: 0 | G65: =Sum(E65:F65) -> 0 | H65: =D65*G65 -> 0
C66: Choco Latte | D66: =VLOOKUP(C66, 'LIST HPP'!$B$4:$C$39, 2, ) -> 6013.63 | E66: 0 | G66: =Sum(E66:F66) -> 0 | H66: =D66*G66 -> 0
C67: Choco Ichigo Latte | D67: =VLOOKUP(C67, 'LIST HPP'!$B$4:$C$39, 2, ) -> 7131.43 | E67: 0 | G67: =Sum(E67:F67) -> 0 | H67: =D67*G67 -> 0
C68: Matcha Tea | D68: =VLOOKUP(C68, 'LIST HPP'!$B$4:$C$39, 2, ) -> 3748.21 | E68: 0 | G68: =Sum(E68:F68) -> 0 | H68: =D68*G68 -> 0
C69: Ice Tea | D69: =VLOOKUP(C69, 'LIST HPP'!$B$4:$C$39, 2, ) -> 1448.63 | E69: 0 | G69: =Sum(E69:F69) -> 0 | H69: =D69*G69 -> 0
C70: Gyumeshi | D70: =VLOOKUP(C70, 'LIST HPP'!$B$4:$C$39, 2, ) -> 11670 | E70: 0 | G70: =Sum(E70:F70) -> 0 | H70: =D70*G70 -> 0
C71: Karage Don | D71: =VLOOKUP(C71, 'LIST HPP'!$B$4:$C$39, 2, ) -> 9350.16 | E71: 0 | G71: =Sum(E71:F71) -> 0 | H71: =D71*G71 -> 0
C72: Hot Honey Karage Don | D72: =VLOOKUP(C72, 'LIST HPP'!$B$4:$C$39, 2, ) -> 9990.16 | E72: 0 | G72: =Sum(E72:F72) -> 0 | H72: =D72*G72 -> 0
C73: Chicken Katsu Don | D73: =VLOOKUP(C73, 'LIST HPP'!$B$4:$C$39, 2, ) -> 7445.2 | E73: 3 | G73: =Sum(E73:F73) -> 3 | H73: =D73*G73 -> 22335.6
C74: Gyuniku Ala Carte | D74: =VLOOKUP(C74, 'LIST HPP'!$B$4:$C$39, 2, ) -> 17260 | E74: 0 | G74: =Sum(E74:F74) -> 0 | H74: =D74*G74 -> 0
C75: Karage Ala Carte | D75: =VLOOKUP(C75, 'LIST HPP'!$B$4:$C$39, 2, ) -> 14155 | E75: 0 | G75: =Sum(E75:F75) -> 0 | H75: =D75*G75 -> 0
C76: Hot Honey Karage Ala Carte | D76: =VLOOKUP(C76, 'LIST HPP'!$B$4:$C$39, 2, ) -> 15435 | E76: 0 | G76: =Sum(E76:F76) -> 0 | H76: =D76*G76 -> 0
... C93: Kaarage Bento | D93: =VLOOKUP(C93, 'LIST HPP'!$B$4:$C$39, 2, ) -> 12796.31 | E93: 0 | G93: =Sum(E93:F93) -> 0 | H93: =D93*G93 -> 0
C94: Gyuniku Bento | D94: =VLOOKUP(C94, 'LIST HPP'!$B$4:$C$39, 2, FALSE) -> 14616.31 | E94: 0 | G94: =Sum(E94:F94) -> 0 | H94: =D94*G94 -> 0
C95: Matcha Latte | D95: =VLOOKUP(C95, 'LIST HPP'!$B$4:$C$39, 2, FALSE) -> 8805.63 | G95: =sum(E95:F95) -> 0 | H95: =D95*G95 -> 0 | I95: =sum(H95:H125) -> 0 | K95: =(J95-I95)/J95 -> #DIV/0! | L95: =J95-I95 -> 0
C96: Hojicha Latte | D96: =VLOOKUP(C96, 'LIST HPP'!$B$4:$C$39, 2, FALSE) -> 8150.63 | G96: =sum(E96:F96) -> 0 | H96: =D96*G96 -> 0
C97: Choco Latte | D97: =VLOOKUP(C97, 'LIST HPP'!$B$4:$C$39, 2, FALSE) -> 6013.63 | G97: =sum(E97:F97) -> 0 | H97: =D97*G97 -> 0
C98: Choco Ichigo Latte | D98: =VLOOKUP(C98, 'LIST HPP'!$B$4:$C$39, 2, FALSE) -> 7131.43 | G98: =sum(E98:F98) -> 0 | H98: =D98*G98 -> 0
C99: Matcha Tea | D99: =VLOOKUP(C99, 'LIST HPP'!$B$4:$C$39, 2, FALSE) -> 3748.21 | G99: =sum(E99:F99) -> 0 | H99: =D99*G99 -> 0
C100: Ice Tea | D100: =VLOOKUP(C100, 'LIST HPP'!$B$4:$C$39, 2, FALSE) -> 1448.63 | G100: =sum(E100:F100) -> 0 | H100: =D100*G100 -> 0
C101: Gyumeshi | D101: =VLOOKUP(C101, 'LIST HPP'!$B$4:$C$39, 2, FALSE) -> 11670 | G101: =sum(E101:F101) -> 0 | H101: =D101*G101 -> 0
C102: Karage Don | D102: =VLOOKUP(C102, 'LIST HPP'!$B$4:$C$39, 2, FALSE) -> 9350.16 | G102: =sum(E102:F102) -> 0 | H102: =D102*G102 -> 0
C103: Hot Honey Karage Don | D103: =VLOOKUP(C103, 'LIST HPP'!$B$4:$C$39, 2, FALSE) -> 9990.16 | G103: =sum(E103:F103) -> 0 | H103: =D103*G103 -> 0
C104: Chicken Katsu Don | D104: =VLOOKUP(C104, 'LIST HPP'!$B$4:$C$39, 2, FALSE) -> 7445.2 | G104: =sum(E104:F104) -> 0 | H104: =D104*G104 -> 0
C105: Gyuniku Ala Carte | D105: =VLOOKUP(C105, 'LIST HPP'!$B$4:$C$39, 2, FALSE) -> 17260 | G105: =sum(E105:F105) -> 0 | H105: =D105*G105 -> 0
C106: Karage Ala Carte | D106: =VLOOKUP(C106, 'LIST HPP'!$B$4:$C$39, 2, FALSE) -> 14155 | G106: =sum(E106:F106) -> 0 | H106: =D106*G106 -> 0
C107: Hot Honey Karage Ala Carte | D107: =VLOOKUP(C107, 'LIST HPP'!$B$4:$C$39, 2, FALSE) -> 15435 | G107: =sum(E107:F107) -> 0 | H107: =D107*G107 -> 0
... C125: Gyuniku Bento | D125: =VLOOKUP(C125, 'LIST HPP'!$B$4:$C$39, 2, FALSE) -> 14616.31 | G125: =sum(E125:F125) -> 0 | H125: =D125*G125 -> 0
B126: =#REF! -> #REF! | I126: =SUM(I2:I125) -> 1334091.6 | J126: =SUM(J2:J125) -> 2219197 | L126: =SUM(L2:L125) -> 885105.38
A128: Stock Opname Inventory | I128: TOTAL JUMLAH ITEM TERJUAL
A129: Menu | B129: No | F129: Data Penjualan
C130: Bahan | D130: Berat | E130: Satuan | F130: Porsi | G130: Total Bahan Terpakai
A131: Gyumeshi | B131: 1 | C131: Daging Blackpepper | D131: 70 | E131: gr | F131: =VLOOKUP(A131, '21062026'!$I$130:$J$158, 2, ) -> 10 | G131: =D131*F131 -> 700
B132: 2 | C132: Bowl Mangkok | D132: 1 | E132: pcs | G132: =D132*F131 -> 10
B133: 3 | C133: Tutup Mangkok | D133: 1 | E133: pcs | G133: =D133*F131 -> 10
B134: 4 | C134: inner tray bowl | D134: 1 | E134: pcs | G134: =D134*F131 -> 10
B135: 5 | C135: Nasi Putih | D135: 180 | E135: gr | G135: =D135*F131 -> 1800
A136: Karage Don | B136: 1 | C136: Ayam Karage | D136: 130 | E136: gr | F136: =VLOOKUP(A136, '21062026'!$I$130:$J$158, 2, ) -> 14 | G136: =D136*F136 -> 1820
B137: 2 | C137: Bowl Mangkok | D137: 1 | E137: pcs | G137: =D137*F136 -> 14
B138: 3 | C138: Tutup Mangkok | D138: 1 | E138: pcs | G138: =D138*F136 -> 14
B139: 4 | C139: Nasi Putih | D139: 180 | E139: gr | G139: =D139*F136 -> 2520
A140: Hot Honey Karage Don | B140: 1 | C140: Ayam Karage | D140: 130 | E140: gr | F140: =VLOOKUP(A140, '21062026'!$I$130:$J$158, 2, ) -> 3 | G140: =D140*F140 -> 390
B141: 2 | C141: Bowl Mangkok | D141: 1 | E141: pcs | G141: =D141*F140 -> 3
B142: 3 | C142: Tutup Mangkok | D142: 1 | E142: pcs | G142: =D142*F140 -> 3
B143: 4 | C143: Nasi Putih | D143: 180 | E143: gr | G143: =D143*F140 -> 540
B144: 5 | C144: Hot Honey Sauce | D144: 20 | E144: gr | G144: =D144*F140 -> 60
A145: Gyuniku Ala Carte | B145: 1 | C145: Daging Blackpepper | D145: 140 | E145: gr | F145: =VLOOKUP(A145, '21062026'!$I$130:$J$158, 2, ) -> 0 | G145: =D145*F145 -> 0
B146: 2 | C146: thinwall 500ml | D146: 1 | E146: pcs | G146: =D146*F145 -> 0
A147: Karage Ala Carte | B147: 1 | C147: Ayam Karage | D147: 260 | E147: gr | F147: =VLOOKUP(A147, '21062026'!$I$130:$J$158, 2, ) -> 3 | G147: =D147*F147 -> 780
B148: 2 | C148: Bowl Mangkok | D148: 1 | E148: pcs | G148: =D148*F147 -> 3
B149: 3 | C149: Tutup Mangkok | D149: 1 | E149: pcs | G149: =D149*F147 -> 3
A150: Hot Honey Karage Ala Carte | B150: 1 | C150: Ayam Karage | D150: 260 | E150: gr | F150: =VLOOKUP(A150, '21062026'!$I$130:$J$158, 2, ) -> 4 | G150: =D150*F150 -> 1040
B151: 2 | C151: Bowl Mangkok | D151: 1 | E151: pcs | G151: =D151*F150 -> 4
B152: 3 | C152: Tutup Mangkok | D152: 1 | E152: pcs | G152: =D152*F150 -> 4
B153: 4 | C153: Hot Honey Sauce | D153: 40 | E153: gr | G153: =D153*F150 -> 160
A154: Curry Karage Don | B154: 1 | C154: Ayam Karage | D154: 130 | E154: porsi | F154: =VLOOKUP(A154, '21062026'!$I$130:$J$158, 2, ) -> 2 | G154: =D154*F154 -> 260
B155: 2 | C155: Bowl Mangkok | D155: 1 | E155: pcs | G155: =D155*F154 -> 2
B156: 3 | C156: Tutup Mangkok | D156: 1 | E156: pcs | G156: =D156*F154 -> 2
B157: 4 | C157: Nasi Putih | D157: 180 | E157: gr | G157: =D157*F154 -> 360
B158: 5 | C158: Curry Sauce | D158: 1 | E158: pcs | G158: =D158*F154 -> 2
A159: Curry Omurice | B159: 1 | C159: Telor Ayam | D159: 2 | E159: pcs | F159: =VLOOKUP(A159, '21062026'!$I$130:$J$158, 2, ) -> 0 | G159: =D159*F159 -> 0
B160: 2 | C160: Bowl Mangkok | D160: 1 | E160: pcs | G160: =D160*F159 -> 0
B161: 3 | C161: Tutup Mangkok | D161: 1 | E161: pcs | G161: =D161*F159 -> 0
B162: 4 | C162: Nasi Putih | D162: 180 | E162: gr | G162: =D162*F159 -> 0
B163: 5 | C163: Curry Sauce | D163: 1 | E163: pcs | G163: =D163*F159 -> 0
B164: 6 | C164: Gula Pasir | D164: 3 | E164: gr | G164: =D164*F159 -> 0
B165: 7 | C165: Dashi Halal | D165: 3 | E165: gr | G165: =D165*F159 -> 0
B166: 8 | C166: Mirin Halal | D166: 5 | E166: gr | G166: =D166*F159 -> 0
A167: Miso Sup | B167: 1 | C167: miso soup | D167: 1 | E167: porsi | F167: =VLOOKUP(A167, '21062026'!$I$130:$J$158, 2, ) -> 12 | G167: =D167*F167 -> 12
B168: 2 | C168: daun bawang | D168: 1 | E168: Pcs | G168: =D168*F167 -> 12
...

Sheet 20062026
A1: PLATFORM | B1: Tanggal | C1: Nama Item | D1: HPP | E1: Jumlah | F1: Jumlah QR | G1: Total Jumlah | H1: Total | I1: Total HPP | J1: Uang Masuk | K1: Margin | L1: Gross Profit
A2: SHOPEE | C2: Matcha Latte | D2: =VLOOKUP(C2, 'LIST HPP'!$B$4:$C$39, 2, ) -> 8805.63 | E2: 1 | G2: =sum(E2:F2) -> 1 | H2: =D2*G2 -> 8805.63 | I2: =sum(H2:H32) -> 374763.61 | J2: 547221 | K2: =(J2-I2)/J2 -> 0.31515126 | L2: =J2-I2 -> 172457.39
C3: Hojicha Latte | D3: =VLOOKUP(C3, 'LIST HPP'!$B$4:$C$39, 2, ) -> 8150.63 | E3: 0 | G3: =sum(E3:F3) -> 0 | H3: =D3*G3 -> 0
C4: Choco Latte | D4: =VLOOKUP(C4, 'LIST HPP'!$B$4:$C$39, 2, ) -> 6013.63 | E4: 0 | G4: =sum(E4:F4) -> 0 | H4: =D4*G4 -> 0
C5: Choco Ichigo Latte | D5: =VLOOKUP(C5, 'LIST HPP'!$B$4:$C$39, 2, ) -> 7131.43 | E5: 0 | G5: =sum(E5:F5) -> 0 | H5: =D5*G5 -> 0
C6: Matcha Tea | D6: =VLOOKUP(C6, 'LIST HPP'!$B$4:$C$39, 2, ) -> 3748.21 | E6: 1 | G6: =sum(E6:F6) -> 1 | H6: =D6*G6 -> 3748.21
C7: Ice Tea | D7: =VLOOKUP(C7, 'LIST HPP'!$B$4:$C$39, 2, ) -> 1448.63 | E7: 2 | G7: =sum(E7:F7) -> 2 | H7: =D7*G7 -> 2897.26
C8: Gyumeshi | D8: =VLOOKUP(C8, 'LIST HPP'!$B$4:$C$39, 2, ) -> 11670 | E8: 3 | G8: =sum(E8:F8) -> 3 | H8: =D8*G8 -> 35010
C9: Karage Don | D9: =VLOOKUP(C9, 'LIST HPP'!$B$4:$C$39, 2, ) -> 9350.16 | E9: 7 | G9: =sum(E9:F9) -> 7 | H9: =D9*G9 -> 65451.12
C10: Hot Honey Karage Don | D10: =VLOOKUP(C10, 'LIST HPP'!$B$4:$C$39, 2, ) -> 9990.16 | E10: 3 | G10: =sum(E10:F10) -> 3 | H10: =D10*G10 -> 29970.48
C11: Chicken Katsu Don | D11: =VLOOKUP(C11, 'LIST HPP'!$B$4:$C$39, 2, ) -> 7445.2 | E11: 23 | G11: =sum(E11:F11) -> 23 | H11: =D11*G11 -> 171239.6
C12: Gyuniku Ala Carte | D12: =VLOOKUP(C12, 'LIST HPP'!$B$4:$C$39, 2, ) -> 17260 | E12: 0 | G12: =sum(E12:F12) -> 0 | H12: =D12*G12 -> 0
C13: Karage Ala Carte | D13: =VLOOKUP(C13, 'LIST HPP'!$B$4:$C$39, 2, ) -> 14155 | E13: 0 | G13: =sum(E13:F13) -> 0 | H13: =D13*G13 -> 0
C14: Hot Honey Karage Ala Carte | D14: =VLOOKUP(C14, 'LIST HPP'!$B$4:$C$39, 2, ) -> 15435 | E14: 0 | G14: =sum(E14:F14) -> 0 | H14: =D14*G14 -> 0
... C32: Gyuniku Bento | D32: =VLOOKUP(C32, 'LIST HPP'!$B$4:$C$39, 2, ) -> 14616.31 | E32: 0 | G32: =sum(E32:F32) -> 0 | H32: =D32*G32 -> 0
A33: GRAB/ OFFLINE Q | C33: Matcha Latte | D33: =VLOOKUP(C33, 'LIST HPP'!$B$4:$C$39, 2, ) -> 8805.63 | E33: 1 | G33: =SUM(E33:F33) -> 1 | H33: =D33*G33 -> 8805.63 | I33: =sum(H33:H63) -> 321010.49 | J33: 538745 | K33: =(J33-I33)/J33 -> 0.40415133 | L33: =J33-I33 -> 217734.51
C34: Hojicha Latte | D34: =VLOOKUP(C34, 'LIST HPP'!$B$4:$C$39, 2, ) -> 8150.63 | E34: 0 | G34: =SUM(E34:F34) -> 0 | H34: =D34*G34 -> 0
C35: Choco Latte | D35: =VLOOKUP(C35, 'LIST HPP'!$B$4:$C$39, 2, ) -> 6013.63 | E35: 0 | G35: =SUM(E35:F35) -> 0 | H35: =D35*G35 -> 0
C36: Choco Ichigo Latte | D36: =VLOOKUP(C36, 'LIST HPP'!$B$4:$C$39, 2, ) -> 7131.43 | E36: 0 | G36: =SUM(E36:F36) -> 0 | H36: =D36*G36 -> 0
C37: Matcha Tea | D37: =VLOOKUP(C37, 'LIST HPP'!$B$4:$C$39, 2, ) -> 3748.21 | E37: 2 | G37: =SUM(E37:F37) -> 2 | H37: =D37*G37 -> 7496.42
C38: Ice Tea | D38: =VLOOKUP(C38, 'LIST HPP'!$B$4:$C$39, 2, ) -> 1448.63 | E38: 1 | G38: =SUM(E38:F38) -> 1 | H38: =D38*G38 -> 1448.63
C39: Gyumeshi | D39: =VLOOKUP(C39, 'LIST HPP'!$B$4:$C$39, 2, ) -> 11670 | E39: 6 | G39: =SUM(E39:F39) -> 6 | H39: =D39*G39 -> 70020
C40: Karage Don | D40: =VLOOKUP(C40, 'LIST HPP'!$B$4:$C$39, 2, ) -> 9350.16 | E40: 1 | G40: =SUM(E40:F40) -> 1 | H40: =D40*G40 -> 9350.16
C41: Hot Honey Karage Don | D41: =VLOOKUP(C41, 'LIST HPP'!$B$4:$C$39, 2, ) -> 9990.16 | E41: 1 | G41: =SUM(E41:F41) -> 1 | H41: =D41*G41 -> 9990.16
C42: Chicken Katsu Don | D42: =VLOOKUP(C42, 'LIST HPP'!$B$4:$C$39, 2, ) -> 7445.2 | E42: 10 | G42: =SUM(E42:F42) -> 10 | H42: =D42*G42 -> 74452
C43: Gyuniku Ala Carte | D43: =VLOOKUP(C43, 'LIST HPP'!$B$4:$C$39, 2, ) -> 17260 | E43: 0 | G43: =SUM(E43:F43) -> 0 | H43: =D43*G43 -> 0
C44: Karage Ala Carte | D44: =VLOOKUP(C44, 'LIST HPP'!$B$4:$C$39, 2, ) -> 14155 | E44: 0 | G44: =SUM(E44:F44) -> 0 | H44: =D44*G44 -> 0
C45: Hot Honey Karage Ala Carte | D45: =VLOOKUP(C45, 'LIST HPP'!$B$4:$C$39, 2, ) -> 15435 | E45: 0 | G45: =SUM(E45:F45) -> 0 | H45: =D45*G45 -> 0
... C63: Gyuniku Bento | D63: =VLOOKUP(C63, 'LIST HPP'!$B$4:$C$39, 2, ) -> 14616.31 | E63: 1 | G63: =SUM(E63:F63) -> 1 | H63: =D63*G63 -> 14616.31
A64: GOJEK | C64: Matcha Latte | D64: =VLOOKUP(C64, 'LIST HPP'!$B$4:$C$39, 2, ) -> 8805.63 | E64: 0 | G64: =Sum(E64:F64) -> 0 | H64: =D64*G64 -> 0 | I64: =sum(H64:H94) -> 41271.31 | J64: 74682 | K64: =(J64-I64)/J64 -> 0.44737273 | L64: =J64-I64 -> 33410.69
C65: Hojicha Latte | D65: =VLOOKUP(C65, 'LIST HPP'!$B$4:$C$39, 2, ) -> 8150.63 | E65: 0 | G65: =Sum(E65:F65) -> 0 | H65: =D65*G65 -> 0
C66: Choco Latte | D66: =VLOOKUP(C66, 'LIST HPP'!$B$4:$C$39, 2, ) -> 6013.63 | E66: 0 | G66: =Sum(E66:F66) -> 0 | H66: =D66*G66 -> 0
C67: Choco Ichigo Latte | D67: =VLOOKUP(C67, 'LIST HPP'!$B$4:$C$39, 2, ) -> 7131.43 | E67: 0 | G67: =Sum(E67:F67) -> 0 | H67: =D67*G67 -> 0
C68: Matcha Tea | D68: =VLOOKUP(C68, 'LIST HPP'!$B$4:$C$39, 2, ) -> 3748.21 | E68: 1 | G68: =Sum(E68:F68) -> 1 | H68: =D68*G68 -> 3748.21
C69: Ice Tea | D69: =VLOOKUP(C69, 'LIST HPP'!$B$4:$C$39, 2, ) -> 1448.63 | E69: 0 | G69: =Sum(E69:F69) -> 0 | H69: =D69*G69 -> 0
C70: Gyumeshi | D70: =VLOOKUP(C70, 'LIST HPP'!$B$4:$C$39, 2, ) -> 11670 | E70: 0 | G70: =Sum(E70:F70) -> 0 | H70: =D70*G70 -> 0
C71: Karage Don | D71: =VLOOKUP(C71, 'LIST HPP'!$B$4:$C$39, 2, ) -> 9350.16 | E71: 0 | G71: =Sum(E71:F71) -> 0 | H71: =D71*G71 -> 0
C72: Hot Honey Karage Don | D72: =VLOOKUP(C72, 'LIST HPP'!$B$4:$C$39, 2, ) -> 9990.16 | E72: 0 | G72: =Sum(E72:F72) -> 0 | H72: =D72*G72 -> 0
C73: Chicken Katsu Don | D73: =VLOOKUP(C73, 'LIST HPP'!$B$4:$C$39, 2, ) -> 7445.2 | E73: 3 | G73: =Sum(E73:F73) -> 3 | H73: =D73*G73 -> 22335.6
C74: Gyuniku Ala Carte | D74: =VLOOKUP(C74, 'LIST HPP'!$B$4:$C$39, 2, ) -> 17260 | E74: 0 | G74: =Sum(E74:F74) -> 0 | H74: =D74*G74 -> 0
C75: Karage Ala Carte | D75: =VLOOKUP(C75, 'LIST HPP'!$B$4:$C$39, 2, ) -> 14155 | E75: 0 | G75: =Sum(E75:F75) -> 0 | H75: =D75*G75 -> 0
C76: Hot Honey Karage Ala Carte | D76: =VLOOKUP(C76, 'LIST HPP'!$B$4:$C$39, 2, ) -> 15435 | E76: 0 | G76: =Sum(E76:F76) -> 0 | H76: =D76*G76 -> 0
... C93: Kaarage Bento | D93: =VLOOKUP(C93, 'LIST HPP'!$B$4:$C$39, 2, ) -> 12796.31 | E93: 0 | G93: =Sum(E93:F93) -> 0 | H93: =D93*G93 -> 0
C94: Gyuniku Bento | D94: =VLOOKUP(C94, 'LIST HPP'!$B$4:$C$39, 2, FALSE) -> 14616.31 | E94: 0 | G94: =Sum(E94:F94) -> 0 | H94: =D94*G94 -> 0
C95: Matcha Latte | D95: =VLOOKUP(C95, 'LIST HPP'!$B$4:$C$39, 2, FALSE) -> 8805.63 | G95: =sum(E95:F95) -> 0 | H95: =D95*G95 -> 0 | I95: =sum(H95:H125) -> 0 | K95: =(J95-I95)/J95 -> #DIV/0! | L95: =J95-I95 -> 0
C96: Hojicha Latte | D96: =VLOOKUP(C96, 'LIST HPP'!$B$4:$C$39, 2, FALSE) -> 8150.63 | G96: =sum(E96:F96) -> 0 | H96: =D96*G96 -> 0
C97: Choco Latte | D97: =VLOOKUP(C97, 'LIST HPP'!$B$4:$C$39, 2, FALSE) -> 6013.63 | G97: =sum(E97:F97) -> 0 | H97: =D97*G97 -> 0
C98: Choco Ichigo Latte | D98: =VLOOKUP(C98, 'LIST HPP'!$B$4:$C$39, 2, FALSE) -> 7131.43 | G98: =sum(E98:F98) -> 0 | H98: =D98*G98 -> 0
C99: Matcha Tea | D99: =VLOOKUP(C99, 'LIST HPP'!$B$4:$C$39, 2, FALSE) -> 3748.21 | G99: =sum(E99:F99) -> 0 | H99: =D99*G99 -> 0
C100: Ice Tea | D100: =VLOOKUP(C100, 'LIST HPP'!$B$4:$C$39, 2, FALSE) -> 1448.63 | G100: =sum(E100:F100) -> 0 | H100: =D100*G100 -> 0
C101: Gyumeshi | D101: =VLOOKUP(C101, 'LIST HPP'!$B$4:$C$39, 2, FALSE) -> 11670 | G101: =sum(E101:F101) -> 0 | H101: =D101*G101 -> 0
C102: Karage Don | D102: =VLOOKUP(C102, 'LIST HPP'!$B$4:$C$39, 2, FALSE) -> 9350.16 | G102: =sum(E102:F102) -> 0 | H102: =D102*G102 -> 0
C103: Hot Honey Karage Don | D103: =VLOOKUP(C103, 'LIST HPP'!$B$4:$C$39, 2, FALSE) -> 9990.16 | G103: =sum(E103:F103) -> 0 | H103: =D103*G103 -> 0
C104: Chicken Katsu Don | D104: =VLOOKUP(C104, 'LIST HPP'!$B$4:$C$39, 2, FALSE) -> 7445.2 | G104: =sum(E104:F104) -> 0 | H104: =D104*G104 -> 0
C105: Gyuniku Ala Carte | D105: =VLOOKUP(C105, 'LIST HPP'!$B$4:$C$39, 2, FALSE) -> 17260 | G105: =sum(E105:F105) -> 0 | H105: =D105*G105 -> 0
C106: Karage Ala Carte | D106: =VLOOKUP(C106, 'LIST HPP'!$B$4:$C$39, 2, FALSE) -> 14155 | G106: =sum(E106:F106) -> 0 | H106: =D106*G106 -> 0
C107: Hot Honey Karage Ala Carte | D107: =VLOOKUP(C107, 'LIST HPP'!$B$4:$C$39, 2, FALSE) -> 15435 | G107: =sum(E107:F107) -> 0 | H107: =D107*G107 -> 0
... C125: Gyuniku Bento | D125: =VLOOKUP(C125, 'LIST HPP'!$B$4:$C$39, 2, FALSE) -> 14616.31 | G125: =sum(E125:F125) -> 0 | H125: =D125*G125 -> 0
B126: =#REF! -> #REF! | I126: =SUM(I2:I125) -> 737045.41 | J126: =SUM(J2:J125) -> 1160648 | L126: =SUM(L2:L125) -> 423602.59
A128: Stock Opname Inventory | I128: TOTAL JUMLAH ITEM TERJUAL
A129: Menu | B129: No | F129: Data Penjualan
C130: Bahan | D130: Berat | E130: Satuan | F130: Porsi | G130: Total Bahan Terpakai
A131: Gyumeshi | B131: 1 | C131: Daging Blackpepper | D131: 70 | E131: gr | F131: =VLOOKUP(A131, '20062026'!$I$130:$J$158, 2, ) -> 9 | G131: =D131*F131 -> 630
B132: 2 | C132: Bowl Mangkok | D132: 1 | E132: pcs | G132: =D132*F131 -> 9
B133: 3 | C133: Tutup Mangkok | D133: 1 | E133: pcs | G133: =D133*F131 -> 9
B134: 4 | C134: inner tray bowl | D134: 1 | E134: pcs | G134: =D134*F131 -> 9
B135: 5 | C135: Nasi Putih | D135: 180 | E135: gr | G135: =D135*F131 -> 1620
A136: Karage Don | B136: 1 | C136: Ayam Karage | D136: 130 | E136: gr | F136: =VLOOKUP(A136, '20062026'!$I$130:$J$158, 2, ) -> 8 | G136: =D136*F136 -> 1040
B137: 2 | C137: Bowl Mangkok | D137: 1 | E137: pcs | G137: =D137*F136 -> 8
B138: 3 | C138: Tutup Mangkok | D138: 1 | E138: pcs | G138: =D138*F136 -> 8
B139: 4 | C139: Nasi Putih | D139: 180 | E139: gr | G139: =D139*F136 -> 1440
A140: Hot Honey Karage Don | B140: 1 | C140: Ayam Karage | D140: 130 | E140: gr | F140: =VLOOKUP(A140, '20062026'!$I$130:$J$158, 2, ) -> 4 | G140: =D140*F140 -> 520
B141: 2 | C141: Bowl Mangkok | D141: 1 | E141: pcs | G141: =D141*F140 -> 4
B142: 3 | C142: Tutup Mangkok | D142: 1 | E142: pcs | G142: =D142*F140 -> 4
B143: 4 | C143: Nasi Putih | D143: 180 | E143: gr | G143: =D143*F140 -> 720
B144: 5 | C144: Hot Honey Sauce | D144: 20 | E144: gr | G144: =D144*F140 -> 80
A145: Gyuniku Ala Carte | B145: 1 | C145: Daging Blackpepper | D145: 140 | E145: gr | F145: =VLOOKUP(A145, '20062026'!$I$130:$J$158, 2, ) -> 0 | G145: =D145*F145 -> 0
B146: 2 | C146: thinwall 500ml | D146: 1 | E146: pcs | G146: =D146*F145 -> 0
A147: Karage Ala Carte | B147: 1 | C147: Ayam Karage | D147: 260 | E147: gr | F147: =VLOOKUP(A147, '20062026'!$I$130:$J$158, 2, ) -> 0 | G147: =D147*F147 -> 0
B148: 2 | C148: Bowl Mangkok | D148: 1 | E148: pcs | G148: =D148*F147 -> 0
B149: 3 | C149: Tutup Mangkok | D149: 1 | E149: pcs | G149: =D149*F147 -> 0
A150: Hot Honey Karage Ala Carte | B150: 1 | C150: Ayam Karage | D150: 260 | E150: gr | F150: =VLOOKUP(A150, '20062026'!$I$130:$J$158, 2, ) -> 0 | G150: =D150*F150 -> 0
B151: 2 | C151: Bowl Mangkok | D151: 1 | E151: pcs | G151: =D151*F150 -> 0
B152: 3 | C152: Tutup Mangkok | D152: 1 | E152: pcs | G152: =D152*F150 -> 0
B153: 4 | C153: Hot Honey Sauce | D153: 40 | E153: gr | G153: =D153*F150 -> 0
A154: Curry Karage Don | B154: 1 | C154: Ayam Karage | D154: 130 | E154: porsi | F154: =VLOOKUP(A154, '20062026'!$I$130:$J$158, 2, ) -> 2 | G154: =D154*F154 -> 260
B155: 2 | C155: Bowl Mangkok | D155: 1 | E155: pcs | G155: =D155*F154 -> 2
B156: 3 | C156: Tutup Mangkok | D156: 1 | E156: pcs | G156: =D156*F154 -> 2
B157: 4 | C157: Nasi Putih | D157: 180 | E157: gr | G157: =D157*F154 -> 360
B158: 5 | C158: Curry Sauce | D158: 1 | E158: pcs | G158: =D158*F154 -> 2
A159: Curry Omurice | B159: 1 | C159: Telor Ayam | D159: 2 | E159: pcs | F159: =VLOOKUP(A159, '20062026'!$I$130:$J$158, 2, ) -> 0 | G159: =D159*F159 -> 0
B160: 2 | C160: Bowl Mangkok | D160: 1 | E160: pcs | G160: =D160*F159 -> 0
B161: 3 | C161: Tutup Mangkok | D161: 1 | E161: pcs | G161: =D161*F159 -> 0
B162: 4 | C162: Nasi Putih | D162: 180 | E162: gr | G162: =D162*F159 -> 0
B163: 5 | C163: Curry Sauce | D163: 1 | E163: pcs | G163: =D163*F159 -> 0
B164: 6 | C164: Gula Pasir | D164: 3 | E164: gr | G164: =D164*F159 -> 0
B165: 7 | C165: Dashi Halal | D165: 3 | E165: gr | G165: =D165*F159 -> 0
B166: 8 | C166: Mirin Halal | D166: 5 | E166: gr | G166: =D166*F159 -> 0
A167: Miso Sup | B167: 1 | C167: miso soup | D167: 1 | E167: porsi | F167: =VLOOKUP(A167, '20062026'!$I$130:$J$158, 2, ) -> 5 | G167: =D167*F167 -> 5
B168: 2 | C168: daun bawang | D168: 1 | E168: Pcs | G168: =D168*F167 -> 5
...

Sheet 19062026
A1: PLATFORM | B1: Tanggal | C1: Nama Item | D1: HPP | E1: Jumlah | F1: Jumlah QR | G1: Total Jumlah | H1: Total | I1: Total HPP | J1: Uang Masuk | K1: Margin | L1: Gross Profit
A2: SHOPEE | C2: Matcha Latte | D2: =VLOOKUP(C2, 'LIST HPP'!$B$4:$C$39, 2, ) -> 8805.63 | E2: 0 | G2: =sum(E2:F2) -> 0 | H2: =D2*G2 -> 0 | I2: =sum(H2:H32) -> 573511.46 | J2: 921835 | K2: =(J2-I2)/J2 -> 0.37785888 | L2: =J2-I2 -> 348323.54
C3: Hojicha Latte | D3: =VLOOKUP(C3, 'LIST HPP'!$B$4:$C$39, 2, ) -> 8150.63 | E3: 0 | G3: =sum(E3:F3) -> 0 | H3: =D3*G3 -> 0
C4: Choco Latte | D4: =VLOOKUP(C4, 'LIST HPP'!$B$4:$C$39, 2, ) -> 6013.63 | E4: 1 | G4: =sum(E4:F4) -> 1 | H4: =D4*G4 -> 6013.63
C5: Choco Ichigo Latte | D5: =VLOOKUP(C5, 'LIST HPP'!$B$4:$C$39, 2, ) -> 7131.43 | E5: 0 | G5: =sum(E5:F5) -> 0 | H5: =D5*G5 -> 0
C6: Matcha Tea | D6: =VLOOKUP(C6, 'LIST HPP'!$B$4:$C$39, 2, ) -> 3748.21 | E6: 2 | G6: =sum(E6:F6) -> 2 | H6: =D6*G6 -> 7496.42
C7: Ice Tea | D7: =VLOOKUP(C7, 'LIST HPP'!$B$4:$C$39, 2, ) -> 1448.63 | E7: 2 | G7: =sum(E7:F7) -> 2 | H7: =D7*G7 -> 2897.26
C8: Gyumeshi | D8: =VLOOKUP(C8, 'LIST HPP'!$B$4:$C$39, 2, ) -> 11670 | E8: 5 | G8: =sum(E8:F8) -> 5 | H8: =D8*G8 -> 58350
C9: Karage Don | D9: =VLOOKUP(C9, 'LIST HPP'!$B$4:$C$39, 2, ) -> 9350.16 | E9: 18 | G9: =sum(E9:F9) -> 18 | H9: =D9*G9 -> 168302.88
C10: Hot Honey Karage Don | D10: =VLOOKUP(C10, 'LIST HPP'!$B$4:$C$39, 2, ) -> 9990.16 | E10: 3 | G10: =sum(E10:F10) -> 3 | H10: =D10*G10 -> 29970.48
C11: Chicken Katsu Don | D11: =VLOOKUP(C11, 'LIST HPP'!$B$4:$C$39, 2, ) -> 7445.2 | E11: 22 | G11: =sum(E11:F11) -> 22 | H11: =D11*G11 -> 163794.4
C12: Gyuniku Ala Carte | D12: =VLOOKUP(C12, 'LIST HPP'!$B$4:$C$39, 2, ) -> 17260 | E12: 0 | G12: =sum(E12:F12) -> 0 | H12: =D12*G12 -> 0
C13: Karage Ala Carte | D13: =VLOOKUP(C13, 'LIST HPP'!$B$4:$C$39, 2, ) -> 14155 | E13: 0 | G13: =sum(E13:F13) -> 0 | H13: =D13*G13 -> 0
C14: Hot Honey Karage Ala Carte | D14: =VLOOKUP(C14, 'LIST HPP'!$B$4:$C$39, 2, ) -> 15435 | E14: 0 | G14: =sum(E14:F14) -> 0 | H14: =D14*G14 -> 0
... C32: Gyuniku Bento | D32: =VLOOKUP(C32, 'LIST HPP'!$B$4:$C$39, 2, ) -> 14616.31 | E32: 0 | G32: =sum(E32:F32) -> 0 | H32: =D32*G32 -> 0
A33: GRAB/ OFFLINE Q | C33: Matcha Latte | D33: =VLOOKUP(C33, 'LIST HPP'!$B$4:$C$39, 2, ) -> 8805.63 | E33: 0 | G33: =SUM(E33:F33) -> 0 | H33: =D33*G33 -> 0 | I33: =sum(H33:H63) -> 152894.17 | J33: 100180 | K33: =(J33-I33)/J33 -> -0.52619455 | L33: =J33-I33 -> -52714.17
C34: Hojicha Latte | D34: =VLOOKUP(C34, 'LIST HPP'!$B$4:$C$39, 2, ) -> 8150.63 | E34: 0 | G34: =SUM(E34:F34) -> 0 | H34: =D34*G34 -> 0
C35: Choco Latte | D35: =VLOOKUP(C35, 'LIST HPP'!$B$4:$C$39, 2, ) -> 6013.63 | E35: 0 | G35: =SUM(E35:F35) -> 0 | H35: =D35*G35 -> 0
C36: Choco Ichigo Latte | D36: =VLOOKUP(C36, 'LIST HPP'!$B$4:$C$39, 2, ) -> 7131.43 | E36: 0 | G36: =SUM(E36:F36) -> 0 | H36: =D36*G36 -> 0
C37: Matcha Tea | D37: =VLOOKUP(C37, 'LIST HPP'!$B$4:$C$39, 2, ) -> 3748.21 | E37: 2 | G37: =SUM(E37:F37) -> 2 | H37: =D37*G37 -> 7496.42
C38: Ice Tea | D38: =VLOOKUP(C38, 'LIST HPP'!$B$4:$C$39, 2, ) -> 1448.63 | E38: 0 | G38: =SUM(E38:F38) -> 0 | H38: =D38*G38 -> 0
C39: Gyumeshi | D39: =VLOOKUP(C39, 'LIST HPP'!$B$4:$C$39, 2, ) -> 11670 | E39: 1 | G39: =SUM(E39:F39) -> 1 | H39: =D39*G39 -> 11670
C40: Karage Don | D40: =VLOOKUP(C40, 'LIST HPP'!$B$4:$C$39, 2, ) -> 9350.16 | E40: 0 | G40: =SUM(E40:F40) -> 0 | H40: =D40*G40 -> 0
C41: Hot Honey Karage Don | D41: =VLOOKUP(C41, 'LIST HPP'!$B$4:$C$39, 2, ) -> 9990.16 | E41: 0 | G41: =SUM(E41:F41) -> 0 | H41: =D41*G41 -> 0
C42: Chicken Katsu Don | D42: =VLOOKUP(C42, 'LIST HPP'!$B$4:$C$39, 2, ) -> 7445.2 | E42: 10 | G42: =SUM(E42:F42) -> 10 | H42: =D42*G42 -> 74452
C43: Gyuniku Ala Carte | D43: =VLOOKUP(C43, 'LIST HPP'!$B$4:$C$39, 2, ) -> 17260 | E43: 0 | G43: =SUM(E43:F43) -> 0 | H43: =D43*G43 -> 0
C44: Karage Ala Carte | D44: =VLOOKUP(C44, 'LIST HPP'!$B$4:$C$39, 2, ) -> 14155 | E44: 0 | G44: =SUM(E44:F44) -> 0 | H44: =D44*G44 -> 0
C45: Hot Honey Karage Ala Carte | D45: =VLOOKUP(C45, 'LIST HPP'!$B$4:$C$39, 2, ) -> 15435 | E45: 0 | G45: =SUM(E45:F45) -> 0 | H45: =D45*G45 -> 0
... C63: Gyuniku Bento | D63: =VLOOKUP(C63, 'LIST HPP'!$B$4:$C$39, 2, ) -> 14616.31 | E63: 0 | G63: =SUM(E63:F63) -> 0 | H63: =D63*G63 -> 0
A64: GOJEK | C64: Matcha Latte | D64: =VLOOKUP(C64, 'LIST HPP'!$B$4:$C$39, 2, ) -> 8805.63 | E64: 0 | G64: =Sum(E64:F64) -> 0 | H64: =D64*G64 -> 0 | I64: =sum(H64:H94) -> 39201.62 | J64: 87717 | K64: =(J64-I64)/J64 -> 0.55308982 | L64: =J64-I64 -> 48515.38
C65: Hojicha Latte | D65: =VLOOKUP(C65, 'LIST HPP'!$B$4:$C$39, 2, ) -> 8150.63 | E65: 0 | G65: =Sum(E65:F65) -> 0 | H65: =D65*G65 -> 0
C66: Choco Latte | D66: =VLOOKUP(C66, 'LIST HPP'!$B$4:$C$39, 2, ) -> 6013.63 | E66: 1 | G66: =Sum(E66:F66) -> 1 | H66: =D66*G66 -> 6013.63
C67: Choco Ichigo Latte | D67: =VLOOKUP(C67, 'LIST HPP'!$B$4:$C$39, 2, ) -> 7131.43 | E67: 0 | G67: =Sum(E67:F67) -> 0 | H67: =D67*G67 -> 0
C68: Matcha Tea | D68: =VLOOKUP(C68, 'LIST HPP'!$B$4:$C$39, 2, ) -> 3748.21 | E68: 0 | G68: =Sum(E68:F68) -> 0 | H68: =D68*G68 -> 0
C69: Ice Tea | D69: =VLOOKUP(C69, 'LIST HPP'!$B$4:$C$39, 2, ) -> 1448.63 | E69: 1 | G69: =Sum(E69:F69) -> 1 | H69: =D69*G69 -> 1448.63
C70: Gyumeshi | D70: =VLOOKUP(C70, 'LIST HPP'!$B$4:$C$39, 2, ) -> 11670 | E70: 0 | G70: =Sum(E70:F70) -> 0 | H70: =D70*G70 -> 0
C71: Karage Don | D71: =VLOOKUP(C71, 'LIST HPP'!$B$4:$C$39, 2, ) -> 9350.16 | E71: 0 | G71: =Sum(E71:F71) -> 0 | H71: =D71*G71 -> 0
C72: Hot Honey Karage Don | D72: =VLOOKUP(C72, 'LIST HPP'!$B$4:$C$39, 2, ) -> 9990.16 | E72: 0 | G72: =Sum(E72:F72) -> 0 | H72: =D72*G72 -> 0
C73: Chicken Katsu Don | D73: =VLOOKUP(C73, 'LIST HPP'!$B$4:$C$39, 2, ) -> 7445.2 | E73: 1 | G73: =Sum(E73:F73) -> 1 | H73: =D73*G73 -> 7445.2
C74: Gyuniku Ala Carte | D74: =VLOOKUP(C74, 'LIST HPP'!$B$4:$C$39, 2, ) -> 17260 | E74: 0 | G74: =Sum(E74:F74) -> 0 | H74: =D74*G74 -> 0
C75: Karage Ala Carte | D75: =VLOOKUP(C75, 'LIST HPP'!$B$4:$C$39, 2, ) -> 14155 | E75: 0 | G75: =Sum(E75:F75) -> 0 | H75: =D75*G75 -> 0
C76: Hot Honey Karage Ala Carte | D76: =VLOOKUP(C76, 'LIST HPP'!$B$4:$C$39, 2, ) -> 15435 | E76: 0 | G76: =Sum(E76:F76) -> 0 | H76: =D76*G76 -> 0
... C93: Kaarage Bento | D93: =VLOOKUP(C93, 'LIST HPP'!$B$4:$C$39, 2, ) -> 12796.31 | E93: 0 | G93: =Sum(E93:F93) -> 0 | H93: =D93*G93 -> 0
C94: Gyuniku Bento | D94: =VLOOKUP(C94, 'LIST HPP'!$B$4:$C$39, 2, FALSE) -> 14616.31 | E94: 0 | G94: =Sum(E94:F94) -> 0 | H94: =D94*G94 -> 0
A95: OFFLINE | C95: Matcha Latte | D95: =VLOOKUP(C95, 'LIST HPP'!$B$4:$C$39, 2, FALSE) -> 8805.63 | G95: =sum(E95:F95) -> 0 | H95: =D95*G95 -> 0 | I95: =sum(H95:H125) -> 213173.2 | J95: 420000 | K95: =(J95-I95)/J95 -> 0.49244476 | L95: =J95-I95 -> 206826.8
C96: Hojicha Latte | D96: =VLOOKUP(C96, 'LIST HPP'!$B$4:$C$39, 2, FALSE) -> 8150.63 | G96: =sum(E96:F96) -> 0 | H96: =D96*G96 -> 0
C97: Choco Latte | D97: =VLOOKUP(C97, 'LIST HPP'!$B$4:$C$39, 2, FALSE) -> 6013.63 | G97: =sum(E97:F97) -> 0 | H97: =D97*G97 -> 0
C98: Choco Ichigo Latte | D98: =VLOOKUP(C98, 'LIST HPP'!$B$4:$C$39, 2, FALSE) -> 7131.43 | G98: =sum(E98:F98) -> 0 | H98: =D98*G98 -> 0
C99: Matcha Tea | D99: =VLOOKUP(C99, 'LIST HPP'!$B$4:$C$39, 2, FALSE) -> 3748.21 | G99: =sum(E99:F99) -> 0 | H99: =D99*G99 -> 0
C100: Ice Tea | D100: =VLOOKUP(C100, 'LIST HPP'!$B$4:$C$39, 2, FALSE) -> 1448.63 | G100: =sum(E100:F100) -> 0 | H100: =D100*G100 -> 0
C101: Gyumeshi | D101: =VLOOKUP(C101, 'LIST HPP'!$B$4:$C$39, 2, FALSE) -> 11670 | G101: =sum(E101:F101) -> 0 | H101: =D101*G101 -> 0
C102: Karage Don | D102: =VLOOKUP(C102, 'LIST HPP'!$B$4:$C$39, 2, FALSE) -> 9350.16 | E102: 10 | G102: =sum(E102:F102) -> 10 | H102: =D102*G102 -> 93501.6
C103: Hot Honey Karage Don | D103: =VLOOKUP(C103, 'LIST HPP'!$B$4:$C$39, 2, FALSE) -> 9990.16 | E103: 10 | G103: =sum(E103:F103) -> 10 | H103: =D103*G103 -> 99901.6
C104: Chicken Katsu Don | D104: =VLOOKUP(C104, 'LIST HPP'!$B$4:$C$39, 2, FALSE) -> 7445.2 | G104: =sum(E104:F104) -> 0 | H104: =D104*G104 -> 0
C105: Gyuniku Ala Carte | D105: =VLOOKUP(C105, 'LIST HPP'!$B$4:$C$39, 2, FALSE) -> 17260 | G105: =sum(E105:F105) -> 0 | H105: =D105*G105 -> 0
C106: Karage Ala Carte | D106: =VLOOKUP(C106, 'LIST HPP'!$B$4:$C$39, 2, FALSE) -> 14155 | G106: =sum(E106:F106) -> 0 | H106: =D106*G106 -> 0
C107: Hot Honey Karage Ala Carte | D107: =VLOOKUP(C107, 'LIST HPP'!$B$4:$C$39, 2, FALSE) -> 15435 | G107: =sum(E107:F107) -> 0 | H107: =D107*G107 -> 0
C108: Curry Omurice | D108: =VLOOKUP(C108, 'LIST HPP'!$B$4:$C$39, 2, FALSE) -> 9229.59 | G108: =sum(E108:F108) -> 0 | H108: =D108*G108 -> 0
C109: Curry Karage Don | D109: =VLOOKUP(C109, 'LIST HPP'!$B$4:$C$39, 2, FALSE) -> 11550.16 | G109: =sum(E109:F109) -> 0 | H109: =D109*G109 -> 0
C110: Curry Katsu Don | D110: =VLOOKUP(C110, 'LIST HPP'!$B$4:$C$39, 2, FALSE) -> 9300.16 | G110: =sum(E110:F110) -> 0 | H110: =D110*G110 -> 0
C111: Miso Sup | D111: =VLOOKUP(C111, 'LIST HPP'!$B$4:$C$39, 2, FALSE) -> 1741 | G111: =sum(E111:F111) -> 0 | H111: =D111*G111 -> 0
C112: Curry Sauce | D112: =VLOOKUP(C112, 'LIST HPP'!$B$4:$C$39, 2, FALSE) -> 2200 | G112: =sum(E112:F112) -> 0 | H112: =D112*G112 -> 0
C113: Spicy Sauce | D113: =VLOOKUP(C113, 'LIST HPP'!$B$4:$C$39, 2, FALSE) -> 2875 | G113: =sum(E113:F113) -> 0 | H113: =D113*G113 -> 0
C114: nasi putih | D114: =VLOOKUP(C114, 'LIST HPP'!$B$4:$C$39, 2, FALSE) -> 2113.16 | G114: =sum(E114:F114) -> 0 | H114: =D114*G114 -> 0
C115: saus tomat sachet | D115: =VLOOKUP(C115, 'LIST HPP'!$B$4:$C$39, 2, FALSE) -> 235 | E115: 20 | G115: =sum(E115:F115) -> 20 | H115: =D115*G115 -> 4700
C116: saus sambal sachet | D116: =VLOOKUP(C116, 'LIST HPP'!$B$4:$C$39, 2, FALSE) -> 296 | E116: 20 | G116: =sum(E116:F116) -> 20 | H116: =D116*G116 -> 5920
C117: cabe bubuk | D117: =VLOOKUP(C117, 'LIST HPP'!$B$4:$C$39, 2, FALSE) -> 249.5 | E117: 20 | G117: =sum(E117:F117) -> 20 | H117: =D117*G117 -> 4990
C118: sendok plastik | D118: =VLOOKUP(C118, 'LIST HPP'!$B$4:$C$39, 2, FALSE) -> 208 | E118: 20 | G118: =sum(E118:F118) -> 20 | H118: =D118*G118 -> 4160
C119: extra 2pcs karage | D119: =VLOOKUP(C119, 'LIST HPP'!$B$4:$C$39, 2, FALSE) -> 2446.08 | G119: =sum(E119:F119) -> 0 | H119: =D119*G119 -> 0
C120: extra beef 50gr | D120: =VLOOKUP(C120, 'LIST HPP'!$B$4:$C$39, 2, FALSE) -> 4095 | G120: =sum(E120:F120) -> 0 | H120: =D120*G120 -> 0
C121: Japanese Caramel Pudding | D121: =VLOOKUP(C121, 'LIST HPP'!$B$4:$C$39, 2, FALSE) -> 2064.84 | G121: =sum(E121:F121) -> 0 | H121: =D121*G121 -> 0
C122: Japanese Beef Curry Rice | D122: =VLOOKUP(C122, 'LIST HPP'!$B$4:$C$39, 2, FALSE) -> 13871 | G122: =sum(E122:F122) -> 0 | H122: =D122*G122 -> 0
C123: Katsu Bento | D123: =VLOOKUP(C123, 'LIST HPP'!$B$4:$C$39, 2, FALSE) -> 10521.31 | G123: =sum(E123:F123) -> 0 | H123: =D123*G123 -> 0
C124: Kaarage Bento | D124: =VLOOKUP(C124, 'LIST HPP'!$B$4:$C$39, 2, FALSE) -> 12796.31 | G124: =sum(E124:F124) -> 0 | H124: =D124*G124 -> 0
C125: Gyuniku Bento | D125: =VLOOKUP(C125, 'LIST HPP'!$B$4:$C$39, 2, FALSE) -> 14616.31 | G125: =sum(E125:F125) -> 0 | H125: =D125*G125 -> 0
B126: =#REF! -> #REF! | I126: =SUM(I2:I125) -> 978780.45 | J126: =SUM(J2:J125) -> 1529732 | L126: =SUM(L2:L125) -> 550951.55
A128: Stock Opname Inventory | I128: TOTAL JUMLAH ITEM TERJUAL
A129: Menu | B129: No | F129: Data Penjualan
C130: Bahan | D130: Berat | E130: Satuan | F130: Porsi | G130: Total Bahan Terpakai
A131: Gyumeshi | B131: 1 | C131: Daging Blackpepper | D131: 70 | E131: gr | F131: =VLOOKUP(A131, '19062026'!$I$130:$J$158, 2, ) -> 6 | G131: =D131*F131 -> 420
B132: 2 | C132: Bowl Mangkok | D132: 1 | E132: pcs | G132: =D132*F131 -> 6
B133: 3 | C133: Tutup Mangkok | D133: 1 | E133: pcs | G133: =D133*F131 -> 6
B134: 4 | C134: inner tray bowl | D134: 1 | E134: pcs | G134: =D134*F131 -> 6
B135: 5 | C135: Nasi Putih | D135: 180 | E135: gr | G135: =D135*F131 -> 1080
A136: Karage Don | B136: 1 | C136: Ayam Karage | D136: 130 | E136: gr | F136: =VLOOKUP(A136, '19062026'!$I$130:$J$158, 2, ) -> 28 | G136: =D136*F136 -> 3640
B137: 2 | C137: Bowl Mangkok | D137: 1 | E137: pcs | G137: =D137*F136 -> 28
B138: 3 | C138: Tutup Mangkok | D138: 1 | E138: pcs | G138: =D138*F136 -> 28
B139: 4 | C139: Nasi Putih | D139: 180 | E139: gr | G139: =D139*F136 -> 5040
A140: Hot Honey Karage Don | B140: 1 | C140: Ayam Karage | D140: 130 | E140: gr | F140: =VLOOKUP(A140, '19062026'!$I$130:$J$158, 2, ) -> 13 | G140: =D140*F140 -> 1690
B141: 2 | C141: Bowl Mangkok | D141: 1 | E141: pcs | G141: =D141*F140 -> 13
B142: 3 | C142: Tutup Mangkok | D142: 1 | E142: pcs | G142: =D142*F140 -> 13
B143: 4 | C143: Nasi Putih | D143: 180 | E143: gr | G143: =D143*F140 -> 2340
B144: 5 | C144: Hot Honey Sauce | D144: 20 | E144: gr | G144: =D144*F140 -> 260
A145: Gyuniku Ala Carte | B145: 1 | C145: Daging Blackpepper | D145: 140 | E145: gr | F145: =VLOOKUP(A145, '19062026'!$I$130:$J$158, 2, ) -> 0 | G145: =D145*F145 -> 0
B146: 2 | C146: thinwall 500ml | D146: 1 | E146: pcs | G146: =D146*F145 -> 0
A147: Karage Ala Carte | B147: 1 | C147: Ayam Karage | D147: 260 | E147: gr | F147: =VLOOKUP(A147, '19062026'!$I$130:$J$158, 2, ) -> 0 | G147: =D147*F147 -> 0
B148: 2 | C148: Bowl Mangkok | D148: 1 | E148: pcs | G148: =D148*F147 -> 0
B149: 3 | C149: Tutup Mangkok | D149: 1 | E149: pcs | G149: =D149*F147 -> 0
A150: Hot Honey Karage Ala Carte | B150: 1 | C150: Ayam Karage | D150: 260 | E150: gr | F150: =VLOOKUP(A150, '19062026'!$I$130:$J$158, 2, ) -> 0 | G150: =D150*F150 -> 0
B151: 2 | C151: Bowl Mangkok | D151: 1 | E151: pcs | G151: =D151*F150 -> 0
...

Sheet 18062026
A1: PLATFORM | B1: Tanggal | C1: Nama Item | D1: HPP | E1: Jumlah | F1: Jumlah QR | G1: Total Jumlah | H1: Total | I1: Total HPP | J1: Uang Masuk | K1: Margin | L1: Gross Profit
A2: SHOPEE | C2: Matcha Latte | D2: =VLOOKUP(C2, 'LIST HPP'!$B$4:$C$39, 2, ) -> 8805.63 | E2: 0 | G2: =sum(E2:F2) -> 0 | H2: =D2*G2 -> 0 | I2: =sum(H2:H32) -> 652454.72 | J2: 1072185 | K2: =(J2-I2)/J2 -> 0.39147188 | L2: =J2-I2 -> 419730.28
C3: Hojicha Latte | D3: =VLOOKUP(C3, 'LIST HPP'!$B$4:$C$39, 2, ) -> 8150.63 | E3: 0 | G3: =sum(E3:F3) -> 0 | H3: =D3*G3 -> 0
C4: Choco Latte | D4: =VLOOKUP(C4, 'LIST HPP'!$B$4:$C$39, 2, ) -> 6013.63 | E4: 1 | G4: =sum(E4:F4) -> 1 | H4: =D4*G4 -> 6013.63
C5: Choco Ichigo Latte | D5: =VLOOKUP(C5, 'LIST HPP'!$B$4:$C$39, 2, ) -> 7131.43 | E5: 0 | G5: =sum(E5:F5) -> 0 | H5: =D5*G5 -> 0
C6: Matcha Tea | D6: =VLOOKUP(C6, 'LIST HPP'!$B$4:$C$39, 2, ) -> 3748.21 | E6: 0 | G6: =sum(E6:F6) -> 0 | H6: =D6*G6 -> 0
C7: Ice Tea | D7: =VLOOKUP(C7, 'LIST HPP'!$B$4:$C$39, 2, ) -> 1448.63 | E7: 4 | G7: =sum(E7:F7) -> 4 | H7: =D7*G7 -> 5794.52
C8: Gyumeshi | D8: =VLOOKUP(C8, 'LIST HPP'!$B$4:$C$39, 2, ) -> 11670 | E8: 8 | G8: =sum(E8:F8) -> 8 | H8: =D8*G8 -> 93360
C9: Karage Don | D9: =VLOOKUP(C9, 'LIST HPP'!$B$4:$C$39, 2, ) -> 9350.16 | E9: 6 | G9: =sum(E9:F9) -> 6 | H9: =D9*G9 -> 56100.96
C10: Hot Honey Karage Don | D10: =VLOOKUP(C10, 'LIST HPP'!$B$4:$C$39, 2, ) -> 9990.16 | E10: 7 | G10: =sum(E10:F10) -> 7 | H10: =D10*G10 -> 69931.12
C11: Chicken Katsu Don | D11: =VLOOKUP(C11, 'LIST HPP'!$B$4:$C$39, 2, ) -> 7445.2 | E11: 30 | G11: =sum(E11:F11) -> 30 | H11: =D11*G11 -> 223356
C12: Gyuniku Ala Carte | D12: =VLOOKUP(C12, 'LIST HPP'!$B$4:$C$39, 2, ) -> 17260 | E12: 0 | G12: =sum(E12:F12) -> 0 | H12: =D12*G12 -> 0
C13: Karage Ala Carte | D13: =VLOOKUP(C13, 'LIST HPP'!$B$4:$C$39, 2, ) -> 14155 | E13: 0 | G13: =sum(E13:F13) -> 0 | H13: =D13*G13 -> 0
C14: Hot Honey Karage Ala Carte | D14: =VLOOKUP(C14, 'LIST HPP'!$B$4:$C$39, 2, ) -> 15435 | E14: 0 | G14: =sum(E14:F14) -> 0 | H14: =D14*G14 -> 0
... C32: Gyuniku Bento | D32: =VLOOKUP(C32, 'LIST HPP'!$B$4:$C$39, 2, ) -> 14616.31 | E32: 2 | G32: =sum(E32:F32) -> 2 | H32: =D32*G32 -> 29232.62
A33: GRAB/ OFFLINE Q | C33: Matcha Latte | D33: =VLOOKUP(C33, 'LIST HPP'!$B$4:$C$39, 2, ) -> 8805.63 | E33: 0 | G33: =SUM(E33:F33) -> 0 | H33: =D33*G33 -> 0 | I33: =sum(H33:H63) -> 264708.89 | J33: 547574 | K33: =(J33-I33)/J33 -> 0.51657878 | L33: =J33-I33 -> 282865.11
C34: Hojicha Latte | D34: =VLOOKUP(C34, 'LIST HPP'!$B$4:$C$39, 2, ) -> 8150.63 | E34: 0 | G34: =SUM(E34:F34) -> 0 | H34: =D34*G34 -> 0
C35: Choco Latte | D35: =VLOOKUP(C35, 'LIST HPP'!$B$4:$C$39, 2, ) -> 6013.63 | E35: 1 | G35: =SUM(E35:F35) -> 1 | H35: =D35*G35 -> 6013.63
C36: Choco Ichigo Latte | D36: =VLOOKUP(C36, 'LIST HPP'!$B$4:$C$39, 2, ) -> 7131.43 | E36: 1 | G36: =SUM(E36:F36) -> 1 | H36: =D36*G36 -> 7131.43
C37: Matcha Tea | D37: =VLOOKUP(C37, 'LIST HPP'!$B$4:$C$39, 2, ) -> 3748.21 | E37: 0 | G37: =SUM(E37:F37) -> 0 | H37: =D37*G37 -> 0
C38: Ice Tea | D38: =VLOOKUP(C38, 'LIST HPP'!$B$4:$C$39, 2, ) -> 1448.63 | E38: 2 | G38: =SUM(E38:F38) -> 2 | H38: =D38*G38 -> 2897.26
C39: Gyumeshi | D39: =VLOOKUP(C39, 'LIST HPP'!$B$4:$C$39, 2, ) -> 11670 | E39: 1 | G39: =SUM(E39:F39) -> 1 | H39: =D39*G39 -> 11670
C40: Karage Don | D40: =VLOOKUP(C40, 'LIST HPP'!$B$4:$C$39, 2, ) -> 9350.16 | E40: 0 | G40: =SUM(E40:F40) -> 0 | H40: =D40*G40 -> 0
C41: Hot Honey Karage Don | D41: =VLOOKUP(C41, 'LIST HPP'!$B$4:$C$39, 2, ) -> 9990.16 | E41: 1 | G41: =SUM(E41:F41) -> 1 | H41: =D41*G41 -> 9990.16
C42: Chicken Katsu Don | D42: =VLOOKUP(C42, 'LIST HPP'!$B$4:$C$39, 2, ) -> 7445.2 | E42: 15 | G42: =SUM(E42:F42) -> 15 | H42: =D42*G42 -> 111678
C43: Gyuniku Ala Carte | D43: =VLOOKUP(C43, 'LIST HPP'!$B$4:$C$39, 2, ) -> 17260 | E43: 1 | G43: =SUM(E43:F43) -> 1 | H43: =D43*G43 -> 17260
C44: Karage Ala Carte | D44: =VLOOKUP(C44, 'LIST HPP'!$B$4:$C$39, 2, ) -> 14155 | E44: 1 | G44: =SUM(E44:F44) -> 1 | H44: =D44*G44 -> 14155
C45: Hot Honey Karage Ala Carte | D45: =VLOOKUP(C45, 'LIST HPP'!$B$4:$C$39, 2, ) -> 15435 | E45: 0 | G45: =SUM(E45:F45) -> 0 | H45: =D45*G45 -> 0
... C63: Gyuniku Bento | D63: =VLOOKUP(C63, 'LIST HPP'!$B$4:$C$39, 2, ) -> 14616.31 | E63: 0 | G63: =SUM(E63:F63) -> 0 | H63: =D63*G63 -> 0
A64: GOJEK | C64: Matcha Latte | D64: =VLOOKUP(C64, 'LIST HPP'!$B$4:$C$39, 2, ) -> 8805.63 | G64: =Sum(E64:F64) -> 0 | H64: =D64*G64 -> 0 | I64: =sum(H64:H94) -> 0 | K64: =(J64-I64)/J64 -> #DIV/0! | L64: =J64-I64 -> 0
C65: Hojicha Latte | D65: =VLOOKUP(C65, 'LIST HPP'!$B$4:$C$39, 2, ) -> 8150.63 | G65: =Sum(E65:F65) -> 0 | H65: =D65*G65 -> 0
C66: Choco Latte | D66: =VLOOKUP(C66, 'LIST HPP'!$B$4:$C$39, 2, ) -> 6013.63 | G66: =Sum(E66:F66) -> 0 | H66: =D66*G66 -> 0
C67: Choco Ichigo Latte | D67: =VLOOKUP(C67, 'LIST HPP'!$B$4:$C$39, 2, ) -> 7131.43 | G67: =Sum(E67:F67) -> 0 | H67: =D67*G67 -> 0
C68: Matcha Tea | D68: =VLOOKUP(C68, 'LIST HPP'!$B$4:$C$39, 2, ) -> 3748.21 | G68: =Sum(E68:F68) -> 0 | H68: =D68*G68 -> 0
C69: Ice Tea | D69: =VLOOKUP(C69, 'LIST HPP'!$B$4:$C$39, 2, ) -> 1448.63 | G69: =Sum(E69:F69) -> 0 | H69: =D69*G69 -> 0
C70: Gyumeshi | D70: =VLOOKUP(C70, 'LIST HPP'!$B$4:$C$39, 2, ) -> 11670 | G70: =Sum(E70:F70) -> 0 | H70: =D70*G70 -> 0
C71: Karage Don | D71: =VLOOKUP(C71, 'LIST HPP'!$B$4:$C$39, 2, ) -> 9350.16 | G71: =Sum(E71:F71) -> 0 | H71: =D71*G71 -> 0
C72: Hot Honey Karage Don | D72: =VLOOKUP(C72, 'LIST HPP'!$B$4:$C$39, 2, ) -> 9990.16 | G72: =Sum(E72:F72) -> 0 | H72: =D72*G72 -> 0
C73: Chicken Katsu Don | D73: =VLOOKUP(C73, 'LIST HPP'!$B$4:$C$39, 2, ) -> 7445.2 | G73: =Sum(E73:F73) -> 0 | H73: =D73*G73 -> 0
C74: Gyuniku Ala Carte | D74: =VLOOKUP(C74, 'LIST HPP'!$B$4:$C$39, 2, ) -> 17260 | G74: =Sum(E74:F74) -> 0 | H74: =D74*G74 -> 0
C75: Karage Ala Carte | D75: =VLOOKUP(C75, 'LIST HPP'!$B$4:$C$39, 2, ) -> 14155 | G75: =Sum(E75:F75) -> 0 | H75: =D75*G75 -> 0
C76: Hot Honey Karage Ala Carte | D76: =VLOOKUP(C76, 'LIST HPP'!$B$4:$C$39, 2, ) -> 15435 | G76: =Sum(E76:F76) -> 0 | H76: =D76*G76 -> 0
... C93: Kaarage Bento | D93: =VLOOKUP(C93, 'LIST HPP'!$B$4:$C$39, 2, ) -> 12796.31 | G93: =Sum(E93:F93) -> 0 | H93: =D93*G93 -> 0
C94: Gyuniku Bento | D94: =VLOOKUP(C94, 'LIST HPP'!$B$4:$C$39, 2, FALSE) -> 14616.31 | G94: =Sum(E94:F94) -> 0 | H94: =D94*G94 -> 0
C95: Matcha Latte | D95: =VLOOKUP(C95, 'LIST HPP'!$B$4:$C$39, 2, FALSE) -> 8805.63 | G95: =sum(E95:F95) -> 0 | H95: =D95*G95 -> 0 | I95: =sum(H95:H125) -> 0 | K95: =(J95-I95)/J95 -> #DIV/0! | L95: =J95-I95 -> 0
C96: Hojicha Latte | D96: =VLOOKUP(C96, 'LIST HPP'!$B$4:$C$39, 2, FALSE) -> 8150.63 | G96: =sum(E96:F96) -> 0 | H96: =D96*G96 -> 0
C97: Choco Latte | D97: =VLOOKUP(C97, 'LIST HPP'!$B$4:$C$39, 2, FALSE) -> 6013.63 | G97: =sum(E97:F97) -> 0 | H97: =D97*G97 -> 0
C98: Choco Ichigo Latte | D98: =VLOOKUP(C98, 'LIST HPP'!$B$4:$C$39, 2, FALSE) -> 7131.43 | G98: =sum(E98:F98) -> 0 | H98: =D98*G98 -> 0
C99: Matcha Tea | D99: =VLOOKUP(C99, 'LIST HPP'!$B$4:$C$39, 2, FALSE) -> 3748.21 | G99: =sum(E99:F99) -> 0 | H99: =D99*G99 -> 0
C100: Ice Tea | D100: =VLOOKUP(C100, 'LIST HPP'!$B$4:$C$39, 2, FALSE) -> 1448.63 | G100: =sum(E100:F100) -> 0 | H100: =D100*G100 -> 0
C101: Gyumeshi | D101: =VLOOKUP(C101, 'LIST HPP'!$B$4:$C$39, 2, FALSE) -> 11670 | G101: =sum(E101:F101) -> 0 | H101: =D101*G101 -> 0
C102: Karage Don | D102: =VLOOKUP(C102, 'LIST HPP'!$B$4:$C$39, 2, FALSE) -> 9350.16 | G102: =sum(E102:F102) -> 0 | H102: =D102*G102 -> 0
C103: Hot Honey Karage Don | D103: =VLOOKUP(C103, 'LIST HPP'!$B$4:$C$39, 2, FALSE) -> 9990.16 | G103: =sum(E103:F103) -> 0 | H103: =D103*G103 -> 0
C104: Chicken Katsu Don | D104: =VLOOKUP(C104, 'LIST HPP'!$B$4:$C$39, 2, FALSE) -> 7445.2 | G104: =sum(E104:F104) -> 0 | H104: =D104*G104 -> 0
C105: Gyuniku Ala Carte | D105: =VLOOKUP(C105, 'LIST HPP'!$B$4:$C$39, 2, FALSE) -> 17260 | G105: =sum(E105:F105) -> 0 | H105: =D105*G105 -> 0
C106: Karage Ala Carte | D106: =VLOOKUP(C106, 'LIST HPP'!$B$4:$C$39, 2, FALSE) -> 14155 | G106: =sum(E106:F106) -> 0 | H106: =D106*G106 -> 0
C107: Hot Honey Karage Ala Carte | D107: =VLOOKUP(C107, 'LIST HPP'!$B$4:$C$39, 2, FALSE) -> 15435 | G107: =sum(E107:F107) -> 0 | H107: =D107*G107 -> 0
... C125: Gyuniku Bento | D125: =VLOOKUP(C125, 'LIST HPP'!$B$4:$C$39, 2, FALSE) -> 14616.31 | G125: =sum(E125:F125) -> 0 | H125: =D125*G125 -> 0
B126: =#REF! -> #REF! | I126: =SUM(I2:I125) -> 917163.61 | J126: =SUM(J2:J125) -> 1619759 | L126: =SUM(L2:L125) -> 702595.39
A128: Stock Opname Inventory | I128: TOTAL JUMLAH ITEM TERJUAL
A129: Menu | B129: No | F129: Data Penjualan
C130: Bahan | D130: Berat | E130: Satuan | F130: Porsi | G130: Total Bahan Terpakai
A131: Gyumeshi | B131: 1 | C131: Daging Blackpepper | D131: 70 | E131: gr | F131: =VLOOKUP(A131, '18062026'!$I$130:$J$158, 2, ) -> 9 | G131: =D131*F131 -> 630
B132: 2 | C132: Bowl Mangkok | D132: 1 | E132: pcs | G132: =D132*F131 -> 9
B133: 3 | C133: Tutup Mangkok | D133: 1 | E133: pcs | G133: =D133*F131 -> 9
B134: 4 | C134: inner tray bowl | D134: 1 | E134: pcs | G134: =D134*F131 -> 9
B135: 5 | C135: Nasi Putih | D135: 180 | E135: gr | G135: =D135*F131 -> 1620
A136: Karage Don | B136: 1 | C136: Ayam Karage | D136: 130 | E136: gr | F136: =VLOOKUP(A136, '18062026'!$I$130:$J$158, 2, ) -> 6 | G136: =D136*F136 -> 780
B137: 2 | C137: Bowl Mangkok | D137: 1 | E137: pcs | G137: =D137*F136 -> 6
B138: 3 | C138: Tutup Mangkok | D138: 1 | E138: pcs | G138: =D138*F136 -> 6
B139: 4 | C139: Nasi Putih | D139: 180 | E139: gr | G139: =D139*F136 -> 1080
A140: Hot Honey Karage Don | B140: 1 | C140: Ayam Karage | D140: 130 | E140: gr | F140: =VLOOKUP(A140, '18062026'!$I$130:$J$158, 2, ) -> 8 | G140: =D140*F140 -> 1040
B141: 2 | C141: Bowl Mangkok | D141: 1 | E141: pcs | G141: =D141*F140 -> 8
B142: 3 | C142: Tutup Mangkok | D142: 1 | E142: pcs | G142: =D142*F140 -> 8
B143: 4 | C143: Nasi Putih | D143: 180 | E143: gr | G143: =D143*F140 -> 1440
B144: 5 | C144: Hot Honey Sauce | D144: 20 | E144: gr | G144: =D144*F140 -> 160
A145: Gyuniku Ala Carte | B145: 1 | C145: Daging Blackpepper | D145: 140 | E145: gr | F145: =VLOOKUP(A145, '18062026'!$I$130:$J$158, 2, ) -> 1 | G145: =D145*F145 -> 140
B146: 2 | C146: thinwall 500ml | D146: 1 | E146: pcs | G146: =D146*F145 -> 1
A147: Karage Ala Carte | B147: 1 | C147: Ayam Karage | D147: 260 | E147: gr | F147: =VLOOKUP(A147, '18062026'!$I$130:$J$158, 2, ) -> 1 | G147: =D147*F147 -> 260
B148: 2 | C148: Bowl Mangkok | D148: 1 | E148: pcs | G148: =D148*F147 -> 1
B149: 3 | C149: Tutup Mangkok | D149: 1 | E149: pcs | G149: =D149*F147 -> 1
A150: Hot Honey Karage Ala Carte | B150: 1 | C150: Ayam Karage | D150: 260 | E150: gr | F150: =VLOOKUP(A150, '18062026'!$I$130:$J$158, 2, ) -> 0 | G150: =D150*F150 -> 0
B151: 2 | C151: Bowl Mangkok | D151: 1 | E151: pcs | G151: =D151*F150 -> 0
B152: 3 | C152: Tutup Mangkok | D152: 1 | E152: pcs | G152: =D152*F150 -> 0
B153: 4 | C153: Hot Honey Sauce | D153: 40 | E153: gr | G153: =D153*F150 -> 0
A154: Curry Karage Don | B154: 1 | C154: Ayam Karage | D154: 130 | E154: porsi | F154: =VLOOKUP(A154, '18062026'!$I$130:$J$158, 2, ) -> 4 | G154: =D154*F154 -> 520
B155: 2 | C155: Bowl Mangkok | D155: 1 | E155: pcs | G155: =D155*F154 -> 4
B156: 3 | C156: Tutup Mangkok | D156: 1 | E156: pcs | G156: =D156*F154 -> 4
B157: 4 | C157: Nasi Putih | D157: 180 | E157: gr | G157: =D157*F154 -> 720
B158: 5 | C158: Curry Sauce | D158: 1 | E158: pcs | G158: =D158*F154 -> 4
A159: Curry Omurice | B159: 1 | C159: Telor Ayam | D159: 2 | E159: pcs | F159: =VLOOKUP(A159, '18062026'!$I$130:$J$158, 2, ) -> 0 | G159: =D159*F159 -> 0
B160: 2 | C160: Bowl Mangkok | D160: 1 | E160: pcs | G160: =D160*F159 -> 0
B161: 3 | C161: Tutup Mangkok | D161: 1 | E161: pcs | G161: =D161*F159 -> 0
B162: 4 | C162: Nasi Putih | D162: 180 | E162: gr | G162: =D162*F159 -> 0
B163: 5 | C163: Curry Sauce | D163: 1 | E163: pcs | G163: =D163*F159 -> 0
B164: 6 | C164: Gula Pasir | D164: 3 | E164: gr | G164: =D164*F159 -> 0
B165: 7 | C165: Dashi Halal | D165: 3 | E165: gr | G165: =D165*F159 -> 0
B166: 8 | C166: Mirin Halal | D166: 5 | E166: gr | G166: =D166*F159 -> 0
A167: Miso Sup | B167: 1 | C167: miso soup | D167: 1 | E167: porsi | F167: =VLOOKUP(A167, '18062026'!$I$130:$J$158, 2, ) -> 9 | G167: =D167*F167 -> 9
B168: 2 | C168: daun bawang | D168: 1 | E168: Pcs | G168: =D168*F167 -> 9
...

Sheet 17062026
A1: PLATFORM | B1: Tanggal | C1: Nama Item | D1: HPP | E1: Jumlah | F1: Jumlah QR | G1: Total Jumlah | H1: Total | I1: Total HPP | J1: Uang Masuk | K1: Margin | L1: Gross Profit
A2: SHOPEE | C2: Matcha Latte | D2: =VLOOKUP(C2, 'LIST HPP'!$B$4:$C$39, 2, ) -> 8805.63 | E2: 0 | G2: =sum(E2:F2) -> 0 | H2: =D2*G2 -> 0 | I2: =sum(H2:H32) -> 569976.63 | J2: 907481 | K2: =(J2-I2)/J2 -> 0.37191343 | L2: =J2-I2 -> 337504.37
C3: Hojicha Latte | D3: =VLOOKUP(C3, 'LIST HPP'!$B$4:$C$39, 2, ) -> 8150.63 | E3: 0 | G3: =sum(E3:F3) -> 0 | H3: =D3*G3 -> 0
C4: Choco Latte | D4: =VLOOKUP(C4, 'LIST HPP'!$B$4:$C$39, 2, ) -> 6013.63 | E4: 0 | G4: =sum(E4:F4) -> 0 | H4: =D4*G4 -> 0
C5: Choco Ichigo Latte | D5: =VLOOKUP(C5, 'LIST HPP'!$B$4:$C$39, 2, ) -> 7131.43 | E5: 0 | G5: =sum(E5:F5) -> 0 | H5: =D5*G5 -> 0
C6: Matcha Tea | D6: =VLOOKUP(C6, 'LIST HPP'!$B$4:$C$39, 2, ) -> 3748.21 | E6: 2 | G6: =sum(E6:F6) -> 2 | H6: =D6*G6 -> 7496.42
C7: Ice Tea | D7: =VLOOKUP(C7, 'LIST HPP'!$B$4:$C$39, 2, ) -> 1448.63 | E7: 7 | G7: =sum(E7:F7) -> 7 | H7: =D7*G7 -> 10140.41
C8: Gyumeshi | D8: =VLOOKUP(C8, 'LIST HPP'!$B$4:$C$39, 2, ) -> 11670 | E8: 3 | G8: =sum(E8:F8) -> 3 | H8: =D8*G8 -> 35010
C9: Karage Don | D9: =VLOOKUP(C9, 'LIST HPP'!$B$4:$C$39, 2, ) -> 9350.16 | E9: 4 | G9: =sum(E9:F9) -> 4 | H9: =D9*G9 -> 37400.64
C10: Hot Honey Karage Don | D10: =VLOOKUP(C10, 'LIST HPP'!$B$4:$C$39, 2, ) -> 9990.16 | E10: 3 | G10: =sum(E10:F10) -> 3 | H10: =D10*G10 -> 29970.48
C11: Chicken Katsu Don | D11: =VLOOKUP(C11, 'LIST HPP'!$B$4:$C$39, 2, ) -> 7445.2 | E11: 27 | G11: =sum(E11:F11) -> 27 | H11: =D11*G11 -> 201020.4
C12: Gyuniku Ala Carte | D12: =VLOOKUP(C12, 'LIST HPP'!$B$4:$C$39, 2, ) -> 17260 | E12: 0 | G12: =sum(E12:F12) -> 0 | H12: =D12*G12 -> 0
C13: Karage Ala Carte | D13: =VLOOKUP(C13, 'LIST HPP'!$B$4:$C$39, 2, ) -> 14155 | E13: 0 | G13: =sum(E13:F13) -> 0 | H13: =D13*G13 -> 0
C14: Hot Honey Karage Ala Carte | D14: =VLOOKUP(C14, 'LIST HPP'!$B$4:$C$39, 2, ) -> 15435 | E14: 0 | G14: =sum(E14:F14) -> 0 | H14: =D14*G14 -> 0
... C32: Gyuniku Bento | D32: =VLOOKUP(C32, 'LIST HPP'!$B$4:$C$39, 2, ) -> 14616.31 | E32: 0 | G32: =sum(E32:F32) -> 0 | H32: =D32*G32 -> 0
A33: GRAB/ OFFLINE Q | C33: Matcha Latte | D33: =VLOOKUP(C33, 'LIST HPP'!$B$4:$C$39, 2, ) -> 8805.63 | E33: 1 | G33: =SUM(E33:F33) -> 1 | H33: =D33*G33 -> 8805.63 | I33: =sum(H33:H63) -> 282415.13 | J33: 469582 | K33: =(J33-I33)/J33 -> 0.39858187 | L33: =J33-I33 -> 187166.87
C34: Hojicha Latte | D34: =VLOOKUP(C34, 'LIST HPP'!$B$4:$C$39, 2, ) -> 8150.63 | E34: 0 | G34: =SUM(E34:F34) -> 0 | H34: =D34*G34 -> 0
C35: Choco Latte | D35: =VLOOKUP(C35, 'LIST HPP'!$B$4:$C$39, 2, ) -> 6013.63 | E35: 0 | G35: =SUM(E35:F35) -> 0 | H35: =D35*G35 -> 0
C36: Choco Ichigo Latte | D36: =VLOOKUP(C36, 'LIST HPP'!$B$4:$C$39, 2, ) -> 7131.43 | E36: 0 | G36: =SUM(E36:F36) -> 0 | H36: =D36*G36 -> 0
C37: Matcha Tea | D37: =VLOOKUP(C37, 'LIST HPP'!$B$4:$C$39, 2, ) -> 3748.21 | E37: 0 | G37: =SUM(E37:F37) -> 0 | H37: =D37*G37 -> 0
C38: Ice Tea | D38: =VLOOKUP(C38, 'LIST HPP'!$B$4:$C$39, 2, ) -> 1448.63 | E38: 0 | G38: =SUM(E38:F38) -> 0 | H38: =D38*G38 -> 0
C39: Gyumeshi | D39: =VLOOKUP(C39, 'LIST HPP'!$B$4:$C$39, 2, ) -> 11670 | E39: 1 | G39: =SUM(E39:F39) -> 1 | H39: =D39*G39 -> 11670
C40: Karage Don | D40: =VLOOKUP(C40, 'LIST HPP'!$B$4:$C$39, 2, ) -> 9350.16 | E40: 1 | G40: =SUM(E40:F40) -> 1 | H40: =D40*G40 -> 9350.16
C41: Hot Honey Karage Don | D41: =VLOOKUP(C41, 'LIST HPP'!$B$4:$C$39, 2, ) -> 9990.16 | E41: 0 | G41: =SUM(E41:F41) -> 0 | H41: =D41*G41 -> 0
C42: Chicken Katsu Don | D42: =VLOOKUP(C42, 'LIST HPP'!$B$4:$C$39, 2, ) -> 7445.2 | E42: 8 | G42: =SUM(E42:F42) -> 8 | H42: =D42*G42 -> 59561.6
C43: Gyuniku Ala Carte | D43: =VLOOKUP(C43, 'LIST HPP'!$B$4:$C$39, 2, ) -> 17260 | E43: 0 | G43: =SUM(E43:F43) -> 0 | H43: =D43*G43 -> 0
C44: Karage Ala Carte | D44: =VLOOKUP(C44, 'LIST HPP'!$B$4:$C$39, 2, ) -> 14155 | E44: 1 | G44: =SUM(E44:F44) -> 1 | H44: =D44*G44 -> 14155
C45: Hot Honey Karage Ala Carte | D45: =VLOOKUP(C45, 'LIST HPP'!$B$4:$C$39, 2, ) -> 15435 | E45: 0 | G45: =SUM(E45:F45) -> 0 | H45: =D45*G45 -> 0
... C63: Gyuniku Bento | D63: =VLOOKUP(C63, 'LIST HPP'!$B$4:$C$39, 2, ) -> 14616.31 | E63: 0 | G63: =SUM(E63:F63) -> 0 | H63: =D63*G63 -> 0
A64: GOJEK | C64: Matcha Latte | D64: =VLOOKUP(C64, 'LIST HPP'!$B$4:$C$39, 2, ) -> 8805.63 | E64: 0 | G64: =Sum(E64:F64) -> 0 | H64: =D64*G64 -> 0 | I64: =sum(H64:H94) -> 28518.31 | J64: 66475 | K64: =(J64-I64)/J64 -> 0.57099195 | L64: =J64-I64 -> 37956.69
C65: Hojicha Latte | D65: =VLOOKUP(C65, 'LIST HPP'!$B$4:$C$39, 2, ) -> 8150.63 | E65: 0 | G65: =Sum(E65:F65) -> 0 | H65: =D65*G65 -> 0
C66: Choco Latte | D66: =VLOOKUP(C66, 'LIST HPP'!$B$4:$C$39, 2, ) -> 6013.63 | E66: 0 | G66: =Sum(E66:F66) -> 0 | H66: =D66*G66 -> 0
C67: Choco Ichigo Latte | D67: =VLOOKUP(C67, 'LIST HPP'!$B$4:$C$39, 2, ) -> 7131.43 | E67: 0 | G67: =Sum(E67:F67) -> 0 | H67: =D67*G67 -> 0
C68: Matcha Tea | D68: =VLOOKUP(C68, 'LIST HPP'!$B$4:$C$39, 2, ) -> 3748.21 | E68: 1 | G68: =Sum(E68:F68) -> 1 | H68: =D68*G68 -> 3748.21
C69: Ice Tea | D69: =VLOOKUP(C69, 'LIST HPP'!$B$4:$C$39, 2, ) -> 1448.63 | E69: 0 | G69: =Sum(E69:F69) -> 0 | H69: =D69*G69 -> 0
C70: Gyumeshi | D70: =VLOOKUP(C70, 'LIST HPP'!$B$4:$C$39, 2, ) -> 11670 | E70: 0 | G70: =Sum(E70:F70) -> 0 | H70: =D70*G70 -> 0
C71: Karage Don | D71: =VLOOKUP(C71, 'LIST HPP'!$B$4:$C$39, 2, ) -> 9350.16 | E71: 0 | G71: =Sum(E71:F71) -> 0 | H71: =D71*G71 -> 0
C72: Hot Honey Karage Don | D72: =VLOOKUP(C72, 'LIST HPP'!$B$4:$C$39, 2, ) -> 9990.16 | E72: 0 | G72: =Sum(E72:F72) -> 0 | H72: =D72*G72 -> 0
C73: Chicken Katsu Don | D73: =VLOOKUP(C73, 'LIST HPP'!$B$4:$C$39, 2, ) -> 7445.2 | E73: 3 | G73: =Sum(E73:F73) -> 3 | H73: =D73*G73 -> 22335.6
C74: Gyuniku Ala Carte | D74: =VLOOKUP(C74, 'LIST HPP'!$B$4:$C$39, 2, ) -> 17260 | E74: 0 | G74: =Sum(E74:F74) -> 0 | H74: =D74*G74 -> 0
C75: Karage Ala Carte | D75: =VLOOKUP(C75, 'LIST HPP'!$B$4:$C$39, 2, ) -> 14155 | E75: 0 | G75: =Sum(E75:F75) -> 0 | H75: =D75*G75 -> 0
C76: Hot Honey Karage Ala Carte | D76: =VLOOKUP(C76, 'LIST HPP'!$B$4:$C$39, 2, ) -> 15435 | E76: 0 | G76: =Sum(E76:F76) -> 0 | H76: =D76*G76 -> 0
... C93: Kaarage Bento | D93: =VLOOKUP(C93, 'LIST HPP'!$B$4:$C$39, 2, ) -> 12796.31 | E93: 0 | G93: =Sum(E93:F93) -> 0 | H93: =D93*G93 -> 0
C94: Gyuniku Bento | D94: =VLOOKUP(C94, 'LIST HPP'!$B$4:$C$39, 2, FALSE) -> 14616.31 | E94: 0 | G94: =Sum(E94:F94) -> 0 | H94: =D94*G94 -> 0
C95: Matcha Latte | D95: =VLOOKUP(C95, 'LIST HPP'!$B$4:$C$39, 2, FALSE) -> 8805.63 | G95: =sum(E95:F95) -> 0 | H95: =D95*G95 -> 0 | I95: =sum(H95:H125) -> 0 | K95: =(J95-I95)/J95 -> #DIV/0! | L95: =J95-I95 -> 0
C96: Hojicha Latte | D96: =VLOOKUP(C96, 'LIST HPP'!$B$4:$C$39, 2, FALSE) -> 8150.63 | G96: =sum(E96:F96) -> 0 | H96: =D96*G96 -> 0
C97: Choco Latte | D97: =VLOOKUP(C97, 'LIST HPP'!$B$4:$C$39, 2, FALSE) -> 6013.63 | G97: =sum(E97:F97) -> 0 | H97: =D97*G97 -> 0
C98: Choco Ichigo Latte | D98: =VLOOKUP(C98, 'LIST HPP'!$B$4:$C$39, 2, FALSE) -> 7131.43 | G98: =sum(E98:F98) -> 0 | H98: =D98*G98 -> 0
C99: Matcha Tea | D99: =VLOOKUP(C99, 'LIST HPP'!$B$4:$C$39, 2, FALSE) -> 3748.21 | G99: =sum(E99:F99) -> 0 | H99: =D99*G99 -> 0
C100: Ice Tea | D100: =VLOOKUP(C100, 'LIST HPP'!$B$4:$C$39, 2, FALSE) -> 1448.63 | G100: =sum(E100:F100) -> 0 | H100: =D100*G100 -> 0
C101: Gyumeshi | D101: =VLOOKUP(C101, 'LIST HPP'!$B$4:$C$39, 2, FALSE) -> 11670 | G101: =sum(E101:F101) -> 0 | H101: =D101*G101 -> 0
C102: Karage Don | D102: =VLOOKUP(C102, 'LIST HPP'!$B$4:$C$39, 2, FALSE) -> 9350.16 | G102: =sum(E102:F102) -> 0 | H102: =D102*G102 -> 0
C103: Hot Honey Karage Don | D103: =VLOOKUP(C103, 'LIST HPP'!$B$4:$C$39, 2, FALSE) -> 9990.16 | G103: =sum(E103:F103) -> 0 | H103: =D103*G103 -> 0
C104: Chicken Katsu Don | D104: =VLOOKUP(C104, 'LIST HPP'!$B$4:$C$39, 2, FALSE) -> 7445.2 | G104: =sum(E104:F104) -> 0 | H104: =D104*G104 -> 0
C105: Gyuniku Ala Carte | D105: =VLOOKUP(C105, 'LIST HPP'!$B$4:$C$39, 2, FALSE) -> 17260 | G105: =sum(E105:F105) -> 0 | H105: =D105*G105 -> 0
C106: Karage Ala Carte | D106: =VLOOKUP(C106, 'LIST HPP'!$B$4:$C$39, 2, FALSE) -> 14155 | G106: =sum(E106:F106) -> 0 | H106: =D106*G106 -> 0
C107: Hot Honey Karage Ala Carte | D107: =VLOOKUP(C107, 'LIST HPP'!$B$4:$C$39, 2, FALSE) -> 15435 | G107: =sum(E107:F107) -> 0 | H107: =D107*G107 -> 0
... C125: Gyuniku Bento | D125: =VLOOKUP(C125, 'LIST HPP'!$B$4:$C$39, 2, FALSE) -> 14616.31 | G125: =sum(E125:F125) -> 0 | H125: =D125*G125 -> 0
B126: =#REF! -> #REF! | I126: =SUM(I2:I125) -> 880910.07 | J126: =SUM(J2:J125) -> 1443538 | L126: =SUM(L2:L125) -> 562627.93
A128: Stock Opname Inventory | I128: TOTAL JUMLAH ITEM TERJUAL
A129: Menu | B129: No | F129: Data Penjualan
C130: Bahan | D130: Berat | E130: Satuan | F130: Porsi | G130: Total Bahan Terpakai
A131: Gyumeshi | B131: 1 | C131: Daging Blackpepper | D131: 70 | E131: gr | F131: =VLOOKUP(A131, '17062026'!$I$130:$J$158, 2, ) -> 4 | G131: =D131*F131 -> 280
B132: 2 | C132: Bowl Mangkok | D132: 1 | E132: pcs | G132: =D132*F131 -> 4
B133: 3 | C133: Tutup Mangkok | D133: 1 | E133: pcs | G133: =D133*F131 -> 4
B134: 4 | C134: inner tray bowl | D134: 1 | E134: pcs | G134: =D134*F131 -> 4
B135: 5 | C135: Nasi Putih | D135: 180 | E135: gr | G135: =D135*F131 -> 720
A136: Karage Don | B136: 1 | C136: Ayam Karage | D136: 130 | E136: gr | F136: =VLOOKUP(A136, '17062026'!$I$130:$J$158, 2, ) -> 5 | G136: =D136*F136 -> 650
B137: 2 | C137: Bowl Mangkok | D137: 1 | E137: pcs | G137: =D137*F136 -> 5
B138: 3 | C138: Tutup Mangkok | D138: 1 | E138: pcs | G138: =D138*F136 -> 5
B139: 4 | C139: Nasi Putih | D139: 180 | E139: gr | G139: =D139*F136 -> 900
A140: Hot Honey Karage Don | B140: 1 | C140: Ayam Karage | D140: 130 | E140: gr | F140: =VLOOKUP(A140, '17062026'!$I$130:$J$158, 2, ) -> 3 | G140: =D140*F140 -> 390
B141: 2 | C141: Bowl Mangkok | D141: 1 | E141: pcs | G141: =D141*F140 -> 3
B142: 3 | C142: Tutup Mangkok | D142: 1 | E142: pcs | G142: =D142*F140 -> 3
B143: 4 | C143: Nasi Putih | D143: 180 | E143: gr | G143: =D143*F140 -> 540
B144: 5 | C144: Hot Honey Sauce | D144: 20 | E144: gr | G144: =D144*F140 -> 60
A145: Gyuniku Ala Carte | B145: 1 | C145: Daging Blackpepper | D145: 140 | E145: gr | F145: =VLOOKUP(A145, '17062026'!$I$130:$J$158, 2, ) -> 0 | G145: =D145*F145 -> 0
B146: 2 | C146: thinwall 500ml | D146: 1 | E146: pcs | G146: =D146*F145 -> 0
A147: Karage Ala Carte | B147: 1 | C147: Ayam Karage | D147: 260 | E147: gr | F147: =VLOOKUP(A147, '17062026'!$I$130:$J$158, 2, ) -> 1 | G147: =D147*F147 -> 260
B148: 2 | C148: Bowl Mangkok | D148: 1 | E148: pcs | G148: =D148*F147 -> 1
B149: 3 | C149: Tutup Mangkok | D149: 1 | E149: pcs | G149: =D149*F147 -> 1
A150: Hot Honey Karage Ala Carte | B150: 1 | C150: Ayam Karage | D150: 260 | E150: gr | F150: =VLOOKUP(A150, '17062026'!$I$130:$J$158, 2, ) -> 0 | G150: =D150*F150 -> 0
B151: 2 | C151: Bowl Mangkok | D151: 1 | E151: pcs | G151: =D151*F150 -> 0
B152: 3 | C152: Tutup Mangkok | D152: 1 | E152: pcs | G152: =D152*F150 -> 0
B153: 4 | C153: Hot Honey Sauce | D153: 40 | E153: gr | G153: =D153*F150 -> 0
A154: Curry Karage Don | B154: 1 | C154: Ayam Karage | D154: 130 | E154: porsi | F154: =VLOOKUP(A154, '17062026'!$I$130:$J$158, 2, ) -> 6 | G154: =D154*F154 -> 780
B155: 2 | C155: Bowl Mangkok | D155: 1 | E155: pcs | G155: =D155*F154 -> 6
B156: 3 | C156: Tutup Mangkok | D156: 1 | E156: pcs | G156: =D156*F154 -> 6
B157: 4 | C157: Nasi Putih | D157: 180 | E157: gr | G157: =D157*F154 -> 1080
B158: 5 | C158: Curry Sauce | D158: 1 | E158: pcs | G158: =D158*F154 -> 6
A159: Curry Omurice | B159: 1 | C159: Telor Ayam | D159: 2 | E159: pcs | F159: =VLOOKUP(A159, '17062026'!$I$130:$J$158, 2, ) -> 2 | G159: =D159*F159 -> 4
B160: 2 | C160: Bowl Mangkok | D160: 1 | E160: pcs | G160: =D160*F159 -> 2
B161: 3 | C161: Tutup Mangkok | D161: 1 | E161: pcs | G161: =D161*F159 -> 2
B162: 4 | C162: Nasi Putih | D162: 180 | E162: gr | G162: =D162*F159 -> 360
B163: 5 | C163: Curry Sauce | D163: 1 | E163: pcs | G163: =D163*F159 -> 2
B164: 6 | C164: Gula Pasir | D164: 3 | E164: gr | G164: =D164*F159 -> 6
B165: 7 | C165: Dashi Halal | D165: 3 | E165: gr | G165: =D165*F159 -> 6
B166: 8 | C166: Mirin Halal | D166: 5 | E166: gr | G166: =D166*F159 -> 10
A167: Miso Sup | B167: 1 | C167: miso soup | D167: 1 | E167: porsi | F167: =VLOOKUP(A167, '17062026'!$I$130:$J$158, 2, ) -> 4 | G167: =D167*F167 -> 4
B168: 2 | C168: daun bawang | D168: 1 | E168: Pcs | G168: =D168*F167 -> 4
...

Sheet 16062026
A1: PLATFORM | B1: Tanggal | C1: Nama Item | D1: HPP | E1: Jumlah | F1: Jumlah QR | G1: Total Jumlah | H1: Total | I1: Total HPP | J1: Uang Masuk | K1: Margin | L1: Gross Profit
A2: SHOPEE | C2: Matcha Latte | D2: =VLOOKUP(C2, 'LIST HPP'!$B$4:$C$39, 2, ) -> 8805.63 | E2: 0 | G2: =sum(E2:F2) -> 0 | H2: =D2*G2 -> 0 | I2: =sum(H2:H32) -> 789122.4 | J2: 1301577 | K2: =(J2-I2)/J2 -> 0.39371824 | L2: =J2-I2 -> 512454.6
C3: Hojicha Latte | D3: =VLOOKUP(C3, 'LIST HPP'!$B$4:$C$39, 2, ) -> 8150.63 | E3: 0 | G3: =sum(E3:F3) -> 0 | H3: =D3*G3 -> 0
C4: Choco Latte | D4: =VLOOKUP(C4, 'LIST HPP'!$B$4:$C$39, 2, ) -> 6013.63 | E4: 2 | G4: =sum(E4:F4) -> 2 | H4: =D4*G4 -> 12027.26
C5: Choco Ichigo Latte | D5: =VLOOKUP(C5, 'LIST HPP'!$B$4:$C$39, 2, ) -> 7131.43 | E5: 2 | G5: =sum(E5:F5) -> 2 | H5: =D5*G5 -> 14262.86
C6: Matcha Tea | D6: =VLOOKUP(C6, 'LIST HPP'!$B$4:$C$39, 2, ) -> 3748.21 | E6: 5 | G6: =sum(E6:F6) -> 5 | H6: =D6*G6 -> 18741.05
C7: Ice Tea | D7: =VLOOKUP(C7, 'LIST HPP'!$B$4:$C$39, 2, ) -> 1448.63 | E7: 12 | G7: =sum(E7:F7) -> 12 | H7: =D7*G7 -> 17383.56
C8: Gyumeshi | D8: =VLOOKUP(C8, 'LIST HPP'!$B$4:$C$39, 2, ) -> 11670 | E8: 4 | G8: =sum(E8:F8) -> 4 | H8: =D8*G8 -> 46680
C9: Karage Don | D9: =VLOOKUP(C9, 'LIST HPP'!$B$4:$C$39, 2, ) -> 9350.16 | E9: 11 | G9: =sum(E9:F9) -> 11 | H9: =D9*G9 -> 102851.76
C10: Hot Honey Karage Don | D10: =VLOOKUP(C10, 'LIST HPP'!$B$4:$C$39, 2, ) -> 9990.16 | E10: 2 | G10: =sum(E10:F10) -> 2 | H10: =D10*G10 -> 19980.32
C11: Chicken Katsu Don | D11: =VLOOKUP(C11, 'LIST HPP'!$B$4:$C$39, 2, ) -> 7445.2 | E11: 39 | G11: =sum(E11:F11) -> 39 | H11: =D11*G11 -> 290362.8
C12: Gyuniku Ala Carte | D12: =VLOOKUP(C12, 'LIST HPP'!$B$4:$C$39, 2, ) -> 17260 | E12: 2 | G12: =sum(E12:F12) -> 2 | H12: =D12*G12 -> 34520
C13: Karage Ala Carte | D13: =VLOOKUP(C13, 'LIST HPP'!$B$4:$C$39, 2, ) -> 14155 | E13: 0 | G13: =sum(E13:F13) -> 0 | H13: =D13*G13 -> 0
C14: Hot Honey Karage Ala Carte | D14: =VLOOKUP(C14, 'LIST HPP'!$B$4:$C$39, 2, ) -> 15435 | E14: 0 | G14: =sum(E14:F14) -> 0 | H14: =D14*G14 -> 0
... C32: Gyuniku Bento | D32: =VLOOKUP(C32, 'LIST HPP'!$B$4:$C$39, 2, ) -> 14616.31 | E32: 1 | G32: =sum(E32:F32) -> 1 | H32: =D32*G32 -> 14616.31
A33: GRAB/ OFFLINE Q | C33: Matcha Latte | D33: =VLOOKUP(C33, 'LIST HPP'!$B$4:$C$39, 2, ) -> 8805.63 | E33: 1 | G33: =SUM(E33:F33) -> 1 | H33: =D33*G33 -> 8805.63 | I33: =sum(H33:H63) -> 398599.38 | J33: 583516 | K33: =(J33-I33)/J33 -> 0.31690068 | L33: =J33-I33 -> 184916.62
C34: Hojicha Latte | D34: =VLOOKUP(C34, 'LIST HPP'!$B$4:$C$39, 2, ) -> 8150.63 | E34: 0 | G34: =SUM(E34:F34) -> 0 | H34: =D34*G34 -> 0
C35: Choco Latte | D35: =VLOOKUP(C35, 'LIST HPP'!$B$4:$C$39, 2, ) -> 6013.63 | E35: 0 | G35: =SUM(E35:F35) -> 0 | H35: =D35*G35 -> 0
C36: Choco Ichigo Latte | D36: =VLOOKUP(C36, 'LIST HPP'!$B$4:$C$39, 2, ) -> 7131.43 | E36: 0 | G36: =SUM(E36:F36) -> 0 | H36: =D36*G36 -> 0
C37: Matcha Tea | D37: =VLOOKUP(C37, 'LIST HPP'!$B$4:$C$39, 2, ) -> 3748.21 | E37: 2 | G37: =SUM(E37:F37) -> 2 | H37: =D37*G37 -> 7496.42
C38: Ice Tea | D38: =VLOOKUP(C38, 'LIST HPP'!$B$4:$C$39, 2, ) -> 1448.63 | E38: 3 | G38: =SUM(E38:F38) -> 3 | H38: =D38*G38 -> 4345.89
C39: Gyumeshi | D39: =VLOOKUP(C39, 'LIST HPP'!$B$4:$C$39, 2, ) -> 11670 | E39: 1 | G39: =SUM(E39:F39) -> 1 | H39: =D39*G39 -> 11670
C40: Karage Don | D40: =VLOOKUP(C40, 'LIST HPP'!$B$4:$C$39, 2, ) -> 9350.16 | E40: 0 | G40: =SUM(E40:F40) -> 0 | H40: =D40*G40 -> 0
C41: Hot Honey Karage Don | D41: =VLOOKUP(C41, 'LIST HPP'!$B$4:$C$39, 2, ) -> 9990.16 | E41: 0 | G41: =SUM(E41:F41) -> 0 | H41: =D41*G41 -> 0
C42: Chicken Katsu Don | D42: =VLOOKUP(C42, 'LIST HPP'!$B$4:$C$39, 2, ) -> 7445.2 | E42: 21 | G42: =SUM(E42:F42) -> 21 | H42: =D42*G42 -> 156349.2
C43: Gyuniku Ala Carte | D43: =VLOOKUP(C43, 'LIST HPP'!$B$4:$C$39, 2, ) -> 17260 | E43: 1 | G43: =SUM(E43:F43) -> 1 | H43: =D43*G43 -> 17260
C44: Karage Ala Carte | D44: =VLOOKUP(C44, 'LIST HPP'!$B$4:$C$39, 2, ) -> 14155 | E44: 2 | G44: =SUM(E44:F44) -> 2 | H44: =D44*G44 -> 28310
C45: Hot Honey Karage Ala Carte | D45: =VLOOKUP(C45, 'LIST HPP'!$B$4:$C$39, 2, ) -> 15435 | E45: 0 | G45: =SUM(E45:F45) -> 0 | H45: =D45*G45 -> 0
... C63: Gyuniku Bento | D63: =VLOOKUP(C63, 'LIST HPP'!$B$4:$C$39, 2, ) -> 14616.31 | E63: 2 | G63: =SUM(E63:F63) -> 2 | H63: =D63*G63 -> 29232.62
A64: GOJEK | C64: Matcha Latte | D64: =VLOOKUP(C64, 'LIST HPP'!$B$4:$C$39, 2, ) -> 8805.63 | E64: 0 | G64: =Sum(E64:F64) -> 0 | H64: =D64*G64 -> 0 | I64: =sum(H64:H94) -> 61630.22 | J64: 151000 | K64: =(J64-I64)/J64 -> 0.59185285 | L64: =J64-I64 -> 89369.78
C65: Hojicha Latte | D65: =VLOOKUP(C65, 'LIST HPP'!$B$4:$C$39, 2, ) -> 8150.63 | E65: 0 | G65: =Sum(E65:F65) -> 0 | H65: =D65*G65 -> 0
C66: Choco Latte | D66: =VLOOKUP(C66, 'LIST HPP'!$B$4:$C$39, 2, ) -> 6013.63 | E66: 0 | G66: =Sum(E66:F66) -> 0 | H66: =D66*G66 -> 0
C67: Choco Ichigo Latte | D67: =VLOOKUP(C67, 'LIST HPP'!$B$4:$C$39, 2, ) -> 7131.43 | E67: 0 | G67: =Sum(E67:F67) -> 0 | H67: =D67*G67 -> 0
C68: Matcha Tea | D68: =VLOOKUP(C68, 'LIST HPP'!$B$4:$C$39, 2, ) -> 3748.21 | E68: 0 | G68: =Sum(E68:F68) -> 0 | H68: =D68*G68 -> 0
C69: Ice Tea | D69: =VLOOKUP(C69, 'LIST HPP'!$B$4:$C$39, 2, ) -> 1448.63 | E69: 0 | G69: =Sum(E69:F69) -> 0 | H69: =D69*G69 -> 0
C70: Gyumeshi | D70: =VLOOKUP(C70, 'LIST HPP'!$B$4:$C$39, 2, ) -> 11670 | E70: 1 | G70: =Sum(E70:F70) -> 1 | H70: =D70*G70 -> 11670
C71: Karage Don | D71: =VLOOKUP(C71, 'LIST HPP'!$B$4:$C$39, 2, ) -> 9350.16 | E71: 2 | G71: =Sum(E71:F71) -> 2 | H71: =D71*G71 -> 18700.32
C72: Hot Honey Karage Don | D72: =VLOOKUP(C72, 'LIST HPP'!$B$4:$C$39, 2, ) -> 9990.16 | E72: 0 | G72: =Sum(E72:F72) -> 0 | H72: =D72*G72 -> 0
C73: Chicken Katsu Don | D73: =VLOOKUP(C73, 'LIST HPP'!$B$4:$C$39, 2, ) -> 7445.2 | E73: 2 | G73: =Sum(E73:F73) -> 2 | H73: =D73*G73 -> 14890.4
C74: Gyuniku Ala Carte | D74: =VLOOKUP(C74, 'LIST HPP'!$B$4:$C$39, 2, ) -> 17260 | E74: 0 | G74: =Sum(E74:F74) -> 0 | H74: =D74*G74 -> 0
C75: Karage Ala Carte | D75: =VLOOKUP(C75, 'LIST HPP'!$B$4:$C$39, 2, ) -> 14155 | E75: 0 | G75: =Sum(E75:F75) -> 0 | H75: =D75*G75 -> 0
C76: Hot Honey Karage Ala Carte | D76: =VLOOKUP(C76, 'LIST HPP'!$B$4:$C$39, 2, ) -> 15435 | E76: 0 | G76: =Sum(E76:F76) -> 0 | H76: =D76*G76 -> 0
... C93: Kaarage Bento | D93: =VLOOKUP(C93, 'LIST HPP'!$B$4:$C$39, 2, ) -> 12796.31 | E93: 0 | G93: =Sum(E93:F93) -> 0 | H93: =D93*G93 -> 0
C94: Gyuniku Bento | D94: =VLOOKUP(C94, 'LIST HPP'!$B$4:$C$39, 2, FALSE) -> 14616.31 | E94: 0 | G94: =Sum(E94:F94) -> 0 | H94: =D94*G94 -> 0
C95: Matcha Latte | D95: =VLOOKUP(C95, 'LIST HPP'!$B$4:$C$39, 2, FALSE) -> 8805.63 | G95: =sum(E95:F95) -> 0 | H95: =D95*G95 -> 0 | I95: =sum(H95:H125) -> 0 | K95: =(J95-I95)/J95 -> #DIV/0! | L95: =J95-I95 -> 0
C96: Hojicha Latte | D96: =VLOOKUP(C96, 'LIST HPP'!$B$4:$C$39, 2, FALSE) -> 8150.63 | G96: =sum(E96:F96) -> 0 | H96: =D96*G96 -> 0
C97: Choco Latte | D97: =VLOOKUP(C97, 'LIST HPP'!$B$4:$C$39, 2, FALSE) -> 6013.63 | G97: =sum(E97:F97) -> 0 | H97: =D97*G97 -> 0
C98: Choco Ichigo Latte | D98: =VLOOKUP(C98, 'LIST HPP'!$B$4:$C$39, 2, FALSE) -> 7131.43 | G98: =sum(E98:F98) -> 0 | H98: =D98*G98 -> 0
C99: Matcha Tea | D99: =VLOOKUP(C99, 'LIST HPP'!$B$4:$C$39, 2, FALSE) -> 3748.21 | G99: =sum(E99:F99) -> 0 | H99: =D99*G99 -> 0
C100: Ice Tea | D100: =VLOOKUP(C100, 'LIST HPP'!$B$4:$C$39, 2, FALSE) -> 1448.63 | G100: =sum(E100:F100) -> 0 | H100: =D100*G100 -> 0
C101: Gyumeshi | D101: =VLOOKUP(C101, 'LIST HPP'!$B$4:$C$39, 2, FALSE) -> 11670 | G101: =sum(E101:F101) -> 0 | H101: =D101*G101 -> 0
C102: Karage Don | D102: =VLOOKUP(C102, 'LIST HPP'!$B$4:$C$39, 2, FALSE) -> 9350.16 | G102: =sum(E102:F102) -> 0 | H102: =D102*G102 -> 0
C103: Hot Honey Karage Don | D103: =VLOOKUP(C103, 'LIST HPP'!$B$4:$C$39, 2, FALSE) -> 9990.16 | G103: =sum(E103:F103) -> 0 | H103: =D103*G103 -> 0
C104: Chicken Katsu Don | D104: =VLOOKUP(C104, 'LIST HPP'!$B$4:$C$39, 2, FALSE) -> 7445.2 | G104: =sum(E104:F104) -> 0 | H104: =D104*G104 -> 0
C105: Gyuniku Ala Carte | D105: =VLOOKUP(C105, 'LIST HPP'!$B$4:$C$39, 2, FALSE) -> 17260 | G105: =sum(E105:F105) -> 0 | H105: =D105*G105 -> 0
C106: Karage Ala Carte | D106: =VLOOKUP(C106, 'LIST HPP'!$B$4:$C$39, 2, FALSE) -> 14155 | G106: =sum(E106:F106) -> 0 | H106: =D106*G106 -> 0
C107: Hot Honey Karage Ala Carte | D107: =VLOOKUP(C107, 'LIST HPP'!$B$4:$C$39, 2, FALSE) -> 15435 | G107: =sum(E107:F107) -> 0 | H107: =D107*G107 -> 0
... C125: Gyuniku Bento | D125: =VLOOKUP(C125, 'LIST HPP'!$B$4:$C$39, 2, FALSE) -> 14616.31 | G125: =sum(E125:F125) -> 0 | H125: =D125*G125 -> 0
B126: =#REF! -> #REF! | I126: =SUM(I2:I125) -> 1249352 | J126: =SUM(J2:J125) -> 2036093 | L126: =SUM(L2:L125) -> 786741
A128: Stock Opname Inventory | I128: TOTAL JUMLAH ITEM TERJUAL
A129: Menu | B129: No | F129: Data Penjualan
C130: Bahan | D130: Berat | E130: Satuan | F130: Porsi | G130: Total Bahan Terpakai
A131: Gyumeshi | B131: 1 | C131: Daging Blackpepper | D131: 70 | E131: gr | F131: =VLOOKUP(A131, '16062026'!$I$130:$J$158, 2, ) -> 6 | G131: =D131*F131 -> 420
B132: 2 | C132: Bowl Mangkok | D132: 1 | E132: pcs | G132: =D132*F131 -> 6
B133: 3 | C133: Tutup Mangkok | D133: 1 | E133: pcs | G133: =D133*F131 -> 6
B134: 4 | C134: inner tray bowl | D134: 1 | E134: pcs | G134: =D134*F131 -> 6
B135: 5 | C135: Nasi Putih | D135: 180 | E135: gr | G135: =D135*F131 -> 1080
A136: Karage Don | B136: 1 | C136: Ayam Karage | D136: 130 | E136: gr | F136: =VLOOKUP(A136, '16062026'!$I$130:$J$158, 2, ) -> 13 | G136: =D136*F136 -> 1690
B137: 2 | C137: Bowl Mangkok | D137: 1 | E137: pcs | G137: =D137*F136 -> 13
B138: 3 | C138: Tutup Mangkok | D138: 1 | E138: pcs | G138: =D138*F136 -> 13
B139: 4 | C139: Nasi Putih | D139: 180 | E139: gr | G139: =D139*F136 -> 2340
A140: Hot Honey Karage Don | B140: 1 | C140: Ayam Karage | D140: 130 | E140: gr | F140: =VLOOKUP(A140, '16062026'!$I$130:$J$158, 2, ) -> 2 | G140: =D140*F140 -> 260
B141: 2 | C141: Bowl Mangkok | D141: 1 | E141: pcs | G141: =D141*F140 -> 2
B142: 3 | C142: Tutup Mangkok | D142: 1 | E142: pcs | G142: =D142*F140 -> 2
B143: 4 | C143: Nasi Putih | D143: 180 | E143: gr | G143: =D143*F140 -> 360
B144: 5 | C144: Hot Honey Sauce | D144: 20 | E144: gr | G144: =D144*F140 -> 40
A145: Gyuniku Ala Carte | B145: 1 | C145: Daging Blackpepper | D145: 140 | E145: gr | F145: =VLOOKUP(A145, '16062026'!$I$130:$J$158, 2, ) -> 3 | G145: =D145*F145 -> 420
B146: 2 | C146: thinwall 500ml | D146: 1 | E146: pcs | G146: =D146*F145 -> 3
A147: Karage Ala Carte | B147: 1 | C147: Ayam Karage | D147: 260 | E147: gr | F147: =VLOOKUP(A147, '16062026'!$I$130:$J$158, 2, ) -> 2 | G147: =D147*F147 -> 520
B148: 2 | C148: Bowl Mangkok | D148: 1 | E148: pcs | G148: =D148*F147 -> 2
B149: 3 | C149: Tutup Mangkok | D149: 1 | E149: pcs | G149: =D149*F147 -> 2
A150: Hot Honey Karage Ala Carte | B150: 1 | C150: Ayam Karage | D150: 260 | E150: gr | F150: =VLOOKUP(A150, '16062026'!$I$130:$J$158, 2, ) -> 0 | G150: =D150*F150 -> 0
B151: 2 | C151: Bowl Mangkok | D151: 1 | E151: pcs | G151: =D151*F150 -> 0
B152: 3 | C152: Tutup Mangkok | D152: 1 | E152: pcs | G152: =D152*F150 -> 0
B153: 4 | C153: Hot Honey Sauce | D153: 40 | E153: gr | G153: =D153*F150 -> 0
A154: Curry Karage Don | B154: 1 | C154: Ayam Karage | D154: 130 | E154: porsi | F154: =VLOOKUP(A154, '16062026'!$I$130:$J$158, 2, ) -> 1 | G154: =D154*F154 -> 130
B155: 2 | C155: Bowl Mangkok | D155: 1 | E155: pcs | G155: =D155*F154 -> 1
B156: 3 | C156: Tutup Mangkok | D156: 1 | E156: pcs | G156: =D156*F154 -> 1
B157: 4 | C157: Nasi Putih | D157: 180 | E157: gr | G157: =D157*F154 -> 180
B158: 5 | C158: Curry Sauce | D158: 1 | E158: pcs | G158: =D158*F154 -> 1
A159: Curry Omurice | B159: 1 | C159: Telor Ayam | D159: 2 | E159: pcs | F159: =VLOOKUP(A159, '16062026'!$I$130:$J$158, 2, ) -> 2 | G159: =D159*F159 -> 4
B160: 2 | C160: Bowl Mangkok | D160: 1 | E160: pcs | G160: =D160*F159 -> 2
B161: 3 | C161: Tutup Mangkok | D161: 1 | E161: pcs | G161: =D161*F159 -> 2
B162: 4 | C162: Nasi Putih | D162: 180 | E162: gr | G162: =D162*F159 -> 360
B163: 5 | C163: Curry Sauce | D163: 1 | E163: pcs | G163: =D163*F159 -> 2
B164: 6 | C164: Gula Pasir | D164: 3 | E164: gr | G164: =D164*F159 -> 6
B165: 7 | C165: Dashi Halal | D165: 3 | E165: gr | G165: =D165*F159 -> 6
B166: 8 | C166: Mirin Halal | D166: 5 | E166: gr | G166: =D166*F159 -> 10
A167: Miso Sup | B167: 1 | C167: miso soup | D167: 1 | E167: porsi | F167: =VLOOKUP(A167, '16062026'!$I$130:$J$158, 2, ) -> 9 | G167: =D167*F167 -> 9
B168: 2 | C168: daun bawang | D168: 1 | E168: Pcs | G168: =D168*F167 -> 9
...

Sheet 15062026
A1: PLATFORM | B1: Tanggal | C1: Nama Item | D1: HPP | E1: Jumlah | F1: Jumlah QR | G1: Total Jumlah | H1: Total | I1: Total HPP | J1: Uang Masuk | K1: Margin | L1: Gross Profit
A2: SHOPEE | C2: Matcha Latte | D2: =VLOOKUP(C2, 'LIST HPP'!$B$4:$C$39, 2, ) -> 8805.63 | E2: 0 | G2: =sum(E2:F2) -> 0 | H2: =D2*G2 -> 0 | I2: =sum(H2:H32) -> 432554.95 | J2: 665818 | K2: =(J2-I2)/J2 -> 0.35034056 | L2: =J2-I2 -> 233263.05
C3: Hojicha Latte | D3: =VLOOKUP(C3, 'LIST HPP'!$B$4:$C$39, 2, ) -> 8150.63 | E3: 0 | G3: =sum(E3:F3) -> 0 | H3: =D3*G3 -> 0
C4: Choco Latte | D4: =VLOOKUP(C4, 'LIST HPP'!$B$4:$C$39, 2, ) -> 6013.63 | E4: 1 | G4: =sum(E4:F4) -> 1 | H4: =D4*G4 -> 6013.63
C5: Choco Ichigo Latte | D5: =VLOOKUP(C5, 'LIST HPP'!$B$4:$C$39, 2, ) -> 7131.43 | E5: 0 | G5: =sum(E5:F5) -> 0 | H5: =D5*G5 -> 0
C6: Matcha Tea | D6: =VLOOKUP(C6, 'LIST HPP'!$B$4:$C$39, 2, ) -> 3748.21 | E6: 2 | G6: =sum(E6:F6) -> 2 | H6: =D6*G6 -> 7496.42
C7: Ice Tea | D7: =VLOOKUP(C7, 'LIST HPP'!$B$4:$C$39, 2, ) -> 1448.63 | E7: 15 | G7: =sum(E7:F7) -> 15 | H7: =D7*G7 -> 21729.45
C8: Gyumeshi | D8: =VLOOKUP(C8, 'LIST HPP'!$B$4:$C$39, 2, ) -> 11670 | E8: 2 | G8: =sum(E8:F8) -> 2 | H8: =D8*G8 -> 23340
C9: Karage Don | D9: =VLOOKUP(C9, 'LIST HPP'!$B$4:$C$39, 2, ) -> 9350.16 | E9: 9 | G9: =sum(E9:F9) -> 9 | H9: =D9*G9 -> 84151.44
C10: Hot Honey Karage Don | D10: =VLOOKUP(C10, 'LIST HPP'!$B$4:$C$39, 2, ) -> 9990.16 | E10: 1 | G10: =sum(E10:F10) -> 1 | H10: =D10*G10 -> 9990.16
C11: Chicken Katsu Don | D11: =VLOOKUP(C11, 'LIST HPP'!$B$4:$C$39, 2, ) -> 7445.2 | E11: 29 | G11: =sum(E11:F11) -> 29 | H11: =D11*G11 -> 215910.8
C12: Gyuniku Ala Carte | D12: =VLOOKUP(C12, 'LIST HPP'!$B$4:$C$39, 2, ) -> 17260 | E12: 0 | G12: =sum(E12:F12) -> 0 | H12: =D12*G12 -> 0
C13: Karage Ala Carte | D13: =VLOOKUP(C13, 'LIST HPP'!$B$4:$C$39, 2, ) -> 14155 | E13: 0 | G13: =sum(E13:F13) -> 0 | H13: =D13*G13 -> 0
C14: Hot Honey Karage Ala Carte | D14: =VLOOKUP(C14, 'LIST HPP'!$B$4:$C$39, 2, ) -> 15435 | E14: 0 | G14: =sum(E14:F14) -> 0 | H14: =D14*G14 -> 0
... C32: Gyuniku Bento | D32: =VLOOKUP(C32, 'LIST HPP'!$B$4:$C$39, 2, ) -> 14616.31 | E32: 0 | G32: =sum(E32:F32) -> 0 | H32: =D32*G32 -> 0
A33: GRAB/ OFFLINE Q | C33: Matcha Latte | D33: =VLOOKUP(C33, 'LIST HPP'!$B$4:$C$39, 2, ) -> 8805.63 | E33: 0 | G33: =SUM(E33:F33) -> 0 | H33: =D33*G33 -> 0 | I33: =sum(H33:H63) -> 94016.32 | J33: 161316 | K33: =(J33-I33)/J33 -> 0.4171916 | L33: =J33-I33 -> 67299.68
C34: Hojicha Latte | D34: =VLOOKUP(C34, 'LIST HPP'!$B$4:$C$39, 2, ) -> 8150.63 | E34: 0 | G34: =SUM(E34:F34) -> 0 | H34: =D34*G34 -> 0
C35: Choco Latte | D35: =VLOOKUP(C35, 'LIST HPP'!$B$4:$C$39, 2, ) -> 6013.63 | E35: 0 | G35: =SUM(E35:F35) -> 0 | H35: =D35*G35 -> 0
C36: Choco Ichigo Latte | D36: =VLOOKUP(C36, 'LIST HPP'!$B$4:$C$39, 2, ) -> 7131.43 | E36: 0 | G36: =SUM(E36:F36) -> 0 | H36: =D36*G36 -> 0
C37: Matcha Tea | D37: =VLOOKUP(C37, 'LIST HPP'!$B$4:$C$39, 2, ) -> 3748.21 | E37: 1 | G37: =SUM(E37:F37) -> 1 | H37: =D37*G37 -> 3748.21
C38: Ice Tea | D38: =VLOOKUP(C38, 'LIST HPP'!$B$4:$C$39, 2, ) -> 1448.63 | E38: 2 | G38: =SUM(E38:F38) -> 2 | H38: =D38*G38 -> 2897.26
C39: Gyumeshi | D39: =VLOOKUP(C39, 'LIST HPP'!$B$4:$C$39, 2, ) -> 11670 | E39: 0 | G39: =SUM(E39:F39) -> 0 | H39: =D39*G39 -> 0
C40: Karage Don | D40: =VLOOKUP(C40, 'LIST HPP'!$B$4:$C$39, 2, ) -> 9350.16 | E40: 0 | G40: =SUM(E40:F40) -> 0 | H40: =D40*G40 -> 0
C41: Hot Honey Karage Don | D41: =VLOOKUP(C41, 'LIST HPP'!$B$4:$C$39, 2, ) -> 9990.16 | E41: 1 | G41: =SUM(E41:F41) -> 1 | H41: =D41*G41 -> 9990.16
C42: Chicken Katsu Don | D42: =VLOOKUP(C42, 'LIST HPP'!$B$4:$C$39, 2, ) -> 7445.2 | E42: 2 | G42: =SUM(E42:F42) -> 2 | H42: =D42*G42 -> 14890.4
C43: Gyuniku Ala Carte | D43: =VLOOKUP(C43, 'LIST HPP'!$B$4:$C$39, 2, ) -> 17260 | E43: 0 | G43: =SUM(E43:F43) -> 0 | H43: =D43*G43 -> 0
C44: Karage Ala Carte | D44: =VLOOKUP(C44, 'LIST HPP'!$B$4:$C$39, 2, ) -> 14155 | E44: 1 | G44: =SUM(E44:F44) -> 1 | H44: =D44*G44 -> 14155
C45: Hot Honey Karage Ala Carte | D45: =VLOOKUP(C45, 'LIST HPP'!$B$4:$C$39, 2, ) -> 15435 | E45: 0 | G45: =SUM(E45:F45) -> 0 | H45: =D45*G45 -> 0
... C63: Gyuniku Bento | D63: =VLOOKUP(C63, 'LIST HPP'!$B$4:$C$39, 2, ) -> 14616.31 | E63: 0 | G63: =SUM(E63:F63) -> 0 | H63: =D63*G63 -> 0
A64: GOJEK | C64: Matcha Latte | D64: =VLOOKUP(C64, 'LIST HPP'!$B$4:$C$39, 2, ) -> 8805.63 | E64: 0 | G64: =Sum(E64:F64) -> 0 | H64: =D64*G64 -> 0 | I64: =sum(H64:H94) -> 53386.47 | J64: 127945 | K64: =(J64-I64)/J64 -> 0.58273891 | L64: =J64-I64 -> 74558.53
C65: Hojicha Latte | D65: =VLOOKUP(C65, 'LIST HPP'!$B$4:$C$39, 2, ) -> 8150.63 | E65: 0 | G65: =Sum(E65:F65) -> 0 | H65: =D65*G65 -> 0
C66: Choco Latte | D66: =VLOOKUP(C66, 'LIST HPP'!$B$4:$C$39, 2, ) -> 6013.63 | E66: 0 | G66: =Sum(E66:F66) -> 0 | H66: =D66*G66 -> 0
C67: Choco Ichigo Latte | D67: =VLOOKUP(C67, 'LIST HPP'!$B$4:$C$39, 2, ) -> 7131.43 | E67: 0 | G67: =Sum(E67:F67) -> 0 | H67: =D67*G67 -> 0
C68: Matcha Tea | D68: =VLOOKUP(C68, 'LIST HPP'!$B$4:$C$39, 2, ) -> 3748.21 | E68: 1 | G68: =Sum(E68:F68) -> 1 | H68: =D68*G68 -> 3748.21
C69: Ice Tea | D69: =VLOOKUP(C69, 'LIST HPP'!$B$4:$C$39, 2, ) -> 1448.63 | E69: 0 | G69: =Sum(E69:F69) -> 0 | H69: =D69*G69 -> 0
C70: Gyumeshi | D70: =VLOOKUP(C70, 'LIST HPP'!$B$4:$C$39, 2, ) -> 11670 | E70: 0 | G70: =Sum(E70:F70) -> 0 | H70: =D70*G70 -> 0
C71: Karage Don | D71: =VLOOKUP(C71, 'LIST HPP'!$B$4:$C$39, 2, ) -> 9350.16 | E71: 0 | G71: =Sum(E71:F71) -> 0 | H71: =D71*G71 -> 0
C72: Hot Honey Karage Don | D72: =VLOOKUP(C72, 'LIST HPP'!$B$4:$C$39, 2, ) -> 9990.16 | E72: 0 | G72: =Sum(E72:F72) -> 0 | H72: =D72*G72 -> 0
C73: Chicken Katsu Don | D73: =VLOOKUP(C73, 'LIST HPP'!$B$4:$C$39, 2, ) -> 7445.2 | E73: 3 | G73: =Sum(E73:F73) -> 3 | H73: =D73*G73 -> 22335.6
C74: Gyuniku Ala Carte | D74: =VLOOKUP(C74, 'LIST HPP'!$B$4:$C$39, 2, ) -> 17260 | E74: 0 | G74: =Sum(E74:F74) -> 0 | H74: =D74*G74 -> 0
C75: Karage Ala Carte | D75: =VLOOKUP(C75, 'LIST HPP'!$B$4:$C$39, 2, ) -> 14155 | E75: 0 | G75: =Sum(E75:F75) -> 0 | H75: =D75*G75 -> 0
C76: Hot Honey Karage Ala Carte | D76: =VLOOKUP(C76, 'LIST HPP'!$B$4:$C$39, 2, ) -> 15435 | E76: 0 | G76: =Sum(E76:F76) -> 0 | H76: =D76*G76 -> 0
... C93: Kaarage Bento | D93: =VLOOKUP(C93, 'LIST HPP'!$B$4:$C$39, 2, ) -> 12796.31 | E93: 0 | G93: =Sum(E93:F93) -> 0 | H93: =D93*G93 -> 0
C94: Gyuniku Bento | D94: =VLOOKUP(C94, 'LIST HPP'!$B$4:$C$39, 2, FALSE) -> 14616.31 | E94: 0 | G94: =Sum(E94:F94) -> 0 | H94: =D94*G94 -> 0
C95: Matcha Latte | D95: =VLOOKUP(C95, 'LIST HPP'!$B$4:$C$39, 2, FALSE) -> 8805.63 | G95: =sum(E95:F95) -> 0 | H95: =D95*G95 -> 0 | I95: =sum(H95:H125) -> 0 | K95: =(J95-I95)/J95 -> #DIV/0! | L95: =J95-I95 -> 0
C96: Hojicha Latte | D96: =VLOOKUP(C96, 'LIST HPP'!$B$4:$C$39, 2, FALSE) -> 8150.63 | G96: =sum(E96:F96) -> 0 | H96: =D96*G96 -> 0
C97: Choco Latte | D97: =VLOOKUP(C97, 'LIST HPP'!$B$4:$C$39, 2, FALSE) -> 6013.63 | G97: =sum(E97:F97) -> 0 | H97: =D97*G97 -> 0
C98: Choco Ichigo Latte | D98: =VLOOKUP(C98, 'LIST HPP'!$B$4:$C$39, 2, FALSE) -> 7131.43 | G98: =sum(E98:F98) -> 0 | H98: =D98*G98 -> 0
C99: Matcha Tea | D99: =VLOOKUP(C99, 'LIST HPP'!$B$4:$C$39, 2, FALSE) -> 3748.21 | G99: =sum(E99:F99) -> 0 | H99: =D99*G99 -> 0
C100: Ice Tea | D100: =VLOOKUP(C100, 'LIST HPP'!$B$4:$C$39, 2, FALSE) -> 1448.63 | G100: =sum(E100:F100) -> 0 | H100: =D100*G100 -> 0
C101: Gyumeshi | D101: =VLOOKUP(C101, 'LIST HPP'!$B$4:$C$39, 2, FALSE) -> 11670 | G101: =sum(E101:F101) -> 0 | H101: =D101*G101 -> 0
C102: Karage Don | D102: =VLOOKUP(C102, 'LIST HPP'!$B$4:$C$39, 2, FALSE) -> 9350.16 | G102: =sum(E102:F102) -> 0 | H102: =D102*G102 -> 0
C103: Hot Honey Karage Don | D103: =VLOOKUP(C103, 'LIST HPP'!$B$4:$C$39, 2, FALSE) -> 9990.16 | G103: =sum(E103:F103) -> 0 | H103: =D103*G103 -> 0
C104: Chicken Katsu Don | D104: =VLOOKUP(C104, 'LIST HPP'!$B$4:$C$39, 2, FALSE) -> 7445.2 | G104: =sum(E104:F104) -> 0 | H104: =D104*G104 -> 0
C105: Gyuniku Ala Carte | D105: =VLOOKUP(C105, 'LIST HPP'!$B$4:$C$39, 2, FALSE) -> 17260 | G105: =sum(E105:F105) -> 0 | H105: =D105*G105 -> 0
C106: Karage Ala Carte | D106: =VLOOKUP(C106, 'LIST HPP'!$B$4:$C$39, 2, FALSE) -> 14155 | G106: =sum(E106:F106) -> 0 | H106: =D106*G106 -> 0
C107: Hot Honey Karage Ala Carte | D107: =VLOOKUP(C107, 'LIST HPP'!$B$4:$C$39, 2, FALSE) -> 15435 | G107: =sum(E107:F107) -> 0 | H107: =D107*G107 -> 0
... C125: Gyuniku Bento | D125: =VLOOKUP(C125, 'LIST HPP'!$B$4:$C$39, 2, FALSE) -> 14616.31 | G125: =sum(E125:F125) -> 0 | H125: =D125*G125 -> 0
B126: =#REF! -> #REF! | I126: =SUM(I2:I125) -> 579957.74 | J126: =SUM(J2:J125) -> 955079 | L126: =SUM(L2:L125) -> 375121.26
A128: Stock Opname Inventory | I128: TOTAL JUMLAH ITEM TERJUAL
A129: Menu | B129: No | F129: Data Penjualan
C130: Bahan | D130: Berat | E130: Satuan | F130: Porsi | G130: Total Bahan Terpakai
A131: Gyumeshi | B131: 1 | C131: Daging Blackpepper | D131: 70 | E131: gr | F131: =VLOOKUP(A131, '15062026'!$I$130:$J$158, 2, ) -> 2 | G131: =D131*F131 -> 140
B132: 2 | C132: Bowl Mangkok | D132: 1 | E132: pcs | G132: =D132*F131 -> 2
B133: 3 | C133: Tutup Mangkok | D133: 1 | E133: pcs | G133: =D133*F131 -> 2
B134: 4 | C134: inner tray bowl | D134: 1 | E134: pcs | G134: =D134*F131 -> 2
B135: 5 | C135: Nasi Putih | D135: 180 | E135: gr | G135: =D135*F131 -> 360
A136: Karage Don | B136: 1 | C136: Ayam Karage | D136: 130 | E136: gr | F136: =VLOOKUP(A136, '15062026'!$I$130:$J$158, 2, ) -> 9 | G136: =D136*F136 -> 1170
B137: 2 | C137: Bowl Mangkok | D137: 1 | E137: pcs | G137: =D137*F136 -> 9
B138: 3 | C138: Tutup Mangkok | D138: 1 | E138: pcs | G138: =D138*F136 -> 9
B139: 4 | C139: Nasi Putih | D139: 180 | E139: gr | G139: =D139*F136 -> 1620
A140: Hot Honey Karage Don | B140: 1 | C140: Ayam Karage | D140: 130 | E140: gr | F140: =VLOOKUP(A140, '15062026'!$I$130:$J$158, 2, ) -> 2 | G140: =D140*F140 -> 260
B141: 2 | C141: Bowl Mangkok | D141: 1 | E141: pcs | G141: =D141*F140 -> 2
B142: 3 | C142: Tutup Mangkok | D142: 1 | E142: pcs | G142: =D142*F140 -> 2
B143: 4 | C143: Nasi Putih | D143: 180 | E143: gr | G143: =D143*F140 -> 360
B144: 5 | C144: Hot Honey Sauce | D144: 20 | E144: gr | G144: =D144*F140 -> 40
A145: Gyuniku Ala Carte | B145: 1 | C145: Daging Blackpepper | D145: 140 | E145: gr | F145: =VLOOKUP(A145, '15062026'!$I$130:$J$158, 2, ) -> 0 | G145: =D145*F145 -> 0
B146: 2 | C146: thinwall 500ml | D146: 1 | E146: pcs | G146: =D146*F145 -> 0
A147: Karage Ala Carte | B147: 1 | C147: Ayam Karage | D147: 260 | E147: gr | F147: =VLOOKUP(A147, '15062026'!$I$130:$J$158, 2, ) -> 1 | G147: =D147*F147 -> 260
B148: 2 | C148: Bowl Mangkok | D148: 1 | E148: pcs | G148: =D148*F147 -> 1
B149: 3 | C149: Tutup Mangkok | D149: 1 | E149: pcs | G149: =D149*F147 -> 1
A150: Hot Honey Karage Ala Carte | B150: 1 | C150: Ayam Karage | D150: 260 | E150: gr | F150: =VLOOKUP(A150, '15062026'!$I$130:$J$158, 2, ) -> 0 | G150: =D150*F150 -> 0
B151: 2 | C151: Bowl Mangkok | D151: 1 | E151: pcs | G151: =D151*F150 -> 0
B152: 3 | C152: Tutup Mangkok | D152: 1 | E152: pcs | G152: =D152*F150 -> 0
B153: 4 | C153: Hot Honey Sauce | D153: 40 | E153: gr | G153: =D153*F150 -> 0
A154: Curry Karage Don | B154: 1 | C154: Ayam Karage | D154: 130 | E154: porsi | F154: =VLOOKUP(A154, '15062026'!$I$130:$J$158, 2, ) -> 2 | G154: =D154*F154 -> 260
B155: 2 | C155: Bowl Mangkok | D155: 1 | E155: pcs | G155: =D155*F154 -> 2
B156: 3 | C156: Tutup Mangkok | D156: 1 | E156: pcs | G156: =D156*F154 -> 2
B157: 4 | C157: Nasi Putih | D157: 180 | E157: gr | G157: =D157*F154 -> 360
B158: 5 | C158: Curry Sauce | D158: 1 | E158: pcs | G158: =D158*F154 -> 2
A159: Curry Omurice | B159: 1 | C159: Telor Ayam | D159: 2 | E159: pcs | F159: =VLOOKUP(A159, '15062026'!$I$130:$J$158, 2, ) -> 1 | G159: =D159*F159 -> 2
B160: 2 | C160: Bowl Mangkok | D160: 1 | E160: pcs | G160: =D160*F159 -> 1
B161: 3 | C161: Tutup Mangkok | D161: 1 | E161: pcs | G161: =D161*F159 -> 1
B162: 4 | C162: Nasi Putih | D162: 180 | E162: gr | G162: =D162*F159 -> 180
B163: 5 | C163: Curry Sauce | D163: 1 | E163: pcs | G163: =D163*F159 -> 1
B164: 6 | C164: Gula Pasir | D164: 3 | E164: gr | G164: =D164*F159 -> 3
B165: 7 | C165: Dashi Halal | D165: 3 | E165: gr | G165: =D165*F159 -> 3
B166: 8 | C166: Mirin Halal | D166: 5 | E166: gr | G166: =D166*F159 -> 5
A167: Miso Sup | B167: 1 | C167: miso soup | D167: 1 | E167: porsi | F167: =VLOOKUP(A167, '15062026'!$I$130:$J$158, 2, ) -> 8 | G167: =D167*F167 -> 8
B168: 2 | C168: daun bawang | D168: 1 | E168: Pcs | G168: =D168*F167 -> 8
...

Sheet 14062026
A1: PLATFORM | B1: Tanggal | C1: Nama Item | D1: HPP | E1: Jumlah | F1: Jumlah QR | G1: Total Jumlah | H1: Total | I1: Total HPP | J1: Uang Masuk | K1: Margin | L1: Gross Profit
A2: SHOPEE | C2: Matcha Latte | D2: =VLOOKUP(C2, 'LIST HPP'!$B$4:$C$39, 2, ) -> 8805.63 | E2: 0 | G2: =sum(E2:F2) -> 0 | H2: =D2*G2 -> 0 | I2: =sum(H2:H32) -> 557551.38 | J2: 865369 | K2: =(J2-I2)/J2 -> 0.35570678 | L2: =J2-I2 -> 307817.62
C3: Hojicha Latte | D3: =VLOOKUP(C3, 'LIST HPP'!$B$4:$C$39, 2, ) -> 8150.63 | E3: 0 | G3: =sum(E3:F3) -> 0 | H3: =D3*G3 -> 0
C4: Choco Latte | D4: =VLOOKUP(C4, 'LIST HPP'!$B$4:$C$39, 2, ) -> 6013.63 | E4: 0 | G4: =sum(E4:F4) -> 0 | H4: =D4*G4 -> 0
C5: Choco Ichigo Latte | D5: =VLOOKUP(C5, 'LIST HPP'!$B$4:$C$39, 2, ) -> 7131.43 | E5: 0 | G5: =sum(E5:F5) -> 0 | H5: =D5*G5 -> 0
C6: Matcha Tea | D6: =VLOOKUP(C6, 'LIST HPP'!$B$4:$C$39, 2, ) -> 3748.21 | E6: 2 | G6: =sum(E6:F6) -> 2 | H6: =D6*G6 -> 7496.42
C7: Ice Tea | D7: =VLOOKUP(C7, 'LIST HPP'!$B$4:$C$39, 2, ) -> 1448.63 | E7: 15 | G7: =sum(E7:F7) -> 15 | H7: =D7*G7 -> 21729.45
C8: Gyumeshi | D8: =VLOOKUP(C8, 'LIST HPP'!$B$4:$C$39, 2, ) -> 11670 | E8: 3 | G8: =sum(E8:F8) -> 3 | H8: =D8*G8 -> 35010
C9: Karage Don | D9: =VLOOKUP(C9, 'LIST HPP'!$B$4:$C$39, 2, ) -> 9350.16 | E9: 10 | G9: =sum(E9:F9) -> 10 | H9: =D9*G9 -> 93501.6
C10: Hot Honey Karage Don | D10: =VLOOKUP(C10, 'LIST HPP'!$B$4:$C$39, 2, ) -> 9990.16 | E10: 0 | G10: =sum(E10:F10) -> 0 | H10: =D10*G10 -> 0
C11: Chicken Katsu Don | D11: =VLOOKUP(C11, 'LIST HPP'!$B$4:$C$39, 2, ) -> 7445.2 | E11: 40 | G11: =sum(E11:F11) -> 40 | H11: =D11*G11 -> 297808
C12: Gyuniku Ala Carte | D12: =VLOOKUP(C12, 'LIST HPP'!$B$4:$C$39, 2, ) -> 17260 | E12: 0 | G12: =sum(E12:F12) -> 0 | H12: =D12*G12 -> 0
C13: Karage Ala Carte | D13: =VLOOKUP(C13, 'LIST HPP'!$B$4:$C$39, 2, ) -> 14155 | E13: 0 | G13: =sum(E13:F13) -> 0 | H13: =D13*G13 -> 0
C14: Hot Honey Karage Ala Carte | D14: =VLOOKUP(C14, 'LIST HPP'!$B$4:$C$39, 2, ) -> 15435 | E14: 0 | G14: =sum(E14:F14) -> 0 | H14: =D14*G14 -> 0
... C32: Gyuniku Bento | D32: =VLOOKUP(C32, 'LIST HPP'!$B$4:$C$39, 2, ) -> 14616.31 | E32: 1 | G32: =sum(E32:F32) -> 1 | H32: =D32*G32 -> 14616.31
A33: GRAB/ OFFLINE Q | C33: Matcha Latte | D33: =VLOOKUP(C33, 'LIST HPP'!$B$4:$C$39, 2, ) -> 8805.63 | E33: 0 | G33: =SUM(E33:F33) -> 0 | H33: =D33*G33 -> 0 | I33: =sum(H33:H63) -> 305246.67 | J33: 480751 | K33: =(J33-I33)/J33 -> 0.36506285 | L33: =J33-I33 -> 175504.33
C34: Hojicha Latte | D34: =VLOOKUP(C34, 'LIST HPP'!$B$4:$C$39, 2, ) -> 8150.63 | E34: 0 | G34: =SUM(E34:F34) -> 0 | H34: =D34*G34 -> 0
C35: Choco Latte | D35: =VLOOKUP(C35, 'LIST HPP'!$B$4:$C$39, 2, ) -> 6013.63 | E35: 2 | G35: =SUM(E35:F35) -> 2 | H35: =D35*G35 -> 12027.26
C36: Choco Ichigo Latte | D36: =VLOOKUP(C36, 'LIST HPP'!$B$4:$C$39, 2, ) -> 7131.43 | E36: 1 | G36: =SUM(E36:F36) -> 1 | H36: =D36*G36 -> 7131.43
C37: Matcha Tea | D37: =VLOOKUP(C37, 'LIST HPP'!$B$4:$C$39, 2, ) -> 3748.21 | E37: 0 | G37: =SUM(E37:F37) -> 0 | H37: =D37*G37 -> 0
C38: Ice Tea | D38: =VLOOKUP(C38, 'LIST HPP'!$B$4:$C$39, 2, ) -> 1448.63 | E38: 10 | G38: =SUM(E38:F38) -> 10 | H38: =D38*G38 -> 14486.3
C39: Gyumeshi | D39: =VLOOKUP(C39, 'LIST HPP'!$B$4:$C$39, 2, ) -> 11670 | E39: 4 | G39: =SUM(E39:F39) -> 4 | H39: =D39*G39 -> 46680
C40: Karage Don | D40: =VLOOKUP(C40, 'LIST HPP'!$B$4:$C$39, 2, ) -> 9350.16 | E40: 2 | G40: =SUM(E40:F40) -> 2 | H40: =D40*G40 -> 18700.32
C41: Hot Honey Karage Don | D41: =VLOOKUP(C41, 'LIST HPP'!$B$4:$C$39, 2, ) -> 9990.16 | E41: 0 | G41: =SUM(E41:F41) -> 0 | H41: =D41*G41 -> 0
C42: Chicken Katsu Don | D42: =VLOOKUP(C42, 'LIST HPP'!$B$4:$C$39, 2, ) -> 7445.2 | E42: 9 | G42: =SUM(E42:F42) -> 9 | H42: =D42*G42 -> 67006.8
C43: Gyuniku Ala Carte | D43: =VLOOKUP(C43, 'LIST HPP'!$B$4:$C$39, 2, ) -> 17260 | E43: 1 | G43: =SUM(E43:F43) -> 1 | H43: =D43*G43 -> 17260
C44: Karage Ala Carte | D44: =VLOOKUP(C44, 'LIST HPP'!$B$4:$C$39, 2, ) -> 14155 | E44: 1 | G44: =SUM(E44:F44) -> 1 | H44: =D44*G44 -> 14155
C45: Hot Honey Karage Ala Carte | D45: =VLOOKUP(C45, 'LIST HPP'!$B$4:$C$39, 2, ) -> 15435 | E45: 1 | G45: =SUM(E45:F45) -> 1 | H45: =D45*G45 -> 15435
... C63: Gyuniku Bento | D63: =VLOOKUP(C63, 'LIST HPP'!$B$4:$C$39, 2, ) -> 14616.31 | E63: 1 | G63: =SUM(E63:F63) -> 1 | H63: =D63*G63 -> 14616.31
A64: GOJEK | C64: Matcha Latte | D64: =VLOOKUP(C64, 'LIST HPP'!$B$4:$C$39, 2, ) -> 8805.63 | E64: 0 | G64: =Sum(E64:F64) -> 0 | H64: =D64*G64 -> 0 | I64: =sum(H64:H94) -> 92264.22 | J64: 189434 | K64: =(J64-I64)/J64 -> 0.51294794 | L64: =J64-I64 -> 97169.78
C65: Hojicha Latte | D65: =VLOOKUP(C65, 'LIST HPP'!$B$4:$C$39, 2, ) -> 8150.63 | E65: 0 | G65: =Sum(E65:F65) -> 0 | H65: =D65*G65 -> 0
C66: Choco Latte | D66: =VLOOKUP(C66, 'LIST HPP'!$B$4:$C$39, 2, ) -> 6013.63 | E66: 1 | G66: =Sum(E66:F66) -> 1 | H66: =D66*G66 -> 6013.63
C67: Choco Ichigo Latte | D67: =VLOOKUP(C67, 'LIST HPP'!$B$4:$C$39, 2, ) -> 7131.43 | E67: 1 | G67: =Sum(E67:F67) -> 1 | H67: =D67*G67 -> 7131.43
C68: Matcha Tea | D68: =VLOOKUP(C68, 'LIST HPP'!$B$4:$C$39, 2, ) -> 3748.21 | E68: 0 | G68: =Sum(E68:F68) -> 0 | H68: =D68*G68 -> 0
C69: Ice Tea | D69: =VLOOKUP(C69, 'LIST HPP'!$B$4:$C$39, 2, ) -> 1448.63 | E69: 2 | G69: =Sum(E69:F69) -> 2 | H69: =D69*G69 -> 2897.26
C70: Gyumeshi | D70: =VLOOKUP(C70, 'LIST HPP'!$B$4:$C$39, 2, ) -> 11670 | E70: 0 | G70: =Sum(E70:F70) -> 0 | H70: =D70*G70 -> 0
C71: Karage Don | D71: =VLOOKUP(C71, 'LIST HPP'!$B$4:$C$39, 2, ) -> 9350.16 | E71: 0 | G71: =Sum(E71:F71) -> 0 | H71: =D71*G71 -> 0
C72: Hot Honey Karage Don | D72: =VLOOKUP(C72, 'LIST HPP'!$B$4:$C$39, 2, ) -> 9990.16 | E72: 4 | G72: =Sum(E72:F72) -> 4 | H72: =D72*G72 -> 39960.64
C73: Chicken Katsu Don | D73: =VLOOKUP(C73, 'LIST HPP'!$B$4:$C$39, 2, ) -> 7445.2 | E73: 3 | G73: =Sum(E73:F73) -> 3 | H73: =D73*G73 -> 22335.6
C74: Gyuniku Ala Carte | D74: =VLOOKUP(C74, 'LIST HPP'!$B$4:$C$39, 2, ) -> 17260 | E74: 0 | G74: =Sum(E74:F74) -> 0 | H74: =D74*G74 -> 0
C75: Karage Ala Carte | D75: =VLOOKUP(C75, 'LIST HPP'!$B$4:$C$39, 2, ) -> 14155 | E75: 0 | G75: =Sum(E75:F75) -> 0 | H75: =D75*G75 -> 0
C76: Hot Honey Karage Ala Carte | D76: =VLOOKUP(C76, 'LIST HPP'!$B$4:$C$39, 2, ) -> 15435 | E76: 0 | G76: =Sum(E76:F76) -> 0 | H76: =D76*G76 -> 0
... C93: Kaarage Bento | D93: =VLOOKUP(C93, 'LIST HPP'!$B$4:$C$39, 2, ) -> 12796.31 | E93: 0 | G93: =Sum(E93:F93) -> 0 | H93: =D93*G93 -> 0
C94: Gyuniku Bento | D94: =VLOOKUP(C94, 'LIST HPP'!$B$4:$C$39, 2, FALSE) -> 14616.31 | E94: 0 | G94: =Sum(E94:F94) -> 0 | H94: =D94*G94 -> 0
C95: Matcha Latte | D95: =VLOOKUP(C95, 'LIST HPP'!$B$4:$C$39, 2, FALSE) -> 8805.63 | G95: =sum(E95:F95) -> 0 | H95: =D95*G95 -> 0 | I95: =sum(H95:H125) -> 0 | K95: =(J95-I95)/J95 -> #DIV/0! | L95: =J95-I95 -> 0
C96: Hojicha Latte | D96: =VLOOKUP(C96, 'LIST HPP'!$B$4:$C$39, 2, FALSE) -> 8150.63 | G96: =sum(E96:F96) -> 0 | H96: =D96*G96 -> 0
C97: Choco Latte | D97: =VLOOKUP(C97, 'LIST HPP'!$B$4:$C$39, 2, FALSE) -> 6013.63 | G97: =sum(E97:F97) -> 0 | H97: =D97*G97 -> 0
C98: Choco Ichigo Latte | D98: =VLOOKUP(C98, 'LIST HPP'!$B$4:$C$39, 2, FALSE) -> 7131.43 | G98: =sum(E98:F98) -> 0 | H98: =D98*G98 -> 0
C99: Matcha Tea | D99: =VLOOKUP(C99, 'LIST HPP'!$B$4:$C$39, 2, FALSE) -> 3748.21 | G99: =sum(E99:F99) -> 0 | H99: =D99*G99 -> 0
C100: Ice Tea | D100: =VLOOKUP(C100, 'LIST HPP'!$B$4:$C$39, 2, FALSE) -> 1448.63 | G100: =sum(E100:F100) -> 0 | H100: =D100*G100 -> 0
C101: Gyumeshi | D101: =VLOOKUP(C101, 'LIST HPP'!$B$4:$C$39, 2, FALSE) -> 11670 | G101: =sum(E101:F101) -> 0 | H101: =D101*G101 -> 0
C102: Karage Don | D102: =VLOOKUP(C102, 'LIST HPP'!$B$4:$C$39, 2, FALSE) -> 9350.16 | G102: =sum(E102:F102) -> 0 | H102: =D102*G102 -> 0
C103: Hot Honey Karage Don | D103: =VLOOKUP(C103, 'LIST HPP'!$B$4:$C$39, 2, FALSE) -> 9990.16 | G103: =sum(E103:F103) -> 0 | H103: =D103*G103 -> 0
C104: Chicken Katsu Don | D104: =VLOOKUP(C104, 'LIST HPP'!$B$4:$C$39, 2, FALSE) -> 7445.2 | G104: =sum(E104:F104) -> 0 | H104: =D104*G104 -> 0
C105: Gyuniku Ala Carte | D105: =VLOOKUP(C105, 'LIST HPP'!$B$4:$C$39, 2, FALSE) -> 17260 | G105: =sum(E105:F105) -> 0 | H105: =D105*G105 -> 0
C106: Karage Ala Carte | D106: =VLOOKUP(C106, 'LIST HPP'!$B$4:$C$39, 2, FALSE) -> 14155 | G106: =sum(E106:F106) -> 0 | H106: =D106*G106 -> 0
C107: Hot Honey Karage Ala Carte | D107: =VLOOKUP(C107, 'LIST HPP'!$B$4:$C$39, 2, FALSE) -> 15435 | G107: =sum(E107:F107) -> 0 | H107: =D107*G107 -> 0
... C125: Gyuniku Bento | D125: =VLOOKUP(C125, 'LIST HPP'!$B$4:$C$39, 2, FALSE) -> 14616.31 | G125: =sum(E125:F125) -> 0 | H125: =D125*G125 -> 0
B126: =#REF! -> #REF! | I126: =SUM(I2:I125) -> 955062.27 | J126: =SUM(J2:J125) -> 1535554 | L126: =SUM(L2:L125) -> 580491.73
A128: Stock Opname Inventory | I128: TOTAL JUMLAH ITEM TERJUAL
A129: Menu | B129: No | F129: Data Penjualan
C130: Bahan | D130: Berat | E130: Satuan | F130: Porsi | G130: Total Bahan Terpakai
A131: Gyumeshi | B131: 1 | C131: Daging Blackpepper | D131: 70 | E131: gr | F131: =VLOOKUP(A131, '14062026'!$I$130:$J$158, 2, ) -> 7 | G131: =D131*F131 -> 490
B132: 2 | C132: Bowl Mangkok | D132: 1 | E132: pcs | G132: =D132*F131 -> 7
B133: 3 | C133: Tutup Mangkok | D133: 1 | E133: pcs | G133: =D133*F131 -> 7
B134: 4 | C134: inner tray bowl | D134: 1 | E134: pcs | G134: =D134*F131 -> 7
B135: 5 | C135: Nasi Putih | D135: 180 | E135: gr | G135: =D135*F131 -> 1260
A136: Karage Don | B136: 1 | C136: Ayam Karage | D136: 130 | E136: gr | F136: =VLOOKUP(A136, '14062026'!$I$130:$J$158, 2, ) -> 12 | G136: =D136*F136 -> 1560
B137: 2 | C137: Bowl Mangkok | D137: 1 | E137: pcs | G137: =D137*F136 -> 12
B138: 3 | C138: Tutup Mangkok | D138: 1 | E138: pcs | G138: =D138*F136 -> 12
B139: 4 | C139: Nasi Putih | D139: 180 | E139: gr | G139: =D139*F136 -> 2160
A140: Hot Honey Karage Don | B140: 1 | C140: Ayam Karage | D140: 130 | E140: gr | F140: =VLOOKUP(A140, '14062026'!$I$130:$J$158, 2, ) -> 4 | G140: =D140*F140 -> 520
B141: 2 | C141: Bowl Mangkok | D141: 1 | E141: pcs | G141: =D141*F140 -> 4
B142: 3 | C142: Tutup Mangkok | D142: 1 | E142: pcs | G142: =D142*F140 -> 4
B143: 4 | C143: Nasi Putih | D143: 180 | E143: gr | G143: =D143*F140 -> 720
B144: 5 | C144: Hot Honey Sauce | D144: 20 | E144: gr | G144: =D144*F140 -> 80
A145: Gyuniku Ala Carte | B145: 1 | C145: Daging Blackpepper | D145: 140 | E145: gr | F145: =VLOOKUP(A145, '14062026'!$I$130:$J$158, 2, ) -> 1 | G145: =D145*F145 -> 140
B146: 2 | C146: thinwall 500ml | D146: 1 | E146: pcs | G146: =D146*F145 -> 1
A147: Karage Ala Carte | B147: 1 | C147: Ayam Karage | D147: 260 | E147: gr | F147: =VLOOKUP(A147, '14062026'!$I$130:$J$158, 2, ) -> 1 | G147: =D147*F147 -> 260
B148: 2 | C148: Bowl Mangkok | D148: 1 | E148: pcs | G148: =D148*F147 -> 1
B149: 3 | C149: Tutup Mangkok | D149: 1 | E149: pcs | G149: =D149*F147 -> 1
A150: Hot Honey Karage Ala Carte | B150: 1 | C150: Ayam Karage | D150: 260 | E150: gr | F150: =VLOOKUP(A150, '14062026'!$I$130:$J$158, 2, ) -> 1 | G150: =D150*F150 -> 260
B151: 2 | C151: Bowl Mangkok | D151: 1 | E151: pcs | G151: =D151*F150 -> 1
B152: 3 | C152: Tutup Mangkok | D152: 1 | E152: pcs | G152: =D152*F150 -> 1
B153: 4 | C153: Hot Honey Sauce | D153: 40 | E153: gr | G153: =D153*F150 -> 40
A154: Curry Karage Don | B154: 1 | C154: Ayam Karage | D154: 130 | E154: porsi | F154: =VLOOKUP(A154, '14062026'!$I$130:$J$158, 2, ) -> 1 | G154: =D154*F154 -> 130
B155: 2 | C155: Bowl Mangkok | D155: 1 | E155: pcs | G155: =D155*F154 -> 1
B156: 3 | C156: Tutup Mangkok | D156: 1 | E156: pcs | G156: =D156*F154 -> 1
B157: 4 | C157: Nasi Putih | D157: 180 | E157: gr | G157: =D157*F154 -> 180
B158: 5 | C158: Curry Sauce | D158: 1 | E158: pcs | G158: =D158*F154 -> 1
A159: Curry Omurice | B159: 1 | C159: Telor Ayam | D159: 2 | E159: pcs | F159: =VLOOKUP(A159, '14062026'!$I$130:$J$158, 2, ) -> 1 | G159: =D159*F159 -> 2
B160: 2 | C160: Bowl Mangkok | D160: 1 | E160: pcs | G160: =D160*F159 -> 1
B161: 3 | C161: Tutup Mangkok | D161: 1 | E161: pcs | G161: =D161*F159 -> 1
B162: 4 | C162: Nasi Putih | D162: 180 | E162: gr | G162: =D162*F159 -> 180
B163: 5 | C163: Curry Sauce | D163: 1 | E163: pcs | G163: =D163*F159 -> 1
B164: 6 | C164: Gula Pasir | D164: 3 | E164: gr | G164: =D164*F159 -> 3
B165: 7 | C165: Dashi Halal | D165: 3 | E165: gr | G165: =D165*F159 -> 3
B166: 8 | C166: Mirin Halal | D166: 5 | E166: gr | G166: =D166*F159 -> 5
A167: Miso Sup | B167: 1 | C167: miso soup | D167: 1 | E167: porsi | F167: =VLOOKUP(A167, '14062026'!$I$130:$J$158, 2, ) -> 9 | G167: =D167*F167 -> 9
B168: 2 | C168: daun bawang | D168: 1 | E168: Pcs | G168: =D168*F167 -> 9
...

Sheet 13062026
A1: PLATFORM | B1: Tanggal | C1: Nama Item | D1: HPP | E1: Jumlah | F1: Jumlah QR | G1: Total Jumlah | H1: Total | I1: Total HPP | J1: Uang Masuk | K1: Margin | L1: Gross Profit
A2: SHOPEE | C2: Matcha Latte | D2: =VLOOKUP(C2, 'LIST HPP'!$B$4:$C$39, 2, ) -> 8805.63 | E2: 0 | G2: =sum(E2:F2) -> 0 | H2: =D2*G2 -> 0 | I2: =sum(H2:H32) -> 332308.58 | J2: 513337 | K2: =(J2-I2)/J2 -> 0.35265025 | L2: =J2-I2 -> 181028.42
C3: Hojicha Latte | D3: =VLOOKUP(C3, 'LIST HPP'!$B$4:$C$39, 2, ) -> 8150.63 | E3: 0 | G3: =sum(E3:F3) -> 0 | H3: =D3*G3 -> 0
C4: Choco Latte | D4: =VLOOKUP(C4, 'LIST HPP'!$B$4:$C$39, 2, ) -> 6013.63 | E4: 0 | G4: =sum(E4:F4) -> 0 | H4: =D4*G4 -> 0
C5: Choco Ichigo Latte | D5: =VLOOKUP(C5, 'LIST HPP'!$B$4:$C$39, 2, ) -> 7131.43 | E5: 0 | G5: =sum(E5:F5) -> 0 | H5: =D5*G5 -> 0
C6: Matcha Tea | D6: =VLOOKUP(C6, 'LIST HPP'!$B$4:$C$39, 2, ) -> 3748.21 | E6: 0 | G6: =sum(E6:F6) -> 0 | H6: =D6*G6 -> 0
C7: Ice Tea | D7: =VLOOKUP(C7, 'LIST HPP'!$B$4:$C$39, 2, ) -> 1448.63 | E7: 6 | G7: =sum(E7:F7) -> 6 | H7: =D7*G7 -> 8691.78
C8: Gyumeshi | D8: =VLOOKUP(C8, 'LIST HPP'!$B$4:$C$39, 2, ) -> 11670 | E8: 2 | G8: =sum(E8:F8) -> 2 | H8: =D8*G8 -> 23340
C9: Karage Don | D9: =VLOOKUP(C9, 'LIST HPP'!$B$4:$C$39, 2, ) -> 9350.16 | E9: 5 | G9: =sum(E9:F9) -> 5 | H9: =D9*G9 -> 46750.8
C10: Hot Honey Karage Don | D10: =VLOOKUP(C10, 'LIST HPP'!$B$4:$C$39, 2, ) -> 9990.16 | E10: 0 | G10: =sum(E10:F10) -> 0 | H10: =D10*G10 -> 0
C11: Chicken Katsu Don | D11: =VLOOKUP(C11, 'LIST HPP'!$B$4:$C$39, 2, ) -> 7445.2 | E11: 21 | G11: =sum(E11:F11) -> 21 | H11: =D11*G11 -> 156349.2
C12: Gyuniku Ala Carte | D12: =VLOOKUP(C12, 'LIST HPP'!$B$4:$C$39, 2, ) -> 17260 | E12: 0 | G12: =sum(E12:F12) -> 0 | H12: =D12*G12 -> 0
C13: Karage Ala Carte | D13: =VLOOKUP(C13, 'LIST HPP'!$B$4:$C$39, 2, ) -> 14155 | E13: 1 | G13: =sum(E13:F13) -> 1 | H13: =D13*G13 -> 14155
C14: Hot Honey Karage Ala Carte | D14: =VLOOKUP(C14, 'LIST HPP'!$B$4:$C$39, 2, ) -> 15435 | E14: 0 | G14: =sum(E14:F14) -> 0 | H14: =D14*G14 -> 0
... C32: Gyuniku Bento | D32: =VLOOKUP(C32, 'LIST HPP'!$B$4:$C$39, 2, ) -> 14616.31 | E32: 0 | G32: =sum(E32:F32) -> 0 | H32: =D32*G32 -> 0
A33: GRAB/ OFFLINE Q | C33: Matcha Latte | D33: =VLOOKUP(C33, 'LIST HPP'!$B$4:$C$39, 2, ) -> 8805.63 | E33: 0 | G33: =SUM(E33:F33) -> 0 | H33: =D33*G33 -> 0 | I33: =sum(H33:H63) -> 223785.97 | J33: 382521 | K33: =(J33-I33)/J33 -> 0.41497076 | L33: =J33-I33 -> 158735.03
C34: Hojicha Latte | D34: =VLOOKUP(C34, 'LIST HPP'!$B$4:$C$39, 2, ) -> 8150.63 | E34: 0 | G34: =SUM(E34:F34) -> 0 | H34: =D34*G34 -> 0
C35: Choco Latte | D35: =VLOOKUP(C35, 'LIST HPP'!$B$4:$C$39, 2, ) -> 6013.63 | E35: 1 | G35: =SUM(E35:F35) -> 1 | H35: =D35*G35 -> 6013.63
C36: Choco Ichigo Latte | D36: =VLOOKUP(C36, 'LIST HPP'!$B$4:$C$39, 2, ) -> 7131.43 | E36: 0 | G36: =SUM(E36:F36) -> 0 | H36: =D36*G36 -> 0
C37: Matcha Tea | D37: =VLOOKUP(C37, 'LIST HPP'!$B$4:$C$39, 2, ) -> 3748.21 | E37: 1 | G37: =SUM(E37:F37) -> 1 | H37: =D37*G37 -> 3748.21
C38: Ice Tea | D38: =VLOOKUP(C38, 'LIST HPP'!$B$4:$C$39, 2, ) -> 1448.63 | E38: 2 | G38: =SUM(E38:F38) -> 2 | H38: =D38*G38 -> 2897.26
C39: Gyumeshi | D39: =VLOOKUP(C39, 'LIST HPP'!$B$4:$C$39, 2, ) -> 11670 | E39: 1 | G39: =SUM(E39:F39) -> 1 | H39: =D39*G39 -> 11670
C40: Karage Don | D40: =VLOOKUP(C40, 'LIST HPP'!$B$4:$C$39, 2, ) -> 9350.16 | E40: 0 | G40: =SUM(E40:F40) -> 0 | H40: =D40*G40 -> 0
C41: Hot Honey Karage Don | D41: =VLOOKUP(C41, 'LIST HPP'!$B$4:$C$39, 2, ) -> 9990.16 | E41: 1 | G41: =SUM(E41:F41) -> 1 | H41: =D41*G41 -> 9990.16
C42: Chicken Katsu Don | D42: =VLOOKUP(C42, 'LIST HPP'!$B$4:$C$39, 2, ) -> 7445.2 | E42: 2 | G42: =SUM(E42:F42) -> 2 | H42: =D42*G42 -> 14890.4
C43: Gyuniku Ala Carte | D43: =VLOOKUP(C43, 'LIST HPP'!$B$4:$C$39, 2, ) -> 17260 | E43: 0 | G43: =SUM(E43:F43) -> 0 | H43: =D43*G43 -> 0
C44: Karage Ala Carte | D44: =VLOOKUP(C44, 'LIST HPP'!$B$4:$C$39, 2, ) -> 14155 | E44: 1 | G44: =SUM(E44:F44) -> 1 | H44: =D44*G44 -> 14155
C45: Hot Honey Karage Ala Carte | D45: =VLOOKUP(C45, 'LIST HPP'!$B$4:$C$39, 2, ) -> 15435 | E45: 0 | G45: =SUM(E45:F45) -> 0 | H45: =D45*G45 -> 0
... C63: Gyuniku Bento | D63: =VLOOKUP(C63, 'LIST HPP'!$B$4:$C$39, 2, ) -> 14616.31 | E63: 2 | G63: =SUM(E63:F63) -> 2 | H63: =D63*G63 -> 29232.62
A64: GOJEK | C64: Matcha Latte | D64: =VLOOKUP(C64, 'LIST HPP'!$B$4:$C$39, 2, ) -> 8805.63 | E64: 0 | G64: =Sum(E64:F64) -> 0 | H64: =D64*G64 -> 0 | I64: =sum(H64:H94) -> 77923.92 | J64: 169565 | K64: =(J64-I64)/J64 -> 0.54044809 | L64: =J64-I64 -> 91641.08
C65: Hojicha Latte | D65: =VLOOKUP(C65, 'LIST HPP'!$B$4:$C$39, 2, ) -> 8150.63 | E65: 0 | G65: =Sum(E65:F65) -> 0 | H65: =D65*G65 -> 0
C66: Choco Latte | D66: =VLOOKUP(C66, 'LIST HPP'!$B$4:$C$39, 2, ) -> 6013.63 | E66: 0 | G66: =Sum(E66:F66) -> 0 | H66: =D66*G66 -> 0
C67: Choco Ichigo Latte | D67: =VLOOKUP(C67, 'LIST HPP'!$B$4:$C$39, 2, ) -> 7131.43 | E67: 0 | G67: =Sum(E67:F67) -> 0 | H67: =D67*G67 -> 0
C68: Matcha Tea | D68: =VLOOKUP(C68, 'LIST HPP'!$B$4:$C$39, 2, ) -> 3748.21 | E68: 0 | G68: =Sum(E68:F68) -> 0 | H68: =D68*G68 -> 0
C69: Ice Tea | D69: =VLOOKUP(C69, 'LIST HPP'!$B$4:$C$39, 2, ) -> 1448.63 | E69: 0 | G69: =Sum(E69:F69) -> 0 | H69: =D69*G69 -> 0
C70: Gyumeshi | D70: =VLOOKUP(C70, 'LIST HPP'!$B$4:$C$39, 2, ) -> 11670 | E70: 1 | G70: =Sum(E70:F70) -> 1 | H70: =D70*G70 -> 11670
C71: Karage Don | D71: =VLOOKUP(C71, 'LIST HPP'!$B$4:$C$39, 2, ) -> 9350.16 | E71: 1 | G71: =Sum(E71:F71) -> 1 | H71: =D71*G71 -> 9350.16
C72: Hot Honey Karage Don | D72: =VLOOKUP(C72, 'LIST HPP'!$B$4:$C$39, 2, ) -> 9990.16 | E72: 0 | G72: =Sum(E72:F72) -> 0 | H72: =D72*G72 -> 0
C73: Chicken Katsu Don | D73: =VLOOKUP(C73, 'LIST HPP'!$B$4:$C$39, 2, ) -> 7445.2 | E73: 2 | G73: =Sum(E73:F73) -> 2 | H73: =D73*G73 -> 14890.4
C74: Gyuniku Ala Carte | D74: =VLOOKUP(C74, 'LIST HPP'!$B$4:$C$39, 2, ) -> 17260 | E74: 0 | G74: =Sum(E74:F74) -> 0 | H74: =D74*G74 -> 0
C75: Karage Ala Carte | D75: =VLOOKUP(C75, 'LIST HPP'!$B$4:$C$39, 2, ) -> 14155 | E75: 1 | G75: =Sum(E75:F75) -> 1 | H75: =D75*G75 -> 14155
C76: Hot Honey Karage Ala Carte | D76: =VLOOKUP(C76, 'LIST HPP'!$B$4:$C$39, 2, ) -> 15435 | E76: 0 | G76: =Sum(E76:F76) -> 0 | H76: =D76*G76 -> 0
... C93: Kaarage Bento | D93: =VLOOKUP(C93, 'LIST HPP'!$B$4:$C$39, 2, ) -> 12796.31 | E93: 0 | G93: =Sum(E93:F93) -> 0 | H93: =D93*G93 -> 0
C94: Gyuniku Bento | D94: =VLOOKUP(C94, 'LIST HPP'!$B$4:$C$39, 2, FALSE) -> 14616.31 | E94: 0 | G94: =Sum(E94:F94) -> 0 | H94: =D94*G94 -> 0
C95: Matcha Latte | D95: =VLOOKUP(C95, 'LIST HPP'!$B$4:$C$39, 2, FALSE) -> 8805.63 | G95: =sum(E95:F95) -> 0 | H95: =D95*G95 -> 0 | I95: =sum(H95:H125) -> 0 | K95: =(J95-I95)/J95 -> #DIV/0! | L95: =J95-I95 -> 0
C96: Hojicha Latte | D96: =VLOOKUP(C96, 'LIST HPP'!$B$4:$C$39, 2, FALSE) -> 8150.63 | G96: =sum(E96:F96) -> 0 | H96: =D96*G96 -> 0
C97: Choco Latte | D97: =VLOOKUP(C97, 'LIST HPP'!$B$4:$C$39, 2, FALSE) -> 6013.63 | G97: =sum(E97:F97) -> 0 | H97: =D97*G97 -> 0
C98: Choco Ichigo Latte | D98: =VLOOKUP(C98, 'LIST HPP'!$B$4:$C$39, 2, FALSE) -> 7131.43 | G98: =sum(E98:F98) -> 0 | H98: =D98*G98 -> 0
C99: Matcha Tea | D99: =VLOOKUP(C99, 'LIST HPP'!$B$4:$C$39, 2, FALSE) -> 3748.21 | G99: =sum(E99:F99) -> 0 | H99: =D99*G99 -> 0
C100: Ice Tea | D100: =VLOOKUP(C100, 'LIST HPP'!$B$4:$C$39, 2, FALSE) -> 1448.63 | G100: =sum(E100:F100) -> 0 | H100: =D100*G100 -> 0
C101: Gyumeshi | D101: =VLOOKUP(C101, 'LIST HPP'!$B$4:$C$39, 2, FALSE) -> 11670 | G101: =sum(E101:F101) -> 0 | H101: =D101*G101 -> 0
C102: Karage Don | D102: =VLOOKUP(C102, 'LIST HPP'!$B$4:$C$39, 2, FALSE) -> 9350.16 | G102: =sum(E102:F102) -> 0 | H102: =D102*G102 -> 0
C103: Hot Honey Karage Don | D103: =VLOOKUP(C103, 'LIST HPP'!$B$4:$C$39, 2, FALSE) -> 9990.16 | G103: =sum(E103:F103) -> 0 | H103: =D103*G103 -> 0
C104: Chicken Katsu Don | D104: =VLOOKUP(C104, 'LIST HPP'!$B$4:$C$39, 2, FALSE) -> 7445.2 | G104: =sum(E104:F104) -> 0 | H104: =D104*G104 -> 0
C105: Gyuniku Ala Carte | D105: =VLOOKUP(C105, 'LIST HPP'!$B$4:$C$39, 2, FALSE) -> 17260 | G105: =sum(E105:F105) -> 0 | H105: =D105*G105 -> 0
C106: Karage Ala Carte | D106: =VLOOKUP(C106, 'LIST HPP'!$B$4:$C$39, 2, FALSE) -> 14155 | G106: =sum(E106:F106) -> 0 | H106: =D106*G106 -> 0
C107: Hot Honey Karage Ala Carte | D107: =VLOOKUP(C107, 'LIST HPP'!$B$4:$C$39, 2, FALSE) -> 15435 | G107: =sum(E107:F107) -> 0 | H107: =D107*G107 -> 0
... C125: Gyuniku Bento | D125: =VLOOKUP(C125, 'LIST HPP'!$B$4:$C$39, 2, FALSE) -> 14616.31 | G125: =sum(E125:F125) -> 0 | H125: =D125*G125 -> 0
B126: =#REF! -> #REF! | I126: =SUM(I2:I125) -> 634018.47 | J126: =SUM(J2:J125) -> 1065423 | L126: =SUM(L2:L125) -> 431404.53
A128: Stock Opname Inventory | I128: TOTAL JUMLAH ITEM TERJUAL
A129: Menu | B129: No | F129: Data Penjualan
C130: Bahan | D130: Berat | E130: Satuan | F130: Porsi | G130: Total Bahan Terpakai
A131: Gyumeshi | B131: 1 | C131: Daging Blackpepper | D131: 70 | E131: gr | F131: =VLOOKUP(A131, '13062026'!$I$130:$J$158, 2, ) -> 4 | G131: =D131*F131 -> 280
B132: 2 | C132: Bowl Mangkok | D132: 1 | E132: pcs | G132: =D132*F131 -> 4
B133: 3 | C133: Tutup Mangkok | D133: 1 | E133: pcs | G133: =D133*F131 -> 4
B134: 4 | C134: inner tray bowl | D134: 1 | E134: pcs | G134: =D134*F131 -> 4
B135: 5 | C135: Nasi Putih | D135: 180 | E135: gr | G135: =D135*F131 -> 720
A136: Karage Don | B136: 1 | C136: Ayam Karage | D136: 130 | E136: gr | F136: =VLOOKUP(A136, '13062026'!$I$130:$J$158, 2, ) -> 6 | G136: =D136*F136 -> 780
B137: 2 | C137: Bowl Mangkok | D137: 1 | E137: pcs | G137: =D137*F136 -> 6
B138: 3 | C138: Tutup Mangkok | D138: 1 | E138: pcs | G138: =D138*F136 -> 6
B139: 4 | C139: Nasi Putih | D139: 180 | E139: gr | G139: =D139*F136 -> 1080
A140: Hot Honey Karage Don | B140: 1 | C140: Ayam Karage | D140: 130 | E140: gr | F140: =VLOOKUP(A140, '13062026'!$I$130:$J$158, 2, ) -> 1 | G140: =D140*F140 -> 130
B141: 2 | C141: Bowl Mangkok | D141: 1 | E141: pcs | G141: =D141*F140 -> 1
B142: 3 | C142: Tutup Mangkok | D142: 1 | E142: pcs | G142: =D142*F140 -> 1
B143: 4 | C143: Nasi Putih | D143: 180 | E143: gr | G143: =D143*F140 -> 180
B144: 5 | C144: Hot Honey Sauce | D144: 20 | E144: gr | G144: =D144*F140 -> 20
A145: Gyuniku Ala Carte | B145: 1 | C145: Daging Blackpepper | D145: 140 | E145: gr | F145: =VLOOKUP(A145, '13062026'!$I$130:$J$158, 2, ) -> 0 | G145: =D145*F145 -> 0
B146: 2 | C146: thinwall 500ml | D146: 1 | E146: pcs | G146: =D146*F145 -> 0
A147: Karage Ala Carte | B147: 1 | C147: Ayam Karage | D147: 260 | E147: gr | F147: =VLOOKUP(A147, '13062026'!$I$130:$J$158, 2, ) -> 3 | G147: =D147*F147 -> 780
B148: 2 | C148: Bowl Mangkok | D148: 1 | E148: pcs | G148: =D148*F147 -> 3
B149: 3 | C149: Tutup Mangkok | D149: 1 | E149: pcs | G149: =D149*F147 -> 3
A150: Hot Honey Karage Ala Carte | B150: 1 | C150: Ayam Karage | D150: 260 | E150: gr | F150: =VLOOKUP(A150, '13062026'!$I$130:$J$158, 2, ) -> 0 | G150: =D150*F150 -> 0
B151: 2 | C151: Bowl Mangkok | D151: 1 | E151: pcs | G151: =D151*F150 -> 0
B152: 3 | C152: Tutup Mangkok | D152: 1 | E152: pcs | G152: =D152*F150 -> 0
B153: 4 | C153: Hot Honey Sauce | D153: 40 | E153: gr | G153: =D153*F150 -> 0
A154: Curry Karage Don | B154: 1 | C154: Ayam Karage | D154: 130 | E154: porsi | F154: =VLOOKUP(A154, '13062026'!$I$130:$J$158, 2, ) -> 0 | G154: =D154*F154 -> 0
B155: 2 | C155: Bowl Mangkok | D155: 1 | E155: pcs | G155: =D155*F154 -> 0
B156: 3 | C156: Tutup Mangkok | D156: 1 | E156: pcs | G156: =D156*F154 -> 0
B157: 4 | C157: Nasi Putih | D157: 180 | E157: gr | G157: =D157*F154 -> 0
B158: 5 | C158: Curry Sauce | D158: 1 | E158: pcs | G158: =D158*F154 -> 0
A159: Curry Omurice | B159: 1 | C159: Telor Ayam | D159: 2 | E159: pcs | F159: =VLOOKUP(A159, '13062026'!$I$130:$J$158, 2, ) -> 5 | G159: =D159*F159 -> 10
B160: 2 | C160: Bowl Mangkok | D160: 1 | E160: pcs | G160: =D160*F159 -> 5
B161: 3 | C161: Tutup Mangkok | D161: 1 | E161: pcs | G161: =D161*F159 -> 5
B162: 4 | C162: Nasi Putih | D162: 180 | E162: gr | G162: =D162*F159 -> 900
B163: 5 | C163: Curry Sauce | D163: 1 | E163: pcs | G163: =D163*F159 -> 5
B164: 6 | C164: Gula Pasir | D164: 3 | E164: gr | G164: =D164*F159 -> 15
B165: 7 | C165: Dashi Halal | D165: 3 | E165: gr | G165: =D165*F159 -> 15
B166: 8 | C166: Mirin Halal | D166: 5 | E166: gr | G166: =D166*F159 -> 25
A167: Miso Sup | B167: 1 | C167: miso soup | D167: 1 | E167: porsi | F167: =VLOOKUP(A167, '13062026'!$I$130:$J$158, 2, ) -> 5 | G167: =D167*F167 -> 5
B168: 2 | C168: daun bawang | D168: 1 | E168: Pcs | G168: =D168*F167 -> 5
...

Sheet 12062026
A1: PLATFORM | B1: Tanggal | C1: Nama Item | D1: HPP | E1: Jumlah | F1: Jumlah QR | G1: Total Jumlah | H1: Total | I1: Total HPP | J1: Uang Masuk | K1: Margin | L1: Gross Profit
A2: SHOPEE | C2: Matcha Latte | D2: =VLOOKUP(C2, 'LIST HPP'!$B$4:$C$39, 2, ) -> 8805.63 | E2: 0 | G2: =sum(E2:F2) -> 0 | H2: =D2*G2 -> 0 | I2: =sum(H2:H32) -> 285121.27 | J2: 462620 | K2: =(J2-I2)/J2 -> 0.38368149 | L2: =J2-I2 -> 177498.73
C3: Hojicha Latte | D3: =VLOOKUP(C3, 'LIST HPP'!$B$4:$C$39, 2, ) -> 8150.63 | E3: 0 | G3: =sum(E3:F3) -> 0 | H3: =D3*G3 -> 0
C4: Choco Latte | D4: =VLOOKUP(C4, 'LIST HPP'!$B$4:$C$39, 2, ) -> 6013.63 | E4: 0 | G4: =sum(E4:F4) -> 0 | H4: =D4*G4 -> 0
C5: Choco Ichigo Latte | D5: =VLOOKUP(C5, 'LIST HPP'!$B$4:$C$39, 2, ) -> 7131.43 | E5: 0 | G5: =sum(E5:F5) -> 0 | H5: =D5*G5 -> 0
C6: Matcha Tea | D6: =VLOOKUP(C6, 'LIST HPP'!$B$4:$C$39, 2, ) -> 3748.21 | E6: 0 | G6: =sum(E6:F6) -> 0 | H6: =D6*G6 -> 0
C7: Ice Tea | D7: =VLOOKUP(C7, 'LIST HPP'!$B$4:$C$39, 2, ) -> 1448.63 | E7: 7 | G7: =sum(E7:F7) -> 7 | H7: =D7*G7 -> 10140.41
C8: Gyumeshi | D8: =VLOOKUP(C8, 'LIST HPP'!$B$4:$C$39, 2, ) -> 11670 | E8: 1 | G8: =sum(E8:F8) -> 1 | H8: =D8*G8 -> 11670
C9: Karage Don | D9: =VLOOKUP(C9, 'LIST HPP'!$B$4:$C$39, 2, ) -> 9350.16 | E9: 2 | G9: =sum(E9:F9) -> 2 | H9: =D9*G9 -> 18700.32
C10: Hot Honey Karage Don | D10: =VLOOKUP(C10, 'LIST HPP'!$B$4:$C$39, 2, ) -> 9990.16 | E10: 1 | G10: =sum(E10:F10) -> 1 | H10: =D10*G10 -> 9990.16
C11: Chicken Katsu Don | D11: =VLOOKUP(C11, 'LIST HPP'!$B$4:$C$39, 2, ) -> 7445.2 | E11: 20 | G11: =sum(E11:F11) -> 20 | H11: =D11*G11 -> 148904
C12: Gyuniku Ala Carte | D12: =VLOOKUP(C12, 'LIST HPP'!$B$4:$C$39, 2, ) -> 17260 | E12: 0 | G12: =sum(E12:F12) -> 0 | H12: =D12*G12 -> 0
C13: Karage Ala Carte | D13: =VLOOKUP(C13, 'LIST HPP'!$B$4:$C$39, 2, ) -> 14155 | E13: 0 | G13: =sum(E13:F13) -> 0 | H13: =D13*G13 -> 0
C14: Hot Honey Karage Ala Carte | D14: =VLOOKUP(C14, 'LIST HPP'!$B$4:$C$39, 2, ) -> 15435 | E14: 0 | G14: =sum(E14:F14) -> 0 | H14: =D14*G14 -> 0
... C32: Gyuniku Bento | D32: =VLOOKUP(C32, 'LIST HPP'!$B$4:$C$39, 2, ) -> 14616.31 | E32: 0 | G32: =sum(E32:F32) -> 0 | H32: =D32*G32 -> 0
A33: GRAB/ OFFLINE Q | C33: Matcha Latte | D33: =VLOOKUP(C33, 'LIST HPP'!$B$4:$C$39, 2, ) -> 8805.63 | E33: 0 | G33: =SUM(E33:F33) -> 0 | H33: =D33*G33 -> 0 | I33: =sum(H33:H63) -> 483286.76 | J33: 982650 | K33: =(J33-I33)/J33 -> 0.50818017 | L33: =J33-I33 -> 499363.24
C34: Hojicha Latte | D34: =VLOOKUP(C34, 'LIST HPP'!$B$4:$C$39, 2, ) -> 8150.63 | E34: 0 | G34: =SUM(E34:F34) -> 0 | H34: =D34*G34 -> 0
C35: Choco Latte | D35: =VLOOKUP(C35, 'LIST HPP'!$B$4:$C$39, 2, ) -> 6013.63 | E35: 0 | G35: =SUM(E35:F35) -> 0 | H35: =D35*G35 -> 0
C36: Choco Ichigo Latte | D36: =VLOOKUP(C36, 'LIST HPP'!$B$4:$C$39, 2, ) -> 7131.43 | E36: 1 | G36: =SUM(E36:F36) -> 1 | H36: =D36*G36 -> 7131.43
C37: Matcha Tea | D37: =VLOOKUP(C37, 'LIST HPP'!$B$4:$C$39, 2, ) -> 3748.21 | E37: 0 | G37: =SUM(E37:F37) -> 0 | H37: =D37*G37 -> 0
C38: Ice Tea | D38: =VLOOKUP(C38, 'LIST HPP'!$B$4:$C$39, 2, ) -> 1448.63 | E38: 6 | G38: =SUM(E38:F38) -> 6 | H38: =D38*G38 -> 8691.78
C39: Gyumeshi | D39: =VLOOKUP(C39, 'LIST HPP'!$B$4:$C$39, 2, ) -> 11670 | E39: 0 | G39: =SUM(E39:F39) -> 0 | H39: =D39*G39 -> 0
C40: Karage Don | D40: =VLOOKUP(C40, 'LIST HPP'!$B$4:$C$39, 2, ) -> 9350.16 | E40: 1 | G40: =SUM(E40:F40) -> 1 | H40: =D40*G40 -> 9350.16
C41: Hot Honey Karage Don | D41: =VLOOKUP(C41, 'LIST HPP'!$B$4:$C$39, 2, ) -> 9990.16 | E41: 0 | G41: =SUM(E41:F41) -> 0 | H41: =D41*G41 -> 0
C42: Chicken Katsu Don | D42: =VLOOKUP(C42, 'LIST HPP'!$B$4:$C$39, 2, ) -> 7445.2 | E42: 6 | G42: =SUM(E42:F42) -> 6 | H42: =D42*G42 -> 44671.2
C43: Gyuniku Ala Carte | D43: =VLOOKUP(C43, 'LIST HPP'!$B$4:$C$39, 2, ) -> 17260 | E43: 0 | G43: =SUM(E43:F43) -> 0 | H43: =D43*G43 -> 0
C44: Karage Ala Carte | D44: =VLOOKUP(C44, 'LIST HPP'!$B$4:$C$39, 2, ) -> 14155 | E44: 2 | G44: =SUM(E44:F44) -> 2 | H44: =D44*G44 -> 28310
C45: Hot Honey Karage Ala Carte | D45: =VLOOKUP(C45, 'LIST HPP'!$B$4:$C$39, 2, ) -> 15435 | E45: 2 | G45: =SUM(E45:F45) -> 2 | H45: =D45*G45 -> 30870
... C63: Gyuniku Bento | D63: =VLOOKUP(C63, 'LIST HPP'!$B$4:$C$39, 2, ) -> 14616.31 | E63: 15 | G63: =SUM(E63:F63) -> 15 | H63: =D63*G63 -> 219244.65
A64: GOJEK | C64: Matcha Latte | D64: =VLOOKUP(C64, 'LIST HPP'!$B$4:$C$39, 2, ) -> 8805.63 | E64: 0 | G64: =Sum(E64:F64) -> 0 | H64: =D64*G64 -> 0 | I64: =sum(H64:H94) -> 60193.34 | J64: 126268 | K64: =(J64-I64)/J64 -> 0.52328904 | L64: =J64-I64 -> 66074.66
C65: Hojicha Latte | D65: =VLOOKUP(C65, 'LIST HPP'!$B$4:$C$39, 2, ) -> 8150.63 | E65: 0 | G65: =Sum(E65:F65) -> 0 | H65: =D65*G65 -> 0
C66: Choco Latte | D66: =VLOOKUP(C66, 'LIST HPP'!$B$4:$C$39, 2, ) -> 6013.63 | E66: 0 | G66: =Sum(E66:F66) -> 0 | H66: =D66*G66 -> 0
C67: Choco Ichigo Latte | D67: =VLOOKUP(C67, 'LIST HPP'!$B$4:$C$39, 2, ) -> 7131.43 | E67: 0 | G67: =Sum(E67:F67) -> 0 | H67: =D67*G67 -> 0
C68: Matcha Tea | D68: =VLOOKUP(C68, 'LIST HPP'!$B$4:$C$39, 2, ) -> 3748.21 | E68: 0 | G68: =Sum(E68:F68) -> 0 | H68: =D68*G68 -> 0
C69: Ice Tea | D69: =VLOOKUP(C69, 'LIST HPP'!$B$4:$C$39, 2, ) -> 1448.63 | E69: 0 | G69: =Sum(E69:F69) -> 0 | H69: =D69*G69 -> 0
C70: Gyumeshi | D70: =VLOOKUP(C70, 'LIST HPP'!$B$4:$C$39, 2, ) -> 11670 | E70: 1 | G70: =Sum(E70:F70) -> 1 | H70: =D70*G70 -> 11670
C71: Karage Don | D71: =VLOOKUP(C71, 'LIST HPP'!$B$4:$C$39, 2, ) -> 9350.16 | E71: 2 | G71: =Sum(E71:F71) -> 2 | H71: =D71*G71 -> 18700.32
C72: Hot Honey Karage Don | D72: =VLOOKUP(C72, 'LIST HPP'!$B$4:$C$39, 2, ) -> 9990.16 | E72: 1 | G72: =Sum(E72:F72) -> 1 | H72: =D72*G72 -> 9990.16
C73: Chicken Katsu Don | D73: =VLOOKUP(C73, 'LIST HPP'!$B$4:$C$39, 2, ) -> 7445.2 | E73: 1 | G73: =Sum(E73:F73) -> 1 | H73: =D73*G73 -> 7445.2
C74: Gyuniku Ala Carte | D74: =VLOOKUP(C74, 'LIST HPP'!$B$4:$C$39, 2, ) -> 17260 | E74: 0 | G74: =Sum(E74:F74) -> 0 | H74: =D74*G74 -> 0
C75: Karage Ala Carte | D75: =VLOOKUP(C75, 'LIST HPP'!$B$4:$C$39, 2, ) -> 14155 | E75: 0 | G75: =Sum(E75:F75) -> 0 | H75: =D75*G75 -> 0
C76: Hot Honey Karage Ala Carte | D76: =VLOOKUP(C76, 'LIST HPP'!$B$4:$C$39, 2, ) -> 15435 | E76: 0 | G76: =Sum(E76:F76) -> 0 | H76: =D76*G76 -> 0
... C93: Kaarage Bento | D93: =VLOOKUP(C93, 'LIST HPP'!$B$4:$C$39, 2, ) -> 12796.31 | E93: 0 | G93: =Sum(E93:F93) -> 0 | H93: =D93*G93 -> 0
C94: Gyuniku Bento | D94: =VLOOKUP(C94, 'LIST HPP'!$B$4:$C$39, 2, FALSE) -> 14616.31 | E94: 0 | G94: =Sum(E94:F94) -> 0 | H94: =D94*G94 -> 0
C95: Matcha Latte | D95: =VLOOKUP(C95, 'LIST HPP'!$B$4:$C$39, 2, FALSE) -> 8805.63 | G95: =sum(E95:F95) -> 0 | H95: =D95*G95 -> 0 | I95: =sum(H95:H125) -> 0 | K95: =(J95-I95)/J95 -> #DIV/0! | L95: =J95-I95 -> 0
C96: Hojicha Latte | D96: =VLOOKUP(C96, 'LIST HPP'!$B$4:$C$39, 2, FALSE) -> 8150.63 | G96: =sum(E96:F96) -> 0 | H96: =D96*G96 -> 0
C97: Choco Latte | D97: =VLOOKUP(C97, 'LIST HPP'!$B$4:$C$39, 2, FALSE) -> 6013.63 | G97: =sum(E97:F97) -> 0 | H97: =D97*G97 -> 0
C98: Choco Ichigo Latte | D98: =VLOOKUP(C98, 'LIST HPP'!$B$4:$C$39, 2, FALSE) -> 7131.43 | G98: =sum(E98:F98) -> 0 | H98: =D98*G98 -> 0
C99: Matcha Tea | D99: =VLOOKUP(C99, 'LIST HPP'!$B$4:$C$39, 2, FALSE) -> 3748.21 | G99: =sum(E99:F99) -> 0 | H99: =D99*G99 -> 0
C100: Ice Tea | D100: =VLOOKUP(C100, 'LIST HPP'!$B$4:$C$39, 2, FALSE) -> 1448.63 | G100: =sum(E100:F100) -> 0 | H100: =D100*G100 -> 0
C101: Gyumeshi | D101: =VLOOKUP(C101, 'LIST HPP'!$B$4:$C$39, 2, FALSE) -> 11670 | G101: =sum(E101:F101) -> 0 | H101: =D101*G101 -> 0
C102: Karage Don | D102: =VLOOKUP(C102, 'LIST HPP'!$B$4:$C$39, 2, FALSE) -> 9350.16 | G102: =sum(E102:F102) -> 0 | H102: =D102*G102 -> 0
C103: Hot Honey Karage Don | D103: =VLOOKUP(C103, 'LIST HPP'!$B$4:$C$39, 2, FALSE) -> 9990.16 | G103: =sum(E103:F103) -> 0 | H103: =D103*G103 -> 0
C104: Chicken Katsu Don | D104: =VLOOKUP(C104, 'LIST HPP'!$B$4:$C$39, 2, FALSE) -> 7445.2 | G104: =sum(E104:F104) -> 0 | H104: =D104*G104 -> 0
C105: Gyuniku Ala Carte | D105: =VLOOKUP(C105, 'LIST HPP'!$B$4:$C$39, 2, FALSE) -> 17260 | G105: =sum(E105:F105) -> 0 | H105: =D105*G105 -> 0
C106: Karage Ala Carte | D106: =VLOOKUP(C106, 'LIST HPP'!$B$4:$C$39, 2, FALSE) -> 14155 | G106: =sum(E106:F106) -> 0 | H106: =D106*G106 -> 0
C107: Hot Honey Karage Ala Carte | D107: =VLOOKUP(C107, 'LIST HPP'!$B$4:$C$39, 2, FALSE) -> 15435 | G107: =sum(E107:F107) -> 0 | H107: =D107*G107 -> 0
... C125: Gyuniku Bento | D125: =VLOOKUP(C125, 'LIST HPP'!$B$4:$C$39, 2, FALSE) -> 14616.31 | G125: =sum(E125:F125) -> 0 | H125: =D125*G125 -> 0
B126: =#REF! -> #REF! | I126: =SUM(I2:I125) -> 828601.37 | J126: =SUM(J2:J125) -> 1571538 | L126: =SUM(L2:L125) -> 742936.63
A128: Stock Opname Inventory | I128: TOTAL JUMLAH ITEM TERJUAL
A129: Menu | B129: No | F129: Data Penjualan
C130: Bahan | D130: Berat | E130: Satuan | F130: Porsi | G130: Total Bahan Terpakai
A131: Gyumeshi | B131: 1 | C131: Daging Blackpepper | D131: 70 | E131: gr | F131: =VLOOKUP(A131, '12062026'!$I$130:$J$158, 2, ) -> 2 | G131: =D131*F131 -> 140
B132: 2 | C132: Bowl Mangkok | D132: 1 | E132: pcs | G132: =D132*F131 -> 2
B133: 3 | C133: Tutup Mangkok | D133: 1 | E133: pcs | G133: =D133*F131 -> 2
B134: 4 | C134: inner tray bowl | D134: 1 | E134: pcs | G134: =D134*F131 -> 2
B135: 5 | C135: Nasi Putih | D135: 180 | E135: gr | G135: =D135*F131 -> 360
A136: Karage Don | B136: 1 | C136: Ayam Karage | D136: 130 | E136: gr | F136: =VLOOKUP(A136, '12062026'!$I$130:$J$158, 2, ) -> 5 | G136: =D136*F136 -> 650
B137: 2 | C137: Bowl Mangkok | D137: 1 | E137: pcs | G137: =D137*F136 -> 5
B138: 3 | C138: Tutup Mangkok | D138: 1 | E138: pcs | G138: =D138*F136 -> 5
B139: 4 | C139: Nasi Putih | D139: 180 | E139: gr | G139: =D139*F136 -> 900
A140: Hot Honey Karage Don | B140: 1 | C140: Ayam Karage | D140: 130 | E140: gr | F140: =VLOOKUP(A140, '12062026'!$I$130:$J$158, 2, ) -> 2 | G140: =D140*F140 -> 260
B141: 2 | C141: Bowl Mangkok | D141: 1 | E141: pcs | G141: =D141*F140 -> 2
B142: 3 | C142: Tutup Mangkok | D142: 1 | E142: pcs | G142: =D142*F140 -> 2
B143: 4 | C143: Nasi Putih | D143: 180 | E143: gr | G143: =D143*F140 -> 360
B144: 5 | C144: Hot Honey Sauce | D144: 20 | E144: gr | G144: =D144*F140 -> 40
A145: Gyuniku Ala Carte | B145: 1 | C145: Daging Blackpepper | D145: 140 | E145: gr | F145: =VLOOKUP(A145, '12062026'!$I$130:$J$158, 2, ) -> 0 | G145: =D145*F145 -> 0
B146: 2 | C146: thinwall 500ml | D146: 1 | E146: pcs | G146: =D146*F145 -> 0
A147: Karage Ala Carte | B147: 1 | C147: Ayam Karage | D147: 260 | E147: gr | F147: =VLOOKUP(A147, '12062026'!$I$130:$J$158, 2, ) -> 2 | G147: =D147*F147 -> 520
B148: 2 | C148: Bowl Mangkok | D148: 1 | E148: pcs | G148: =D148*F147 -> 2
B149: 3 | C149: Tutup Mangkok | D149: 1 | E149: pcs | G149: =D149*F147 -> 2
A150: Hot Honey Karage Ala Carte | B150: 1 | C150: Ayam Karage | D150: 260 | E150: gr | F150: =VLOOKUP(A150, '12062026'!$I$130:$J$158, 2, ) -> 2 | G150: =D150*F150 -> 520
B151: 2 | C151: Bowl Mangkok | D151: 1 | E151: pcs | G151: =D151*F150 -> 2
B152: 3 | C152: Tutup Mangkok | D152: 1 | E152: pcs | G152: =D152*F150 -> 2
B153: 4 | C153: Hot Honey Sauce | D153: 40 | E153: gr | G153: =D153*F150 -> 80
A154: Curry Karage Don | B154: 1 | C154: Ayam Karage | D154: 130 | E154: porsi | F154: =VLOOKUP(A154, '12062026'!$I$130:$J$158, 2, ) -> 0 | G154: =D154*F154 -> 0
B155: 2 | C155: Bowl Mangkok | D155: 1 | E155: pcs | G155: =D155*F154 -> 0
B156: 3 | C156: Tutup Mangkok | D156: 1 | E156: pcs | G156: =D156*F154 -> 0
B157: 4 | C157: Nasi Putih | D157: 180 | E157: gr | G157: =D157*F154 -> 0
B158: 5 | C158: Curry Sauce | D158: 1 | E158: pcs | G158: =D158*F154 -> 0
A159: Curry Omurice | B159: 1 | C159: Telor Ayam | D159: 2 | E159: pcs | F159: =VLOOKUP(A159, '12062026'!$I$130:$J$158, 2, ) -> 9 | G159: =D159*F159 -> 18
B160: 2 | C160: Bowl Mangkok | D160: 1 | E160: pcs | G160: =D160*F159 -> 9
B161: 3 | C161: Tutup Mangkok | D161: 1 | E161: pcs | G161: =D161*F159 -> 9
B162: 4 | C162: Nasi Putih | D162: 180 | E162: gr | G162: =D162*F159 -> 1620
B163: 5 | C163: Curry Sauce | D163: 1 | E163: pcs | G163: =D163*F159 -> 9
B164: 6 | C164: Gula Pasir | D164: 3 | E164: gr | G164: =D164*F159 -> 27
B165: 7 | C165: Dashi Halal | D165: 3 | E165: gr | G165: =D165*F159 -> 27
B166: 8 | C166: Mirin Halal | D166: 5 | E166: gr | G166: =D166*F159 -> 45
A167: Miso Sup | B167: 1 | C167: miso soup | D167: 1 | E167: porsi | F167: =VLOOKUP(A167, '12062026'!$I$130:$J$158, 2, ) -> 12 | G167: =D167*F167 -> 12
B168: 2 | C168: daun bawang | D168: 1 | E168: Pcs | G168: =D168*F167 -> 12
...

Sheet 11062026
A1: PLATFORM | B1: Tanggal | C1: Nama Item | D1: HPP | E1: Jumlah | F1: Jumlah QR | G1: Total Jumlah | H1: Total | I1: Total HPP | J1: Uang Masuk | K1: Margin | L1: Gross Profit
A2: SHOPEE | C2: Matcha Latte | D2: =VLOOKUP(C2, 'LIST HPP'!$B$4:$C$39, 2, ) -> 8805.63 | E2: 0 | G2: =sum(E2:F2) -> 0 | H2: =D2*G2 -> 0 | I2: =sum(H2:H32) -> 226595.26 | J2: 337446 | K2: =(J2-I2)/J2 -> 0.3284992 | L2: =J2-I2 -> 110850.74
C3: Hojicha Latte | D3: =VLOOKUP(C3, 'LIST HPP'!$B$4:$C$39, 2, ) -> 8150.63 | E3: 0 | G3: =sum(E3:F3) -> 0 | H3: =D3*G3 -> 0
C4: Choco Latte | D4: =VLOOKUP(C4, 'LIST HPP'!$B$4:$C$39, 2, ) -> 6013.63 | E4: 0 | G4: =sum(E4:F4) -> 0 | H4: =D4*G4 -> 0
C5: Choco Ichigo Latte | D5: =VLOOKUP(C5, 'LIST HPP'!$B$4:$C$39, 2, ) -> 7131.43 | E5: 1 | G5: =sum(E5:F5) -> 1 | H5: =D5*G5 -> 7131.43
C6: Matcha Tea | D6: =VLOOKUP(C6, 'LIST HPP'!$B$4:$C$39, 2, ) -> 3748.21 | E6: 1 | G6: =sum(E6:F6) -> 1 | H6: =D6*G6 -> 3748.21
C7: Ice Tea | D7: =VLOOKUP(C7, 'LIST HPP'!$B$4:$C$39, 2, ) -> 1448.63 | E7: 8 | G7: =sum(E7:F7) -> 8 | H7: =D7*G7 -> 11589.04
C8: Gyumeshi | D8: =VLOOKUP(C8, 'LIST HPP'!$B$4:$C$39, 2, ) -> 11670 | E8: 2 | G8: =sum(E8:F8) -> 2 | H8: =D8*G8 -> 23340
C9: Karage Don | D9: =VLOOKUP(C9, 'LIST HPP'!$B$4:$C$39, 2, ) -> 9350.16 | E9: 5 | G9: =sum(E9:F9) -> 5 | H9: =D9*G9 -> 46750.8
C10: Hot Honey Karage Don | D10: =VLOOKUP(C10, 'LIST HPP'!$B$4:$C$39, 2, ) -> 9990.16 | E10: 1 | G10: =sum(E10:F10) -> 1 | H10: =D10*G10 -> 9990.16
C11: Chicken Katsu Don | D11: =VLOOKUP(C11, 'LIST HPP'!$B$4:$C$39, 2, ) -> 7445.2 | E11: 10 | G11: =sum(E11:F11) -> 10 | H11: =D11*G11 -> 74452
C12: Gyuniku Ala Carte | D12: =VLOOKUP(C12, 'LIST HPP'!$B$4:$C$39, 2, ) -> 17260 | E12: 0 | G12: =sum(E12:F12) -> 0 | H12: =D12*G12 -> 0
C13: Karage Ala Carte | D13: =VLOOKUP(C13, 'LIST HPP'!$B$4:$C$39, 2, ) -> 14155 | E13: 0 | G13: =sum(E13:F13) -> 0 | H13: =D13*G13 -> 0
C14: Hot Honey Karage Ala Carte | D14: =VLOOKUP(C14, 'LIST HPP'!$B$4:$C$39, 2, ) -> 15435 | E14: 0 | G14: =sum(E14:F14) -> 0 | H14: =D14*G14 -> 0
... C32: Gyuniku Bento | D32: =VLOOKUP(C32, 'LIST HPP'!$B$4:$C$39, 2, ) -> 14616.31 | E32: 0 | G32: =sum(E32:F32) -> 0 | H32: =D32*G32 -> 0
A33: GRAB/ OFFLINE Q | C33: Matcha Latte | D33: =VLOOKUP(C33, 'LIST HPP'!$B$4:$C$39, 2, ) -> 8805.63 | E33: 0 | F33: 0 | G33: =SUM(E33:F33) -> 0 | H33: =D33*G33 -> 0 | I33: =sum(H33:H63) -> 193022.66 | J33: 342083 | K33: =(J33-I33)/J33 -> 0.4357432 | L33: =J33-I33 -> 149060.34
C34: Hojicha Latte | D34: =VLOOKUP(C34, 'LIST HPP'!$B$4:$C$39, 2, ) -> 8150.63 | E34: 1 | F34: 0 | G34: =SUM(E34:F34) -> 1 | H34: =D34*G34 -> 8150.63
C35: Choco Latte | D35: =VLOOKUP(C35, 'LIST HPP'!$B$4:$C$39, 2, ) -> 6013.63 | E35: 1 | F35: 0 | G35: =SUM(E35:F35) -> 1 | H35: =D35*G35 -> 6013.63
C36: Choco Ichigo Latte | D36: =VLOOKUP(C36, 'LIST HPP'!$B$4:$C$39, 2, ) -> 7131.43 | E36: 0 | F36: 0 | G36: =SUM(E36:F36) -> 0 | H36: =D36*G36 -> 0
C37: Matcha Tea | D37: =VLOOKUP(C37, 'LIST HPP'!$B$4:$C$39, 2, ) -> 3748.21 | E37: 0 | F37: 0 | G37: =SUM(E37:F37) -> 0 | H37: =D37*G37 -> 0
C38: Ice Tea | D38: =VLOOKUP(C38, 'LIST HPP'!$B$4:$C$39, 2, ) -> 1448.63 | E38: 4 | F38: 0 | G38: =SUM(E38:F38) -> 4 | H38: =D38*G38 -> 5794.52
C39: Gyumeshi | D39: =VLOOKUP(C39, 'LIST HPP'!$B$4:$C$39, 2, ) -> 11670 | E39: 0 | F39: 0 | G39: =SUM(E39:F39) -> 0 | H39: =D39*G39 -> 0
C40: Karage Don | D40: =VLOOKUP(C40, 'LIST HPP'!$B$4:$C$39, 2, ) -> 9350.16 | E40: 0 | F40: 0 | G40: =SUM(E40:F40) -> 0 | H40: =D40*G40 -> 0
C41: Hot Honey Karage Don | D41: =VLOOKUP(C41, 'LIST HPP'!$B$4:$C$39, 2, ) -> 9990.16 | E41: 1 | F41: 0 | G41: =SUM(E41:F41) -> 1 | H41: =D41*G41 -> 9990.16
C42: Chicken Katsu Don | D42: =VLOOKUP(C42, 'LIST HPP'!$B$4:$C$39, 2, ) -> 7445.2 | E42: 4 | F42: 0 | G42: =SUM(E42:F42) -> 4 | H42: =D42*G42 -> 29780.8
C43: Gyuniku Ala Carte | D43: =VLOOKUP(C43, 'LIST HPP'!$B$4:$C$39, 2, ) -> 17260 | E43: 1 | F43: 0 | G43: =SUM(E43:F43) -> 1 | H43: =D43*G43 -> 17260
C44: Karage Ala Carte | D44: =VLOOKUP(C44, 'LIST HPP'!$B$4:$C$39, 2, ) -> 14155 | E44: 2 | F44: 0 | G44: =SUM(E44:F44) -> 2 | H44: =D44*G44 -> 28310
C45: Hot Honey Karage Ala Carte | D45: =VLOOKUP(C45, 'LIST HPP'!$B$4:$C$39, 2, ) -> 15435 | E45: 2 | F45: 0 | G45: =SUM(E45:F45) -> 2 | H45: =D45*G45 -> 30870
... C63: Gyuniku Bento | D63: =VLOOKUP(C63, 'LIST HPP'!$B$4:$C$39, 2, ) -> 14616.31 | E63: 0 | F63: 0 | G63: =SUM(E63:F63) -> 0 | H63: =D63*G63 -> 0
A64: GOJEK | C64: Matcha Latte | D64: =VLOOKUP(C64, 'LIST HPP'!$B$4:$C$39, 2, ) -> 8805.63 | E64: 0 | G64: =Sum(E64:F64) -> 0 | H64: =D64*G64 -> 0 | I64: =sum(H64:H94) -> 134454.55 | J64: 273811 | K64: =(J64-I64)/J64 -> 0.50895125 | L64: =J64-I64 -> 139356.45
C65: Hojicha Latte | D65: =VLOOKUP(C65, 'LIST HPP'!$B$4:$C$39, 2, ) -> 8150.63 | E65: 0 | G65: =Sum(E65:F65) -> 0 | H65: =D65*G65 -> 0
C66: Choco Latte | D66: =VLOOKUP(C66, 'LIST HPP'!$B$4:$C$39, 2, ) -> 6013.63 | E66: 1 | G66: =Sum(E66:F66) -> 1 | H66: =D66*G66 -> 6013.63
C67: Choco Ichigo Latte | D67: =VLOOKUP(C67, 'LIST HPP'!$B$4:$C$39, 2, ) -> 7131.43 | E67: 3 | G67: =Sum(E67:F67) -> 3 | H67: =D67*G67 -> 21394.29
C68: Matcha Tea | D68: =VLOOKUP(C68, 'LIST HPP'!$B$4:$C$39, 2, ) -> 3748.21 | E68: 0 | G68: =Sum(E68:F68) -> 0 | H68: =D68*G68 -> 0
C69: Ice Tea | D69: =VLOOKUP(C69, 'LIST HPP'!$B$4:$C$39, 2, ) -> 1448.63 | E69: 3 | G69: =Sum(E69:F69) -> 3 | H69: =D69*G69 -> 4345.89
C70: Gyumeshi | D70: =VLOOKUP(C70, 'LIST HPP'!$B$4:$C$39, 2, ) -> 11670 | E70: 0 | G70: =Sum(E70:F70) -> 0 | H70: =D70*G70 -> 0
C71: Karage Don | D71: =VLOOKUP(C71, 'LIST HPP'!$B$4:$C$39, 2, ) -> 9350.16 | E71: 2 | G71: =Sum(E71:F71) -> 2 | H71: =D71*G71 -> 18700.32
C72: Hot Honey Karage Don | D72: =VLOOKUP(C72, 'LIST HPP'!$B$4:$C$39, 2, ) -> 9990.16 | E72: 3 | G72: =Sum(E72:F72) -> 3 | H72: =D72*G72 -> 29970.48
C73: Chicken Katsu Don | D73: =VLOOKUP(C73, 'LIST HPP'!$B$4:$C$39, 2, ) -> 7445.2 | E73: 3 | G73: =Sum(E73:F73) -> 3 | H73: =D73*G73 -> 22335.6
C74: Gyuniku Ala Carte | D74: =VLOOKUP(C74, 'LIST HPP'!$B$4:$C$39, 2, ) -> 17260 | E74: 0 | G74: =Sum(E74:F74) -> 0 | H74: =D74*G74 -> 0
C75: Karage Ala Carte | D75: =VLOOKUP(C75, 'LIST HPP'!$B$4:$C$39, 2, ) -> 14155 | E75: 0 | G75: =Sum(E75:F75) -> 0 | H75: =D75*G75 -> 0
C76: Hot Honey Karage Ala Carte | D76: =VLOOKUP(C76, 'LIST HPP'!$B$4:$C$39, 2, ) -> 15435 | E76: 0 | G76: =Sum(E76:F76) -> 0 | H76: =D76*G76 -> 0
... C93: Kaarage Bento | D93: =VLOOKUP(C93, 'LIST HPP'!$B$4:$C$39, 2, ) -> 12796.31 | E93: 0 | G93: =Sum(E93:F93) -> 0 | H93: =D93*G93 -> 0
C94: Gyuniku Bento | D94: =VLOOKUP(C94, 'LIST HPP'!$B$4:$C$39, 2, FALSE) -> 14616.31 | E94: 0 | G94: =Sum(E94:F94) -> 0 | H94: =D94*G94 -> 0
C95: Matcha Latte | D95: =VLOOKUP(C95, 'LIST HPP'!$B$4:$C$39, 2, FALSE) -> 8805.63 | G95: =sum(E95:F95) -> 0 | H95: =D95*G95 -> 0 | I95: =sum(H95:H125) -> 0 | K95: =(J95-I95)/J95 -> #DIV/0! | L95: =J95-I95 -> 0
C96: Hojicha Latte | D96: =VLOOKUP(C96, 'LIST HPP'!$B$4:$C$39, 2, FALSE) -> 8150.63 | G96: =sum(E96:F96) -> 0 | H96: =D96*G96 -> 0
C97: Choco Latte | D97: =VLOOKUP(C97, 'LIST HPP'!$B$4:$C$39, 2, FALSE) -> 6013.63 | G97: =sum(E97:F97) -> 0 | H97: =D97*G97 -> 0
C98: Choco Ichigo Latte | D98: =VLOOKUP(C98, 'LIST HPP'!$B$4:$C$39, 2, FALSE) -> 7131.43 | G98: =sum(E98:F98) -> 0 | H98: =D98*G98 -> 0
C99: Matcha Tea | D99: =VLOOKUP(C99, 'LIST HPP'!$B$4:$C$39, 2, FALSE) -> 3748.21 | G99: =sum(E99:F99) -> 0 | H99: =D99*G99 -> 0
C100: Ice Tea | D100: =VLOOKUP(C100, 'LIST HPP'!$B$4:$C$39, 2, FALSE) -> 1448.63 | G100: =sum(E100:F100) -> 0 | H100: =D100*G100 -> 0
C101: Gyumeshi | D101: =VLOOKUP(C101, 'LIST HPP'!$B$4:$C$39, 2, FALSE) -> 11670 | G101: =sum(E101:F101) -> 0 | H101: =D101*G101 -> 0
C102: Karage Don | D102: =VLOOKUP(C102, 'LIST HPP'!$B$4:$C$39, 2, FALSE) -> 9350.16 | G102: =sum(E102:F102) -> 0 | H102: =D102*G102 -> 0
C103: Hot Honey Karage Don | D103: =VLOOKUP(C103, 'LIST HPP'!$B$4:$C$39, 2, FALSE) -> 9990.16 | G103: =sum(E103:F103) -> 0 | H103: =D103*G103 -> 0
C104: Chicken Katsu Don | D104: =VLOOKUP(C104, 'LIST HPP'!$B$4:$C$39, 2, FALSE) -> 7445.2 | G104: =sum(E104:F104) -> 0 | H104: =D104*G104 -> 0
C105: Gyuniku Ala Carte | D105: =VLOOKUP(C105, 'LIST HPP'!$B$4:$C$39, 2, FALSE) -> 17260 | G105: =sum(E105:F105) -> 0 | H105: =D105*G105 -> 0
C106: Karage Ala Carte | D106: =VLOOKUP(C106, 'LIST HPP'!$B$4:$C$39, 2, FALSE) -> 14155 | G106: =sum(E106:F106) -> 0 | H106: =D106*G106 -> 0
C107: Hot Honey Karage Ala Carte | D107: =VLOOKUP(C107, 'LIST HPP'!$B$4:$C$39, 2, FALSE) -> 15435 | G107: =sum(E107:F107) -> 0 | H107: =D107*G107 -> 0
... C125: Gyuniku Bento | D125: =VLOOKUP(C125, 'LIST HPP'!$B$4:$C$39, 2, FALSE) -> 14616.31 | G125: =sum(E125:F125) -> 0 | H125: =D125*G125 -> 0
B126: =#REF! -> #REF! | I126: =SUM(I2:I125) -> 554072.47 | J126: =SUM(J2:J125) -> 953340 | L126: =SUM(L2:L125) -> 399267.53
A128: Stock Opname Inventory | I128: TOTAL JUMLAH ITEM TERJUAL
A129: Menu | B129: No | F129: Data Penjualan
C130: Bahan | D130: Berat | E130: Satuan | F130: Porsi | G130: Total Bahan Terpakai
A131: Gyumeshi | B131: 1 | C131: Daging Blackpepper | D131: 70 | E131: gr | F131: =VLOOKUP(A131, '11062026'!$I$130:$J$158, 2, ) -> 2 | G131: =D131*F131 -> 140
B132: 2 | C132: Bowl Mangkok | D132: 1 | E132: pcs | G132: =D132*F131 -> 2
B133: 3 | C133: Tutup Mangkok | D133: 1 | E133: pcs | G133: =D133*F131 -> 2
B134: 4 | C134: inner tray bowl | D134: 1 | E134: pcs | G134: =D134*F131 -> 2
B135: 5 | C135: Nasi Putih | D135: 180 | E135: gr | G135: =D135*F131 -> 360
A136: Karage Don | B136: 1 | C136: Ayam Karage | D136: 130 | E136: gr | F136: =VLOOKUP(A136, '11062026'!$I$130:$J$158, 2, ) -> 7 | G136: =D136*F136 -> 910
B137: 2 | C137: Bowl Mangkok | D137: 1 | E137: pcs | G137: =D137*F136 -> 7
B138: 3 | C138: Tutup Mangkok | D138: 1 | E138: pcs | G138: =D138*F136 -> 7
B139: 4 | C139: Nasi Putih | D139: 180 | E139: gr | G139: =D139*F136 -> 1260
A140: Hot Honey Karage Don | B140: 1 | C140: Ayam Karage | D140: 130 | E140: gr | F140: =VLOOKUP(A140, '11062026'!$I$130:$J$158, 2, ) -> 5 | G140: =D140*F140 -> 650
B141: 2 | C141: Bowl Mangkok | D141: 1 | E141: pcs | G141: =D141*F140 -> 5
B142: 3 | C142: Tutup Mangkok | D142: 1 | E142: pcs | G142: =D142*F140 -> 5
B143: 4 | C143: Nasi Putih | D143: 180 | E143: gr | G143: =D143*F140 -> 900
B144: 5 | C144: Hot Honey Sauce | D144: 20 | E144: gr | G144: =D144*F140 -> 100
A145: Gyuniku Ala Carte | B145: 1 | C145: Daging Blackpepper | D145: 140 | E145: gr | F145: =VLOOKUP(A145, '11062026'!$I$130:$J$158, 2, ) -> 1 | G145: =D145*F145 -> 140
B146: 2 | C146: thinwall 500ml | D146: 1 | E146: pcs | G146: =D146*F145 -> 1
A147: Karage Ala Carte | B147: 1 | C147: Ayam Karage | D147: 260 | E147: gr | F147: =VLOOKUP(A147, '11062026'!$I$130:$J$158, 2, ) -> 2 | G147: =D147*F147 -> 520
B148: 2 | C148: Bowl Mangkok | D148: 1 | E148: pcs | G148: =D148*F147 -> 2
B149: 3 | C149: Tutup Mangkok | D149: 1 | E149: pcs | G149: =D149*F147 -> 2
A150: Hot Honey Karage Ala Carte | B150: 1 | C150: Ayam Karage | D150: 260 | E150: gr | F150: =VLOOKUP(A150, '11062026'!$I$130:$J$158, 2, ) -> 2 | G150: =D150*F150 -> 520
B151: 2 | C151: Bowl Mangkok | D151: 1 | E151: pcs | G151: =D151*F150 -> 2
B152: 3 | C152: Tutup Mangkok | D152: 1 | E152: pcs | G152: =D152*F150 -> 2
B153: 4 | C153: Hot Honey Sauce | D153: 40 | E153: gr | G153: =D153*F150 -> 80
A154: Curry Karage Don | B154: 1 | C154: Ayam Karage | D154: 130 | E154: porsi | F154: =VLOOKUP(A154, '11062026'!$I$130:$J$158, 2, ) -> 0 | G154: =D154*F154 -> 0
B155: 2 | C155: Bowl Mangkok | D155: 1 | E155: pcs | G155: =D155*F154 -> 0
B156: 3 | C156: Tutup Mangkok | D156: 1 | E156: pcs | G156: =D156*F154 -> 0
B157: 4 | C157: Nasi Putih | D157: 180 | E157: gr | G157: =D157*F154 -> 0
B158: 5 | C158: Curry Sauce | D158: 1 | E158: pcs | G158: =D158*F154 -> 0
A159: Curry Omurice | B159: 1 | C159: Telor Ayam | D159: 2 | E159: pcs | F159: =VLOOKUP(A159, '11062026'!$I$130:$J$158, 2, ) -> 3 | G159: =D159*F159 -> 6
B160: 2 | C160: Bowl Mangkok | D160: 1 | E160: pcs | G160: =D160*F159 -> 3
B161: 3 | C161: Tutup Mangkok | D161: 1 | E161: pcs | G161: =D161*F159 -> 3
B162: 4 | C162: Nasi Putih | D162: 180 | E162: gr | G162: =D162*F159 -> 540
B163: 5 | C163: Curry Sauce | D163: 1 | E163: pcs | G163: =D163*F159 -> 3
B164: 6 | C164: Gula Pasir | D164: 3 | E164: gr | G164: =D164*F159 -> 9
B165: 7 | C165: Dashi Halal | D165: 3 | E165: gr | G165: =D165*F159 -> 9
B166: 8 | C166: Mirin Halal | D166: 5 | E166: gr | G166: =D166*F159 -> 15
A167: Miso Sup | B167: 1 | C167: miso soup | D167: 1 | E167: porsi | F167: =VLOOKUP(A167, '11062026'!$I$130:$J$158, 2, ) -> 5 | G167: =D167*F167 -> 5
B168: 2 | C168: daun bawang | D168: 1 | E168: Pcs | G168: =D168*F167 -> 5
...

Sheet 10062026
A1: PLATFORM | B1: Tanggal | C1: Nama Item | D1: HPP | E1: Jumlah | F1: Jumlah QR | G1: Total Jumlah | H1: Total | I1: Total HPP | J1: Uang Masuk | K1: Margin | L1: Gross Profit
